Workbook
Name a: #REF!
Name Comprobantes: '[1]Tabla de Comprobantes'!$A$3:$A$65
Name Fletes_MX: Fletes!$A$1:$G$18
Name Fletes_Tab: Fletes!$A$5:$G$17
Name Mobiliario: Fletes!$I$6:$I$19
Name PC: '[1]Tabla de Comprobantes'!$E$3:$E$14
Name Proveedores: Proveedores!$A$2:$D$32
Name ProveedoreS_TC: Proveedores!$A$2:$E$32
Name Taba_Region: Fletes!$G$5:$G$18
Name Tabla_Costos: Fletes!$D$5:$F$18
Name Tabla_Fletes: Fletes!$I$6:$K$19
Name Tabla_Instalacion: Fletes!$M$6:$N$19
Name Tabla_Proveedores: Proveedores!$A$29:$B$37
Name Tabla_Proveedores_1: Proveedores!$A$2:$B$32

Sheet Cotizacion
A3: COTIZACION # | B3: 400-19383
A4: =TODAY() -> 46163
A7: PROYECTO:
A8: Nombre:
A9: Correo:
A10: Telefono:
A11: Direccion:
A12: Razon Social:
A15: CÓDIGO | B15: IMAGEN | C15: DESCRIPCIÓN | D15: MEDIDAS | E15: CANT. | F15: P. UNIT | G15: % DESC. | H15: DESCUENTO | I15: SUBTOTAL | J15: TOTAL
E17: 0 | G17: 0 | H17: =F17*G17 -> 0 | I17: =F17-H17 -> 0 | J17: =E17*I17 -> 0 | L17: =1400/5 -> 280 | O17: 483441.6 | P17: =O17*3% -> 14503.248
G18: 0 | H18: =F18*G18 -> 0 | I18: =F18-H18 -> 0 | J18: =E18*I18 -> 0 | P18: 19774
G19: 0 | H19: =F19*G19 -> 0 | I19: =F19-H19 -> 0 | J19: =E19*I19 -> 0 | P19: =SUM(P17:P18) -> 34277.248
G20: 0 | H20: =F20*G20 -> 0 | I20: =F20-H20 -> 0 | J20: =E20*I20 -> 0
D21: SUBTOTAL: | H21: {=SUM(IFERROR(J17:J20,0))} -> 0
D22: COSTO DE FLETE: | H22: =H21*10% -> 0 | P22: =#REF!-P19 -> #REF!
D23: SUBTOTAL: | H23: =H21+H22 -> 0
D24: IVA: | H24: =H23*16% -> 0
D25: TOTAL: | H25: =H23+H24 -> 0
A29: SHOWROOM Av. México No. 2501, Vallarta Norte, C.P. 44690, Guadalajara Jal | D29: WWW.MOBILITI.MX
A32: CONDICIONES
A33: 1) CONDICIONES COMERCIALES
A34: a. Esta cotización se encuentra en Dolares estadonidenses USD . En caso de que el pago se efectúe en una moneda diferente a la de este documento, se tomará como referencia el tipo de cambio bancario.
A35: b. Las cantidades mencionadas en esta cotización están calculadas sobre las tarifas arancelarias que se encuentran vigentes a la fecha de este documento. Dichas cantidades están sujetas a cambio conforme a actualizaciones que pueda haber en dichas tarifas.
A36: c. Los precios otorgados están basados en la compra del proyecto completo y la entrega en una sola etapa. En caso de requerir más de una entrega o las cantidades o artículos de esta cotización sean cambiados, los precios y descuentos mencionados anteriormente pueden variar.
A37: d. Las condiciones de pago son: 1- Pago 60% Anticipo + 20% Contra Aviso de Embarque + 20% Contra Entrega.
A38: e. En caso de que no se cumplan las condiciones de pago anteriormente mencionadas, se cobrará el 3% sobre el saldo total de esta cotización por cada mes de atraso o fracción.
A39: f. En caso de que, por motivos ajenos a Espacios Corporativos y de Diseño Jofe, SA de CV, no pueda ser entregado el producto de un proyecto, esto no limita el cobro del mismo. En el caso de que se entreguen dañados uno o más productos o componentes de los mismos, por transporte, manejo, instalación, defecto de fábrica, o bien por error de especificación imputable a nuestros representantes, se procederá a reparar dichos daños o a solicitar sus reposiciones. Sin embargo, esto no será motivo de retención de pago, únicamente podrá quedar pendiente el monto correspondiente al valor de esos productos y/o partes dañadas o faltantes.
A41: 2) PLAZO DE ENTREGA
A42: a. El plazo de entrega, en sitio, del producto mencionado en esta cotización es de 12 Semanas habiles despues de recibir anticipo y cotizacion firmada de Vobo con terminados Según Existencias
A43: b. Para que Espacios Corporativos y de Diseño Jofe, SA de CV, procese un pedido, se requieren del cliente los siguientes documentos firmados: orden de compra oficial o contrato, planos del layout (si aplica), presentación (si aplica), cotización con acabados definidos por el cliente, políticas de garantías y que se cumplan las condiciones de pago iniciales.
A44: c. Los plazos de entrega de nuestros productos dependen del volumen de producción de las plantas de fabricación, es por esto que pueden variar sin previo aviso.
... A73: c. Al recibir los documentos mencionados en el inciso 2-b, queda entendido que el cliente acepta incondicionalmente las presentes condiciones de venta y garantías. Renunciando este a cualquier tipo de reclamo que no esté estipulado en este documento.
A77: NOMBRE, FIRMA Y FECHA DE AUTORIZACIÓN DEL CLIENTE | D77: NOMBRE DE EJECUTIVO DE VENTAS
L122: =IF(ROUND(#REF!,2)=ROUND('Estrategia Comercial '!B69,2),"ESTRATEGIA CORRECTA","REVISA TU ESTRATEGIA") -> #REF!

Sheet sheep
A1: Price List
A3: Price to： | I3: contact： | J3: Lynn li
A4: Trade term: | C4: FOB GUANGZHOU PORT | I4: Submitted date： | J4: 46141
A5: address： | I5: Email | J5: lynnli@mexytech.com
A7: No. | B7: Series | C7: Name | D7: Photo | F7: Length/m | G7: Unit | H7: Price | I7: Total money | J7: Note | K7: ramon price with 10% commision
A8: 6 | B8: wpc | C8: 600V slot Bpanel | F8: 600*9*2950 | G8: sqm | H8: 4.774 | K8: =H8*1.1 -> 5.2514
A9: 7 | B9: wpc | C9: 160 slat panel | F9: 160*22*2900 | G9: sqm | H9: 7.29 | K9: =H9*1.1 -> 8.019
A10: 1 | B10: perfil aluminum | C10: 10cm shape duplex Thickness around 0.9 | F10: 3 | G10: meter | H10: 0.781 | K10: =H10*1.1 -> 0.8591
A11: 2 | B11: perfil aluminum | C11: 9cm shape closure Thickness around 0.6 | F11: 3 | G11: meter | H11: 0.671 | K11: =H11*1.1 -> 0.7381
A12: 3 | B12: perfil aluminum | C12: 9cm shape duplex Thickness around 0.9 | F12: 3 | G12: meter | H12: 0.891 | K12: =H12*1.1 -> 0.9801
A13: 4 | B13: perfil aluminum | C13: 9cm I-shaped light strip (including lampshade) Thickness around 0.6 | F13: 3 | G13: meter | H13: 1.001 | K13: =H13*1.1 -> 1.1011
A14: 5 | B14: perfil aluminum | C14: 9 centimeter pointed yang angle Thickness around 0.85 | F14: 3 | G14: meter | H14: 1.023 | K14: =H14*1.1 -> 1.1253
A15: 8 | B15: perfil aluminum | C15: 10cm shape I-beam Thickness around 0.6 | F15: 3 | G15: meter | H15: 0.561 | K15: =H15*1.1 -> 0.6171
A16: 9 | B16: perfil aluminum | C16: 10cm shape closure Thickness around 0.6 | F16: 3 | G16: meter | H16: 0.561 | K16: =H16*1.1 -> 0.6171
A17: 10 | B17: perfil aluminum | C17: 10cm shape duplex Thickness around 0.9 | F17: 3 | G17: meter | H17: 0.671 | K17: =H17*1.1 -> 0.7381
A18: 11 | B18: perfil aluminum | C18: 10cm I-shaped light strip (including lampshade) Thickness around 0.6 | F18: 3 | G18: meter | H18: 1.001 | K18: =H18*1.1 -> 1.1011
A19: 12 | B19: perfil aluminum | C19: 10 centimeter pointed yang angle Thickness around 0.5 | F19: 3 | G19: meter | H19: 0.671 | K19: =H19*1.1 -> 0.7381

Sheet Mobiliti
J2: SELECCIONAR SI LA COTIZACIÓN ESTARÁ EN MXN O USD
A3: Estrategia Descuentos vs GP | AA3: PRECIO CLIENTE O INTERMEDIARIO CUANDO APLIQUE | AH3: BUSCAR QUE SIEMPRE ESTE "OK"
A4: Precio TOTAL de Venta | E4: =AC573 -> 0 | J4: DÓLARES | K4: TRUE | U4: PRIMER PRECIO CARÁTULA
A5: Descuento: | Y5: OJO: BUSCAR EL NO DAR EL MÁXIMO DESCUENTO DE INICIO PARA TENER PODER DE NEGOCIACIÓN
A6: Subtotal: | E6: =E4*E5 -> 0 | J6: #VALUE! | K6: {=_FV(J6,"High")} -> 17.375
A8: GP COMERCIAL DE ESTA SECCIÓN | E8: =(AC573-M573)/AC573 -> #DIV/0! | J8: Lugar de entrega: | K8: #VALUE! | P8: {=IFERROR(_xlfn.XLOOKUP(K8,Fletes!C5:C17,Fletes!D5:F17),"No encontrado")} -> 37000 | Q8: 0 | R8: 0
P9: =P8/H573 -> #DIV/0!
A10: Instrucciones: Llenar SOLAMENTE las celdas en AMARILLO que apliquen.
A11: Intermediario | B11: NA | C11: Tipo de Moneda a Cotizar | D11: Código de Producto | E11: Producto | F11: Proveedor | G11: Código de Proveedor | H11: Cantidad | I11: CÁLCULO COSTO | W11: PRECIO DE VENTA | AT11: =IF(F15="Requiez",W15<=$AM$577,IF(F15="Labenze",W15<=$AM$578,IF(F15="Infinity",W15<=$AL$579,IF(F15="Offiho",W15<=$AL$580,IF(F15="MetalWork",W15<=$AL$581,IF(F15="Jome",W15<=$AL$582,IF(F15="Sunon Inc",W15<=$AL$583,IF(F15="Vandesk",W15<=$AL$584,IF(F15="Conceptos",W15<=$AL$585,IF(F15="Tarkett",W15<=$AL$586,IF(F15="Tarkett Stock",W15<=$AL$587,IF(F15="Tarkett Europa",W15<=$AL$588,IF(F15="Tarkett - Santeco /Nva.Ave",W15<=$AL$589,IF(F15="Lumbro",W15<=$AL$590,IF(F15="Cristales",W15<=$AL$591,IF(F15="Sunon Mty",W15<=$AL$592,IF(F15="Leds",W15<=$AL$593,IF(F15="Herrajes",W15<=$AL$594,IF(F15="Acabados",W15<=$AL$595,IF(F15="Andreu World",W15<=$AL$596,IF(F15="Lauco",W15<=$AL$597,IF(F15="Mamparas",W15<=$AL$598)))))))))))))))))))))) -> FALSE
I12: Descuento Proveedor | J12: Costo Unitario | K12: M3 | L12: M3 TOTALES | M12: Costo Unitario Real | N12: Costo Total | O12: % Margen | P12: Región | Q12: Flete | R12: Flete | S12: Instalación | T12: Instalación | U12: Flete + Instalación | V12: Flete + Instalación | W12: Precio Unitario de Lista (Carátula) | X12: Precio Lista | Y12: Descuento Máximo | Z12: Descuento Carátula | AA12: Precio Descontado | AB12: Precio Final c/ Descuento | AC12: Precio Total Comercial | AD12: Descuento Carátula Cliente Final | AE12: Precio Cliente con Ajuste | AF12: Precio Total Proyecto | AG12: GP COMERCIAL | AU12: NOTA: ESTE ES EL SUBTOTAL ANTES DE FLETE, INSTALACIÓN E IVA
A13: TRUE | C13: Dólares | D13: Sección 1 - NOMBRE
A14: =$A$13 -> TRUE | B14: =A14 -> TRUE | C14: =C13 -> Dólares | G14: =IFERROR(VLOOKUP(F14,Tabla_Proveedores_1,2,0)," ") | H14: 0 | I14: =IFERROR(VLOOKUP(G14,Proveedores!B:C,2,0)," ") | J14: 0 | K14: 0 | L14: =K14*H14 -> 0 | M14: =IF(F14="Offiho", J14*0.55, IF(AND(F14<>"Sunon Inc",F14<>"Alma - Exterior",F14<>"Yabo - Hotelería",F14<>"OSJ - Medical",F14<>"Seezo - Home",F14<>"A&D -Home",F14<>"Encore Alfombras Hoteleria Asia",F14<>"Zhong Xian - Leds",F14<>"Tarkett Europa",F14<>"2tec2",F14<>"Balsan Europa",F14<>"Armstrong Pisos USA",F14<>"Tarkett USA",F14<>"Tarkett Brasil"),J14,IFERROR(IF(K573<=$AO$578,J14*2.14,IF(K573<=$AN$579,J14*1.8,IF(K573>$AN$580,J14*1.5))),J14))*1.1) -> 0 | N14: =M14*H14 -> 0 | O14: =IFERROR(VLOOKUP(G14,Proveedores!B:D,3,0)," ") | Q14: =VLOOKUP(E14,Tabla_Fletes,3,FALSE) -> #N/A | R14: =IF(P14="Centro",Q14,IF(P14="Norte",Q14*1.6,IF(P14="Occidente",Q14*1.2,IF(P14="Sur",Q14*2)))) -> FALSE | S14: =VLOOKUP(E14,Tabla_Instalacion,2,FALSE) -> #N/A | T14: =IF(P14="Centro",S14,IF(P14="Norte",S14*1.1,IF(P14="Occidente",S14*1.1,IF(P14="Sur",S14*1.1)))) -> FALSE | U14: =IF(F14="Offiho",0,R14+T14) -> 0 | V14: =IF(K14=0,U14/$H$573,U14*(K14/L14))*H14 -> #DIV/0! | W14: =IF(F14="Offiho",J14,IF(_xlfn.XLOOKUP(F14,Proveedores!A$2:A$50,Proveedores!E$2:E$50,"")="Nacional",(J14/0.5)+(V14*H14),((J14/0.3/0.5)+(V14*H14)))) -> #DIV/0! | X14: =(W14*H14) -> #DIV/0! | Y14: =IF(F14="Sunon Inc",$AJ$577,IF(F14="Alma - Exterior",$AJ$578,IF(F14="Yabo - Hotelería",$AJ$579,IF(F14="OSJ - Medical",$AJ$580,IF(F14="Seezo - Home",$AJ$581,IF(F14="A&D - Home",$AJ$582,IF(F14="Encore Alfombras Hoteleria Asia",$AJ$583,IF(F14="Zhong Xian - Leds",$AJ$584,IF(F14="Tarkett Europa",$AJ$585,IF(F14="2tec2",$AJ$586,IF(F14="Balsan Europa",$AJ$587,IF(F14="Armstrong Pisos USA",$AJ$588,IF(F14="Tarkett USA",$AJ$589,IF(F14="Tarkett Brasil",$AJ$590,IF(F14="Tarkett MX",$AJ$591,IF(F14="Jome",$AJ$592,IF(F14="Offiho",$AJ$593,IF(F14="Lumbro",$AJ$594,IF(F14="Sunon Mty",$AJ$595,IF(F14="Conceptos Sofas",$AJ$596,IF(F14="Lauco Sofas",$AJ$597,IF(F14="CR Global - Mesas Ajustables",$AJ$598,IF(F14="Vandesk",$AJ$599,IF(F14="Mamparas Tela",$AJ$600,IF(F14="Mampara Cristales",$AJ$601,IF(F14="Herrajes",$AJ$602,IF(F14="MetalWork",$AJ$603,IF(F14="Requiez",$AJ$604,IF(F14="Labenze",$AJ$605,IF(F14="Infinity",$AJ$606,IF(F14="Proveedor Externo",$AJ$607))))))))))))))))))))))))))))))) -> FALSE | Z14: 0.5 | AA14: =W14*Z14 -> #DIV/0! | AB14: =IF(Z14>Y14,"ERROR",(W14-AA14)) -> #DIV/0! | AC14: =AB14*H14 -> #DIV/0! | AD14: =IF(A15=TRUE,MAX(0,1-(AE14/W14)),"NA") -> #DIV/0! | AE14: =IF(A13=FALSE,"NO APLICA",AB14*1.2) -> #DIV/0! | AF14: =AE14*H14 -> #DIV/0! | AG14: =(AC14-N14)/AC14 -> #DIV/0! | AH14: =IF(AG14<30%,"ERROR","OK") -> #DIV/0! | AR14: TABLA DE ESQUEMA COMISION INTERMEDIARIO
A15: =$A$13 -> TRUE | B15: =A15 -> TRUE | C15: =$C$13 -> Dólares | G15: =IFERROR(VLOOKUP(F15,Tabla_Proveedores_1,2,0)," ") | H15: 0 | I15: =IFERROR(VLOOKUP(G15,Proveedores!B:C,2,0)," ") | J15: 0 | K15: 0 | L15: =K15*H15 -> 0 | M15: =IF(F15="Offiho", J15*0.55, IF(AND(F15<>"Sunon Inc",F15<>"Alma - Exterior",F15<>"Yabo - Hotelería",F15<>"OSJ - Medical",F15<>"Seezo - Home",F15<>"A&D -Home",F15<>"Encore Alfombras Hoteleria Asia",F15<>"Zhong Xian - Leds",F15<>"Tarkett Europa",F15<>"2tec2",F15<>"Balsan Europa",F15<>"Armstrong Pisos USA",F15<>"Tarkett USA",F15<>"Tarkett Brasil"),J15,IFERROR(IF(K574<=$AO$578,J15*2.14,IF(K574<=$AN$579,J15*1.8,IF(K574>$AN$580,J15*1.5))),J15))*1.1) -> 0 | N15: =M15*H15 -> 0 | O15: =IFERROR(VLOOKUP(G15,Proveedores!B:D,3,0)," ") | Q15: =VLOOKUP(E15,Tabla_Fletes,3,FALSE) -> #N/A | R15: =IF(P15="Centro",Q15,IF(P15="Norte",Q15*1.6,IF(P15="Occidente",Q15*1.2,IF(P15="Sur",Q15*2)))) -> FALSE | S15: =VLOOKUP(E15,Tabla_Instalacion,2,FALSE) -> #N/A | T15: =IF(P15="Centro",S15,IF(P15="Norte",S15*1.1,IF(P15="Occidente",S15*1.1,IF(P15="Sur",S15*1.1)))) -> FALSE | U15: =IF(F15="Offiho",0,R15+T15) -> 0 | V15: =IF(K15=0,U15/$H$573,U15*(K15/L15))*H15 -> #DIV/0! | W15: =IF(F15="Offiho",J15,IF(_xlfn.XLOOKUP(F15,Proveedores!A$2:A$50,Proveedores!E$2:E$50,"")="Nacional",(J15/0.5)+(V15*H15),((J15/0.3/0.5)+(V15*H15)))) -> #DIV/0! | X15: =(W15*H15) -> #DIV/0! | Y15: =IF(F15="Sunon Inc",$AJ$577,IF(F15="Alma - Exterior",$AJ$578,IF(F15="Yabo - Hotelería",$AJ$579,IF(F15="OSJ - Medical",$AJ$580,IF(F15="Seezo - Home",$AJ$581,IF(F15="A&D - Home",$AJ$582,IF(F15="Encore Alfombras Hoteleria Asia",$AJ$583,IF(F15="Zhong Xian - Leds",$AJ$584,IF(F15="Tarkett Europa",$AJ$585,IF(F15="2tec2",$AJ$586,IF(F15="Balsan Europa",$AJ$587,IF(F15="Armstrong Pisos USA",$AJ$588,IF(F15="Tarkett USA",$AJ$589,IF(F15="Tarkett Brasil",$AJ$590,IF(F15="Tarkett MX",$AJ$591,IF(F15="Jome",$AJ$592,IF(F15="Offiho",$AJ$593,IF(F15="Lumbro",$AJ$594,IF(F15="Sunon Mty",$AJ$595,IF(F15="Conceptos Sofas",$AJ$596,IF(F15="Lauco Sofas",$AJ$597,IF(F15="CR Global - Mesas Ajustables",$AJ$598,IF(F15="Vandesk",$AJ$599,IF(F15="Mamparas Tela",$AJ$600,IF(F15="Mampara Cristales",$AJ$601,IF(F15="Herrajes",$AJ$602,IF(F15="MetalWork",$AJ$603,IF(F15="Requiez",$AJ$604,IF(F15="Labenze",$AJ$605,IF(F15="Infinity",$AJ$606,IF(F15="Proveedor Externo",$AJ$607))))))))))))))))))))))))))))))) -> FALSE | Z15: 0.5 | AA15: =W15*Z15 -> #DIV/0! | AB15: =IF(Z15>Y15,"ERROR",(W15-AA15)) -> #DIV/0! | AC15: =AB15*H15 -> #DIV/0! | AD15: =IF(A16=TRUE,MAX(0,1-(AE15/W15)),"NA") -> #DIV/0! | AE15: =IF(A14=FALSE,"NO APLICA",AB15*1.2) -> #DIV/0! | AF15: =AE15*H15 -> #DIV/0! | AG15: =(AC15-N15)/AC15 -> #DIV/0! | AH15: =IF(AG15<30%,"ERROR","OK") -> #DIV/0! | AR15: Precio de Venta Base | AS15: =AC573 -> 0
A16: =$A$13 -> TRUE | B16: =A16 -> TRUE | C16: =$C$13 -> Dólares | G16: =IFERROR(VLOOKUP(F16,Tabla_Proveedores_1,2,0)," ") | H16: 0 | I16: =IFERROR(VLOOKUP(G16,Proveedores!B:C,2,0)," ") | J16: 0 | K16: 0 | L16: =K16*H16 -> 0 | M16: =IF(F16="Offiho", J16*0.55, IF(AND(F16<>"Sunon Inc",F16<>"Alma - Exterior",F16<>"Yabo - Hotelería",F16<>"OSJ - Medical",F16<>"Seezo - Home",F16<>"A&D -Home",F16<>"Encore Alfombras Hoteleria Asia",F16<>"Zhong Xian - Leds",F16<>"Tarkett Europa",F16<>"2tec2",F16<>"Balsan Europa",F16<>"Armstrong Pisos USA",F16<>"Tarkett USA",F16<>"Tarkett Brasil"),J16,IFERROR(IF(K575<=$AO$578,J16*2.14,IF(K575<=$AN$579,J16*1.8,IF(K575>$AN$580,J16*1.5))),J16))*1.1) -> 0 | N16: =M16*H16 -> 0 | O16: =IFERROR(VLOOKUP(G16,Proveedores!B:D,3,0)," ") | Q16: =VLOOKUP(E16,Tabla_Fletes,3,FALSE) -> #N/A | R16: =IF(P16="Centro",Q16,IF(P16="Norte",Q16*1.6,IF(P16="Occidente",Q16*1.2,IF(P16="Sur",Q16*2)))) -> FALSE | S16: =VLOOKUP(E16,Tabla_Instalacion,2,FALSE) -> #N/A | T16: =IF(P16="Centro",S16,IF(P16="Norte",S16*1.1,IF(P16="Occidente",S16*1.1,IF(P16="Sur",S16*1.1)))) -> FALSE | U16: =IF(F16="Offiho",0,R16+T16) -> 0 | V16: =IF(K16=0,U16/$H$573,U16*(K16/L16))*H16 -> #DIV/0! | W16: =IF(F16="Offiho",J16,IF(_xlfn.XLOOKUP(F16,Proveedores!A$2:A$50,Proveedores!E$2:E$50,"")="Nacional",(J16/0.5)+(V16*H16),((J16/0.3/0.5)+(V16*H16)))) -> #DIV/0! | X16: =(W16*H16) -> #DIV/0! | Y16: =IF(F16="Sunon Inc",$AJ$577,IF(F16="Alma - Exterior",$AJ$578,IF(F16="Yabo - Hotelería",$AJ$579,IF(F16="OSJ - Medical",$AJ$580,IF(F16="Seezo - Home",$AJ$581,IF(F16="A&D - Home",$AJ$582,IF(F16="Encore Alfombras Hoteleria Asia",$AJ$583,IF(F16="Zhong Xian - Leds",$AJ$584,IF(F16="Tarkett Europa",$AJ$585,IF(F16="2tec2",$AJ$586,IF(F16="Balsan Europa",$AJ$587,IF(F16="Armstrong Pisos USA",$AJ$588,IF(F16="Tarkett USA",$AJ$589,IF(F16="Tarkett Brasil",$AJ$590,IF(F16="Tarkett MX",$AJ$591,IF(F16="Jome",$AJ$592,IF(F16="Offiho",$AJ$593,IF(F16="Lumbro",$AJ$594,IF(F16="Sunon Mty",$AJ$595,IF(F16="Conceptos Sofas",$AJ$596,IF(F16="Lauco Sofas",$AJ$597,IF(F16="CR Global - Mesas Ajustables",$AJ$598,IF(F16="Vandesk",$AJ$599,IF(F16="Mamparas Tela",$AJ$600,IF(F16="Mampara Cristales",$AJ$601,IF(F16="Herrajes",$AJ$602,IF(F16="MetalWork",$AJ$603,IF(F16="Requiez",$AJ$604,IF(F16="Labenze",$AJ$605,IF(F16="Infinity",$AJ$606,IF(F16="Proveedor Externo",$AJ$607))))))))))))))))))))))))))))))) -> FALSE | Z16: 0.5 | AA16: =W16*Z16 -> #DIV/0! | AB16: =IF(Z16>Y16,"ERROR",(W16-AA16)) -> #DIV/0! | AC16: =AB16*H16 -> #DIV/0! | AD16: =IF(A17=TRUE,MAX(0,1-(AE16/W16)),"NA") -> #DIV/0! | AE16: =IF(A15=FALSE,"NO APLICA",AB16*1.2) -> #DIV/0! | AF16: =AE16*H16 -> #DIV/0! | AG16: =(AC16-N16)/AC16 -> #DIV/0! | AH16: =IF(AG16<30%,"ERROR","OK") -> #DIV/0! | AR16: Precio de Venta Final | AS16: =AF573 -> 0
A17: =$A$13 -> TRUE | B17: =A17 -> TRUE | C17: =$C$13 -> Dólares | G17: =IFERROR(VLOOKUP(F17,Tabla_Proveedores_1,2,0)," ") | H17: 0 | I17: =IFERROR(VLOOKUP(G17,Proveedores!B:C,2,0)," ") | J17: 0 | K17: 0 | L17: =K17*H17 -> 0 | M17: =IF(F17="Offiho", J17*0.55, IF(AND(F17<>"Sunon Inc",F17<>"Alma - Exterior",F17<>"Yabo - Hotelería",F17<>"OSJ - Medical",F17<>"Seezo - Home",F17<>"A&D -Home",F17<>"Encore Alfombras Hoteleria Asia",F17<>"Zhong Xian - Leds",F17<>"Tarkett Europa",F17<>"2tec2",F17<>"Balsan Europa",F17<>"Armstrong Pisos USA",F17<>"Tarkett USA",F17<>"Tarkett Brasil"),J17,IFERROR(IF(K576<=$AO$578,J17*2.14,IF(K576<=$AN$579,J17*1.8,IF(K576>$AN$580,J17*1.5))),J17))*1.1) -> 0 | N17: =M17*H17 -> 0 | O17: =IFERROR(VLOOKUP(G17,Proveedores!B:D,3,0)," ") | Q17: =VLOOKUP(E17,Tabla_Fletes,3,FALSE) -> #N/A | R17: =IF(P17="Centro",Q17,IF(P17="Norte",Q17*1.6,IF(P17="Occidente",Q17*1.2,IF(P17="Sur",Q17*2)))) -> FALSE | S17: =VLOOKUP(E17,Tabla_Instalacion,2,FALSE) -> #N/A | T17: =IF(P17="Centro",S17,IF(P17="Norte",S17*1.1,IF(P17="Occidente",S17*1.1,IF(P17="Sur",S17*1.1)))) -> FALSE | U17: =IF(F17="Offiho",0,R17+T17) -> 0 | V17: =IF(K17=0,U17/$H$573,U17*(K17/L17))*H17 -> #DIV/0! | W17: =IF(F17="Offiho",J17,IF(_xlfn.XLOOKUP(F17,Proveedores!A$2:A$50,Proveedores!E$2:E$50,"")="Nacional",(J17/0.5)+(V17*H17),((J17/0.3/0.5)+(V17*H17)))) -> #DIV/0! | X17: =(W17*H17) -> #DIV/0! | Y17: =IF(F17="Sunon Inc",$AJ$577,IF(F17="Alma - Exterior",$AJ$578,IF(F17="Yabo - Hotelería",$AJ$579,IF(F17="OSJ - Medical",$AJ$580,IF(F17="Seezo - Home",$AJ$581,IF(F17="A&D - Home",$AJ$582,IF(F17="Encore Alfombras Hoteleria Asia",$AJ$583,IF(F17="Zhong Xian - Leds",$AJ$584,IF(F17="Tarkett Europa",$AJ$585,IF(F17="2tec2",$AJ$586,IF(F17="Balsan Europa",$AJ$587,IF(F17="Armstrong Pisos USA",$AJ$588,IF(F17="Tarkett USA",$AJ$589,IF(F17="Tarkett Brasil",$AJ$590,IF(F17="Tarkett MX",$AJ$591,IF(F17="Jome",$AJ$592,IF(F17="Offiho",$AJ$593,IF(F17="Lumbro",$AJ$594,IF(F17="Sunon Mty",$AJ$595,IF(F17="Conceptos Sofas",$AJ$596,IF(F17="Lauco Sofas",$AJ$597,IF(F17="CR Global - Mesas Ajustables",$AJ$598,IF(F17="Vandesk",$AJ$599,IF(F17="Mamparas Tela",$AJ$600,IF(F17="Mampara Cristales",$AJ$601,IF(F17="Herrajes",$AJ$602,IF(F17="MetalWork",$AJ$603,IF(F17="Requiez",$AJ$604,IF(F17="Labenze",$AJ$605,IF(F17="Infinity",$AJ$606,IF(F17="Proveedor Externo",$AJ$607))))))))))))))))))))))))))))))) -> FALSE | Z17: 0.5 | AA17: =W17*Z17 -> #DIV/0! | AB17: =IF(Z17>Y17,"ERROR",(W17-AA17)) -> #DIV/0! | AC17: =AB17*H17 -> #DIV/0! | AD17: =IF(A18=TRUE,MAX(0,1-(AE17/W17)),"NA") -> #DIV/0! | AE17: =IF(A16=FALSE,"NO APLICA",AB17*1.2) -> #DIV/0! | AF17: =AE17*H17 -> #DIV/0! | AG17: =(AC17-N17)/AC17 -> #DIV/0! | AH17: =IF(AG17<30%,"ERROR","OK") -> #DIV/0! | AR17: Monto Comisión | AS17: =AS16-AS15 -> 0
A18: =$A$13 -> TRUE | B18: =A18 -> TRUE | C18: =$C$13 -> Dólares | G18: =IFERROR(VLOOKUP(F18,Tabla_Proveedores_1,2,0)," ") | H18: 0 | I18: =IFERROR(VLOOKUP(G18,Proveedores!B:C,2,0)," ") | J18: 0 | L18: =K18*H18 -> 0 | M18: =IF(F18="Offiho", J18*0.55, IF(AND(F18<>"Sunon Inc",F18<>"Alma - Exterior",F18<>"Yabo - Hotelería",F18<>"OSJ - Medical",F18<>"Seezo - Home",F18<>"A&D -Home",F18<>"Encore Alfombras Hoteleria Asia",F18<>"Zhong Xian - Leds",F18<>"Tarkett Europa",F18<>"2tec2",F18<>"Balsan Europa",F18<>"Armstrong Pisos USA",F18<>"Tarkett USA",F18<>"Tarkett Brasil"),J18,IFERROR(IF(K577<=$AO$578,J18*2.14,IF(K577<=$AN$579,J18*1.8,IF(K577>$AN$580,J18*1.5))),J18))*1.1) -> 0 | N18: =M18*H18 -> 0 | O18: =IFERROR(VLOOKUP(G18,Proveedores!B:D,3,0)," ") | Q18: =VLOOKUP(E18,Tabla_Fletes,3,FALSE) -> #N/A | R18: =IF(P18="Centro",Q18,IF(P18="Norte",Q18*1.6,IF(P18="Occidente",Q18*1.2,IF(P18="Sur",Q18*2)))) -> FALSE | S18: =VLOOKUP(E18,Tabla_Instalacion,2,FALSE) -> #N/A | T18: =IF(P18="Centro",S18,IF(P18="Norte",S18*1.1,IF(P18="Occidente",S18*1.1,IF(P18="Sur",S18*1.1)))) -> FALSE | U18: =IF(F18="Offiho",0,R18+T18) -> 0 | V18: =IF(K18=0,U18/$H$573,U18*(K18/L18))*H18 -> #DIV/0! | W18: =IF(F18="Offiho",J18,IF(_xlfn.XLOOKUP(F18,Proveedores!A$2:A$50,Proveedores!E$2:E$50,"")="Nacional",(J18/0.5)+(V18*H18),((J18/0.3/0.5)+(V18*H18)))) -> #DIV/0! | X18: =(W18*H18) -> #DIV/0! | Y18: =IF(F18="Sunon Inc",$AJ$577,IF(F18="Alma - Exterior",$AJ$578,IF(F18="Yabo - Hotelería",$AJ$579,IF(F18="OSJ - Medical",$AJ$580,IF(F18="Seezo - Home",$AJ$581,IF(F18="A&D - Home",$AJ$582,IF(F18="Encore Alfombras Hoteleria Asia",$AJ$583,IF(F18="Zhong Xian - Leds",$AJ$584,IF(F18="Tarkett Europa",$AJ$585,IF(F18="2tec2",$AJ$586,IF(F18="Balsan Europa",$AJ$587,IF(F18="Armstrong Pisos USA",$AJ$588,IF(F18="Tarkett USA",$AJ$589,IF(F18="Tarkett Brasil",$AJ$590,IF(F18="Tarkett MX",$AJ$591,IF(F18="Jome",$AJ$592,IF(F18="Offiho",$AJ$593,IF(F18="Lumbro",$AJ$594,IF(F18="Sunon Mty",$AJ$595,IF(F18="Conceptos Sofas",$AJ$596,IF(F18="Lauco Sofas",$AJ$597,IF(F18="CR Global - Mesas Ajustables",$AJ$598,IF(F18="Vandesk",$AJ$599,IF(F18="Mamparas Tela",$AJ$600,IF(F18="Mampara Cristales",$AJ$601,IF(F18="Herrajes",$AJ$602,IF(F18="MetalWork",$AJ$603,IF(F18="Requiez",$AJ$604,IF(F18="Labenze",$AJ$605,IF(F18="Infinity",$AJ$606,IF(F18="Proveedor Externo",$AJ$607))))))))))))))))))))))))))))))) -> FALSE | Z18: 0 | AA18: =W18*Z18 -> #DIV/0! | AB18: =IF(Z18>Y18,"ERROR",(W18-AA18)) -> #DIV/0! | AC18: =AB18*H18 -> #DIV/0! | AD18: =IF(A19=TRUE,MAX(0,1-(AE18/W18)),"NA") -> #DIV/0! | AE18: =IF(A17=FALSE,"NO APLICA",AB18*1.2) -> #DIV/0! | AF18: =AE18*H18 -> #DIV/0! | AG18: =(AC18-N18)/AC18 -> #DIV/0! | AH18: =IF(AG18<30%,"ERROR","OK") -> #DIV/0! | AR18: % Resultante | AS18: =(AS16/AS15)-1 -> #DIV/0! | AT18: 20% de comisión
A19: =$A$13 -> TRUE | B19: =A19 -> TRUE | C19: =$C$13 -> Dólares | G19: =IFERROR(VLOOKUP(F19,Tabla_Proveedores_1,2,0)," ") | H19: 0 | I19: =IFERROR(VLOOKUP(G19,Proveedores!B:C,2,0)," ") | J19: 0 | L19: =K19*H19 -> 0 | M19: =IF(F19="Offiho", J19*0.55, IF(AND(F19<>"Sunon Inc",F19<>"Alma - Exterior",F19<>"Yabo - Hotelería",F19<>"OSJ - Medical",F19<>"Seezo - Home",F19<>"A&D -Home",F19<>"Encore Alfombras Hoteleria Asia",F19<>"Zhong Xian - Leds",F19<>"Tarkett Europa",F19<>"2tec2",F19<>"Balsan Europa",F19<>"Armstrong Pisos USA",F19<>"Tarkett USA",F19<>"Tarkett Brasil"),J19,IFERROR(IF(K578<=$AO$578,J19*2.14,IF(K578<=$AN$579,J19*1.8,IF(K578>$AN$580,J19*1.5))),J19))*1.1) -> 0 | N19: =M19*H19 -> 0 | O19: =IFERROR(VLOOKUP(G19,Proveedores!B:D,3,0)," ") | Q19: =VLOOKUP(E19,Tabla_Fletes,3,FALSE) -> #N/A | R19: =IF(P19="Centro",Q19,IF(P19="Norte",Q19*1.6,IF(P19="Occidente",Q19*1.2,IF(P19="Sur",Q19*2)))) -> FALSE | S19: =VLOOKUP(E19,Tabla_Instalacion,2,FALSE) -> #N/A | T19: =IF(P19="Centro",S19,IF(P19="Norte",S19*1.1,IF(P19="Occidente",S19*1.1,IF(P19="Sur",S19*1.1)))) -> FALSE | U19: =IF(F19="Offiho",0,R19+T19) -> 0 | V19: =IF(K19=0,U19/$H$573,U19*(K19/L19))*H19 -> #DIV/0! | W19: =IF(F19="Offiho",J19,IF(_xlfn.XLOOKUP(F19,Proveedores!A$2:A$50,Proveedores!E$2:E$50,"")="Nacional",(J19/0.5)+(V19*H19),((J19/0.3/0.5)+(V19*H19)))) -> #DIV/0! | X19: =(W19*H19) -> #DIV/0! | Y19: =IF(F19="Sunon Inc",$AJ$577,IF(F19="Alma - Exterior",$AJ$578,IF(F19="Yabo - Hotelería",$AJ$579,IF(F19="OSJ - Medical",$AJ$580,IF(F19="Seezo - Home",$AJ$581,IF(F19="A&D - Home",$AJ$582,IF(F19="Encore Alfombras Hoteleria Asia",$AJ$583,IF(F19="Zhong Xian - Leds",$AJ$584,IF(F19="Tarkett Europa",$AJ$585,IF(F19="2tec2",$AJ$586,IF(F19="Balsan Europa",$AJ$587,IF(F19="Armstrong Pisos USA",$AJ$588,IF(F19="Tarkett USA",$AJ$589,IF(F19="Tarkett Brasil",$AJ$590,IF(F19="Tarkett MX",$AJ$591,IF(F19="Jome",$AJ$592,IF(F19="Offiho",$AJ$593,IF(F19="Lumbro",$AJ$594,IF(F19="Sunon Mty",$AJ$595,IF(F19="Conceptos Sofas",$AJ$596,IF(F19="Lauco Sofas",$AJ$597,IF(F19="CR Global - Mesas Ajustables",$AJ$598,IF(F19="Vandesk",$AJ$599,IF(F19="Mamparas Tela",$AJ$600,IF(F19="Mampara Cristales",$AJ$601,IF(F19="Herrajes",$AJ$602,IF(F19="MetalWork",$AJ$603,IF(F19="Requiez",$AJ$604,IF(F19="Labenze",$AJ$605,IF(F19="Infinity",$AJ$606,IF(F19="Proveedor Externo",$AJ$607))))))))))))))))))))))))))))))) -> FALSE | Z19: 0 | AA19: =W19*Z19 -> #DIV/0! | AB19: =IF(Z19>Y19,"ERROR",(W19-AA19)) -> #DIV/0! | AC19: =AB19*H19 -> #DIV/0! | AD19: =IF(A20=TRUE,MAX(0,1-(AE19/W19)),"NA") -> #DIV/0! | AE19: =IF(A18=FALSE,"NO APLICA",AB19*1.2) -> #DIV/0! | AF19: =AE19*H19 -> #DIV/0! | AG19: =(AC19-N19)/AC19 -> #DIV/0! | AH19: =IF(AG19<30%,"ERROR","OK") -> #DIV/0!
A20: =$A$13 -> TRUE | B20: =A20 -> TRUE | C20: =$C$13 -> Dólares | G20: =IFERROR(VLOOKUP(F20,Tabla_Proveedores_1,2,0)," ") | H20: 0 | I20: =IFERROR(VLOOKUP(G20,Proveedores!B:C,2,0)," ") | J20: 0 | L20: =K20*H20 -> 0 | M20: =IF(F20="Offiho", J20*0.55, IF(AND(F20<>"Sunon Inc",F20<>"Alma - Exterior",F20<>"Yabo - Hotelería",F20<>"OSJ - Medical",F20<>"Seezo - Home",F20<>"A&D -Home",F20<>"Encore Alfombras Hoteleria Asia",F20<>"Zhong Xian - Leds",F20<>"Tarkett Europa",F20<>"2tec2",F20<>"Balsan Europa",F20<>"Armstrong Pisos USA",F20<>"Tarkett USA",F20<>"Tarkett Brasil"),J20,IFERROR(IF(J579<=$AO$578,J20*2.14,IF(J579<=$AN$579,J20*1.8,IF(J579>$AN$580,J20*1.5))),J20))*1.1) -> 0 | N20: =M20*H20 -> 0 | O20: =IFERROR(VLOOKUP(G20,Proveedores!B:D,3,0)," ") | Q20: =VLOOKUP(E20,Tabla_Fletes,3,FALSE) -> #N/A | R20: =IF(P20="Centro",Q20,IF(P20="Norte",Q20*1.6,IF(P20="Occidente",Q20*1.2,IF(P20="Sur",Q20*2)))) -> FALSE | S20: =VLOOKUP(E20,Tabla_Instalacion,2,FALSE) -> #N/A | T20: =IF(P20="Centro",S20,IF(P20="Norte",S20*1.1,IF(P20="Occidente",S20*1.1,IF(P20="Sur",S20*1.1)))) -> FALSE | U20: =IF(F20="Offiho",0,R20+T20) -> 0 | V20: =IF(K20=0,U20/$H$573,U20*(K20/L20))*H20 -> #DIV/0! | W20: =IF(F20="Offiho",J20,IF(_xlfn.XLOOKUP(F20,Proveedores!A$2:A$50,Proveedores!E$2:E$50,"")="Nacional",(J20/0.5)+(V20*H20),((J20/0.3/0.5)+(V20*H20)))) -> #DIV/0! | X20: =(W20*H20) -> #DIV/0! | Y20: =IF(F20="Sunon Inc",$AJ$577,IF(F20="Alma - Exterior",$AJ$578,IF(F20="Yabo - Hotelería",$AJ$579,IF(F20="OSJ - Medical",$AJ$580,IF(F20="Seezo - Home",$AJ$581,IF(F20="A&D - Home",$AJ$582,IF(F20="Encore Alfombras Hoteleria Asia",$AJ$583,IF(F20="Zhong Xian - Leds",$AJ$584,IF(F20="Tarkett Europa",$AJ$585,IF(F20="2tec2",$AJ$586,IF(F20="Balsan Europa",$AJ$587,IF(F20="Armstrong Pisos USA",$AJ$588,IF(F20="Tarkett USA",$AJ$589,IF(F20="Tarkett Brasil",$AJ$590,IF(F20="Tarkett MX",$AJ$591,IF(F20="Jome",$AJ$592,IF(F20="Offiho",$AJ$593,IF(F20="Lumbro",$AJ$594,IF(F20="Sunon Mty",$AJ$595,IF(F20="Conceptos Sofas",$AJ$596,IF(F20="Lauco Sofas",$AJ$597,IF(F20="CR Global - Mesas Ajustables",$AJ$598,IF(F20="Vandesk",$AJ$599,IF(F20="Mamparas Tela",$AJ$600,IF(F20="Mampara Cristales",$AJ$601,IF(F20="Herrajes",$AJ$602,IF(F20="MetalWork",$AJ$603,IF(F20="Requiez",$AJ$604,IF(F20="Labenze",$AJ$605,IF(F20="Infinity",$AJ$606,IF(F20="Proveedor Externo",$AJ$607))))))))))))))))))))))))))))))) -> FALSE | Z20: 0 | AA20: =W20*Z20 -> #DIV/0! | AB20: =IF(Z20>Y20,"ERROR",(W20-AA20)) -> #DIV/0! | AC20: =AB20*H20 -> #DIV/0! | AD20: =IF(A21=TRUE,MAX(0,1-(AE20/W20)),"NA") -> #DIV/0! | AE20: =IF(A19=FALSE,"NO APLICA",AB20*1.2) -> #DIV/0! | AF20: =AE20*H20 -> #DIV/0! | AG20: =(AC20-N20)/AC20 -> #DIV/0! | AH20: =IF(AG20<30%,"ERROR","OK") -> #DIV/0!
A21: =$A$13 -> TRUE | B21: =A21 -> TRUE | C21: =$C$13 -> Dólares | G21: =IFERROR(VLOOKUP(F21,Tabla_Proveedores_1,2,0)," ") | H21: 0 | I21: =IFERROR(VLOOKUP(G21,Proveedores!B:C,2,0)," ") | J21: 0 | L21: =K21*H21 -> 0 | M21: =IF(F21="Offiho", J21*0.55, IF(AND(F21<>"Sunon Inc",F21<>"Alma - Exterior",F21<>"Yabo - Hotelería",F21<>"OSJ - Medical",F21<>"Seezo - Home",F21<>"A&D -Home",F21<>"Encore Alfombras Hoteleria Asia",F21<>"Zhong Xian - Leds",F21<>"Tarkett Europa",F21<>"2tec2",F21<>"Balsan Europa",F21<>"Armstrong Pisos USA",F21<>"Tarkett USA",F21<>"Tarkett Brasil"),J21,IFERROR(IF(J580<=$AO$578,J21*2.14,IF(J580<=$AN$579,J21*1.8,IF(J580>$AN$580,J21*1.5))),J21))*1.1) -> 0 | N21: =M21*H21 -> 0 | O21: =IFERROR(VLOOKUP(G21,Proveedores!B:D,3,0)," ") | Q21: =VLOOKUP(E21,Tabla_Fletes,3,FALSE) -> #N/A | R21: =IF(P21="Centro",Q21,IF(P21="Norte",Q21*1.6,IF(P21="Occidente",Q21*1.2,IF(P21="Sur",Q21*2)))) -> FALSE | S21: =VLOOKUP(E21,Tabla_Instalacion,2,FALSE) -> #N/A | T21: =IF(P21="Centro",S21,IF(P21="Norte",S21*1.1,IF(P21="Occidente",S21*1.1,IF(P21="Sur",S21*1.1)))) -> FALSE | U21: =IF(F21="Offiho",0,R21+T21) -> 0 | V21: =IF(K21=0,U21/$H$573,U21*(K21/L21))*H21 -> #DIV/0! | W21: =IF(F21="Offiho",J21,IF(_xlfn.XLOOKUP(F21,Proveedores!A$2:A$50,Proveedores!E$2:E$50,"")="Nacional",(J21/0.5)+(V21*H21),((J21/0.3/0.5)+(V21*H21)))) -> #DIV/0! | X21: =(W21*H21) -> #DIV/0! | Y21: =IF(F21="Sunon Inc",$AJ$577,IF(F21="Alma - Exterior",$AJ$578,IF(F21="Yabo - Hotelería",$AJ$579,IF(F21="OSJ - Medical",$AJ$580,IF(F21="Seezo - Home",$AJ$581,IF(F21="A&D - Home",$AJ$582,IF(F21="Encore Alfombras Hoteleria Asia",$AJ$583,IF(F21="Zhong Xian - Leds",$AJ$584,IF(F21="Tarkett Europa",$AJ$585,IF(F21="2tec2",$AJ$586,IF(F21="Balsan Europa",$AJ$587,IF(F21="Armstrong Pisos USA",$AJ$588,IF(F21="Tarkett USA",$AJ$589,IF(F21="Tarkett Brasil",$AJ$590,IF(F21="Tarkett MX",$AJ$591,IF(F21="Jome",$AJ$592,IF(F21="Offiho",$AJ$593,IF(F21="Lumbro",$AJ$594,IF(F21="Sunon Mty",$AJ$595,IF(F21="Conceptos Sofas",$AJ$596,IF(F21="Lauco Sofas",$AJ$597,IF(F21="CR Global - Mesas Ajustables",$AJ$598,IF(F21="Vandesk",$AJ$599,IF(F21="Mamparas Tela",$AJ$600,IF(F21="Mampara Cristales",$AJ$601,IF(F21="Herrajes",$AJ$602,IF(F21="MetalWork",$AJ$603,IF(F21="Requiez",$AJ$604,IF(F21="Labenze",$AJ$605,IF(F21="Infinity",$AJ$606,IF(F21="Proveedor Externo",$AJ$607))))))))))))))))))))))))))))))) -> FALSE | Z21: 0 | AA21: =W21*Z21 -> #DIV/0! | AB21: =IF(Z21>Y21,"ERROR",(W21-AA21)) -> #DIV/0! | AC21: =AB21*H21 -> #DIV/0! | AD21: =IF(A22=TRUE,MAX(0,1-(AE21/W21)),"NA") -> #DIV/0! | AE21: =IF(A20=FALSE,"NO APLICA",AB21*1.2) -> #DIV/0! | AF21: =AE21*H21 -> #DIV/0! | AG21: =(AC21-N21)/AC21 -> #DIV/0! | AH21: =IF(AG21<30%,"ERROR","OK") -> #DIV/0!
A22: =$A$13 -> TRUE | B22: =A22 -> TRUE | C22: =$C$13 -> Dólares | G22: =IFERROR(VLOOKUP(F22,Tabla_Proveedores_1,2,0)," ") | H22: 0 | I22: =IFERROR(VLOOKUP(G22,Proveedores!B:C,2,0)," ") | J22: 0 | L22: =K22*H22 -> 0 | M22: =IF(F22="Offiho", J22*0.55, IF(AND(F22<>"Sunon Inc",F22<>"Alma - Exterior",F22<>"Yabo - Hotelería",F22<>"OSJ - Medical",F22<>"Seezo - Home",F22<>"A&D -Home",F22<>"Encore Alfombras Hoteleria Asia",F22<>"Zhong Xian - Leds",F22<>"Tarkett Europa",F22<>"2tec2",F22<>"Balsan Europa",F22<>"Armstrong Pisos USA",F22<>"Tarkett USA",F22<>"Tarkett Brasil"),J22,IFERROR(IF(J581<=$AO$578,J22*2.14,IF(J581<=$AN$579,J22*1.8,IF(J581>$AN$580,J22*1.5))),J22))*1.1) -> 0 | N22: =M22*H22 -> 0 | O22: =IFERROR(VLOOKUP(G22,Proveedores!B:D,3,0)," ") | Q22: =VLOOKUP(E22,Tabla_Fletes,3,FALSE) -> #N/A | R22: =IF(P22="Centro",Q22,IF(P22="Norte",Q22*1.6,IF(P22="Occidente",Q22*1.2,IF(P22="Sur",Q22*2)))) -> FALSE | S22: =VLOOKUP(E22,Tabla_Instalacion,2,FALSE) -> #N/A | T22: =IF(P22="Centro",S22,IF(P22="Norte",S22*1.1,IF(P22="Occidente",S22*1.1,IF(P22="Sur",S22*1.1)))) -> FALSE | U22: =IF(F22="Offiho",0,R22+T22) -> 0 | V22: =IF(K22=0,U22/$H$573,U22*(K22/L22))*H22 -> #DIV/0! | W22: =IF(F22="Offiho",J22,IF(_xlfn.XLOOKUP(F22,Proveedores!A$2:A$50,Proveedores!E$2:E$50,"")="Nacional",(J22/0.5)+(V22*H22),((J22/0.3/0.5)+(V22*H22)))) -> #DIV/0! | X22: =(W22*H22) -> #DIV/0! | Y22: =IF(F22="Sunon Inc",$AJ$577,IF(F22="Alma - Exterior",$AJ$578,IF(F22="Yabo - Hotelería",$AJ$579,IF(F22="OSJ - Medical",$AJ$580,IF(F22="Seezo - Home",$AJ$581,IF(F22="A&D - Home",$AJ$582,IF(F22="Encore Alfombras Hoteleria Asia",$AJ$583,IF(F22="Zhong Xian - Leds",$AJ$584,IF(F22="Tarkett Europa",$AJ$585,IF(F22="2tec2",$AJ$586,IF(F22="Balsan Europa",$AJ$587,IF(F22="Armstrong Pisos USA",$AJ$588,IF(F22="Tarkett USA",$AJ$589,IF(F22="Tarkett Brasil",$AJ$590,IF(F22="Tarkett MX",$AJ$591,IF(F22="Jome",$AJ$592,IF(F22="Offiho",$AJ$593,IF(F22="Lumbro",$AJ$594,IF(F22="Sunon Mty",$AJ$595,IF(F22="Conceptos Sofas",$AJ$596,IF(F22="Lauco Sofas",$AJ$597,IF(F22="CR Global - Mesas Ajustables",$AJ$598,IF(F22="Vandesk",$AJ$599,IF(F22="Mamparas Tela",$AJ$600,IF(F22="Mampara Cristales",$AJ$601,IF(F22="Herrajes",$AJ$602,IF(F22="MetalWork",$AJ$603,IF(F22="Requiez",$AJ$604,IF(F22="Labenze",$AJ$605,IF(F22="Infinity",$AJ$606,IF(F22="Proveedor Externo",$AJ$607))))))))))))))))))))))))))))))) -> FALSE | Z22: 0 | AA22: =W22*Z22 -> #DIV/0! | AB22: =IF(Z22>Y22,"ERROR",(W22-AA22)) -> #DIV/0! | AC22: =AB22*H22 -> #DIV/0! | AD22: =IF(A23=TRUE,MAX(0,1-(AE22/W22)),"NA") -> #DIV/0! | AE22: =IF(A21=FALSE,"NO APLICA",AB22*1.2) -> #DIV/0! | AF22: =AE22*H22 -> #DIV/0! | AG22: =(AC22-N22)/AC22 -> #DIV/0! | AH22: =IF(AG22<30%,"ERROR","OK") -> #DIV/0!
A23: =$A$13 -> TRUE | B23: =A23 -> TRUE | C23: =$C$13 -> Dólares | G23: =IFERROR(VLOOKUP(F23,Tabla_Proveedores_1,2,0)," ") | H23: 0 | I23: =IFERROR(VLOOKUP(G23,Proveedores!B:C,2,0)," ") | J23: 0 | L23: =K23*H23 -> 0 | M23: =IF(F23="Offiho", J23*0.55, IF(AND(F23<>"Sunon Inc",F23<>"Alma - Exterior",F23<>"Yabo - Hotelería",F23<>"OSJ - Medical",F23<>"Seezo - Home",F23<>"A&D -Home",F23<>"Encore Alfombras Hoteleria Asia",F23<>"Zhong Xian - Leds",F23<>"Tarkett Europa",F23<>"2tec2",F23<>"Balsan Europa",F23<>"Armstrong Pisos USA",F23<>"Tarkett USA",F23<>"Tarkett Brasil"),J23,IFERROR(IF(J582<=$AO$578,J23*2.14,IF(J582<=$AN$579,J23*1.8,IF(J582>$AN$580,J23*1.5))),J23))*1.1) -> 0 | N23: =M23*H23 -> 0 | O23: =IFERROR(VLOOKUP(G23,Proveedores!B:D,3,0)," ") | Q23: =VLOOKUP(E23,Tabla_Fletes,3,FALSE) -> #N/A | R23: =IF(P23="Centro",Q23,IF(P23="Norte",Q23*1.6,IF(P23="Occidente",Q23*1.2,IF(P23="Sur",Q23*2)))) -> FALSE | S23: =VLOOKUP(E23,Tabla_Instalacion,2,FALSE) -> #N/A | T23: =IF(P23="Centro",S23,IF(P23="Norte",S23*1.1,IF(P23="Occidente",S23*1.1,IF(P23="Sur",S23*1.1)))) -> FALSE | U23: =IF(F23="Offiho",0,R23+T23) -> 0 | V23: =IF(K23=0,U23/$H$573,U23*(K23/L23))*H23 -> #DIV/0! | W23: =IF(F23="Offiho",J23,IF(_xlfn.XLOOKUP(F23,Proveedores!A$2:A$50,Proveedores!E$2:E$50,"")="Nacional",(J23/0.5)+(V23*H23),((J23/0.3/0.5)+(V23*H23)))) -> #DIV/0! | X23: =(W23*H23) -> #DIV/0! | Y23: =IF(F23="Sunon Inc",$AJ$577,IF(F23="Alma - Exterior",$AJ$578,IF(F23="Yabo - Hotelería",$AJ$579,IF(F23="OSJ - Medical",$AJ$580,IF(F23="Seezo - Home",$AJ$581,IF(F23="A&D - Home",$AJ$582,IF(F23="Encore Alfombras Hoteleria Asia",$AJ$583,IF(F23="Zhong Xian - Leds",$AJ$584,IF(F23="Tarkett Europa",$AJ$585,IF(F23="2tec2",$AJ$586,IF(F23="Balsan Europa",$AJ$587,IF(F23="Armstrong Pisos USA",$AJ$588,IF(F23="Tarkett USA",$AJ$589,IF(F23="Tarkett Brasil",$AJ$590,IF(F23="Tarkett MX",$AJ$591,IF(F23="Jome",$AJ$592,IF(F23="Offiho",$AJ$593,IF(F23="Lumbro",$AJ$594,IF(F23="Sunon Mty",$AJ$595,IF(F23="Conceptos Sofas",$AJ$596,IF(F23="Lauco Sofas",$AJ$597,IF(F23="CR Global - Mesas Ajustables",$AJ$598,IF(F23="Vandesk",$AJ$599,IF(F23="Mamparas Tela",$AJ$600,IF(F23="Mampara Cristales",$AJ$601,IF(F23="Herrajes",$AJ$602,IF(F23="MetalWork",$AJ$603,IF(F23="Requiez",$AJ$604,IF(F23="Labenze",$AJ$605,IF(F23="Infinity",$AJ$606,IF(F23="Proveedor Externo",$AJ$607))))))))))))))))))))))))))))))) -> FALSE | Z23: 0 | AA23: =W23*Z23 -> #DIV/0! | AB23: =IF(Z23>Y23,"ERROR",(W23-AA23)) -> #DIV/0! | AC23: =AB23*H23 -> #DIV/0! | AD23: =IF(A24=TRUE,MAX(0,1-(AE23/W23)),"NA") -> #DIV/0! | AE23: =IF(A22=FALSE,"NO APLICA",AB23*1.2) -> #DIV/0! | AF23: =AE23*H23 -> #DIV/0! | AG23: =(AC23-N23)/AC23 -> #DIV/0! | AH23: =IF(AG23<30%,"ERROR","OK") -> #DIV/0!
A24: =$A$13 -> TRUE | B24: =A24 -> TRUE | C24: =$C$13 -> Dólares | G24: =IFERROR(VLOOKUP(F24,Tabla_Proveedores_1,2,0)," ") | H24: 0 | I24: =IFERROR(VLOOKUP(G24,Proveedores!B:C,2,0)," ") | J24: 0 | L24: =K24*H24 -> 0 | M24: =IF(F24="Offiho", J24*0.55, IF(AND(F24<>"Sunon Inc",F24<>"Alma - Exterior",F24<>"Yabo - Hotelería",F24<>"OSJ - Medical",F24<>"Seezo - Home",F24<>"A&D -Home",F24<>"Encore Alfombras Hoteleria Asia",F24<>"Zhong Xian - Leds",F24<>"Tarkett Europa",F24<>"2tec2",F24<>"Balsan Europa",F24<>"Armstrong Pisos USA",F24<>"Tarkett USA",F24<>"Tarkett Brasil"),J24,IFERROR(IF(J583<=$AO$578,J24*2.14,IF(J583<=$AN$579,J24*1.8,IF(J583>$AN$580,J24*1.5))),J24))*1.1) -> 0 | N24: =M24*H24 -> 0 | O24: =IFERROR(VLOOKUP(G24,Proveedores!B:D,3,0)," ") | Q24: =VLOOKUP(E24,Tabla_Fletes,3,FALSE) -> #N/A | R24: =IF(P24="Centro",Q24,IF(P24="Norte",Q24*1.6,IF(P24="Occidente",Q24*1.2,IF(P24="Sur",Q24*2)))) -> FALSE | S24: =VLOOKUP(E24,Tabla_Instalacion,2,FALSE) -> #N/A | T24: =IF(P24="Centro",S24,IF(P24="Norte",S24*1.1,IF(P24="Occidente",S24*1.1,IF(P24="Sur",S24*1.1)))) -> FALSE | U24: =IF(F24="Offiho",0,R24+T24) -> 0 | V24: =IF(K24=0,U24/$H$573,U24*(K24/L24))*H24 -> #DIV/0! | W24: =IF(F24="Offiho",J24,IF(_xlfn.XLOOKUP(F24,Proveedores!A$2:A$50,Proveedores!E$2:E$50,"")="Nacional",(J24/0.5)+(V24*H24),((J24/0.3/0.5)+(V24*H24)))) -> #DIV/0! | X24: =(W24*H24) -> #DIV/0! | Y24: =IF(F24="Sunon Inc",$AJ$577,IF(F24="Alma - Exterior",$AJ$578,IF(F24="Yabo - Hotelería",$AJ$579,IF(F24="OSJ - Medical",$AJ$580,IF(F24="Seezo - Home",$AJ$581,IF(F24="A&D - Home",$AJ$582,IF(F24="Encore Alfombras Hoteleria Asia",$AJ$583,IF(F24="Zhong Xian - Leds",$AJ$584,IF(F24="Tarkett Europa",$AJ$585,IF(F24="2tec2",$AJ$586,IF(F24="Balsan Europa",$AJ$587,IF(F24="Armstrong Pisos USA",$AJ$588,IF(F24="Tarkett USA",$AJ$589,IF(F24="Tarkett Brasil",$AJ$590,IF(F24="Tarkett MX",$AJ$591,IF(F24="Jome",$AJ$592,IF(F24="Offiho",$AJ$593,IF(F24="Lumbro",$AJ$594,IF(F24="Sunon Mty",$AJ$595,IF(F24="Conceptos Sofas",$AJ$596,IF(F24="Lauco Sofas",$AJ$597,IF(F24="CR Global - Mesas Ajustables",$AJ$598,IF(F24="Vandesk",$AJ$599,IF(F24="Mamparas Tela",$AJ$600,IF(F24="Mampara Cristales",$AJ$601,IF(F24="Herrajes",$AJ$602,IF(F24="MetalWork",$AJ$603,IF(F24="Requiez",$AJ$604,IF(F24="Labenze",$AJ$605,IF(F24="Infinity",$AJ$606,IF(F24="Proveedor Externo",$AJ$607))))))))))))))))))))))))))))))) -> FALSE | Z24: 0 | AA24: =W24*Z24 -> #DIV/0! | AB24: =IF(Z24>Y24,"ERROR",(W24-AA24)) -> #DIV/0! | AC24: =AB24*H24 -> #DIV/0! | AD24: =IF(A25=TRUE,MAX(0,1-(AE24/W24)),"NA") -> #DIV/0! | AE24: =IF(A23=FALSE,"NO APLICA",AB24*1.2) -> #DIV/0! | AF24: =AE24*H24 -> #DIV/0! | AG24: =(AC24-N24)/AC24 -> #DIV/0! | AH24: =IF(AG24<30%,"ERROR","OK") -> #DIV/0!
A25: =$A$13 -> TRUE | B25: =A25 -> TRUE | C25: =$C$13 -> Dólares | G25: =IFERROR(VLOOKUP(F25,Tabla_Proveedores_1,2,0)," ") | H25: 0 | I25: =IFERROR(VLOOKUP(G25,Proveedores!B:C,2,0)," ") | J25: 0 | L25: =K25*H25 -> 0 | M25: =IF(F25="Offiho", J25*0.55, IF(AND(F25<>"Sunon Inc",F25<>"Alma - Exterior",F25<>"Yabo - Hotelería",F25<>"OSJ - Medical",F25<>"Seezo - Home",F25<>"A&D -Home",F25<>"Encore Alfombras Hoteleria Asia",F25<>"Zhong Xian - Leds",F25<>"Tarkett Europa",F25<>"2tec2",F25<>"Balsan Europa",F25<>"Armstrong Pisos USA",F25<>"Tarkett USA",F25<>"Tarkett Brasil"),J25,IFERROR(IF(J584<=$AO$578,J25*2.14,IF(J584<=$AN$579,J25*1.8,IF(J584>$AN$580,J25*1.5))),J25))*1.1) -> 0 | N25: =M25*H25 -> 0 | O25: =IFERROR(VLOOKUP(G25,Proveedores!B:D,3,0)," ") | Q25: =VLOOKUP(E25,Tabla_Fletes,3,FALSE) -> #N/A | R25: =IF(P25="Centro",Q25,IF(P25="Norte",Q25*1.6,IF(P25="Occidente",Q25*1.2,IF(P25="Sur",Q25*2)))) -> FALSE | S25: =VLOOKUP(E25,Tabla_Instalacion,2,FALSE) -> #N/A | T25: =IF(P25="Centro",S25,IF(P25="Norte",S25*1.1,IF(P25="Occidente",S25*1.1,IF(P25="Sur",S25*1.1)))) -> FALSE | U25: =IF(F25="Offiho",0,R25+T25) -> 0 | V25: =IF(K25=0,U25/$H$573,U25*(K25/L25))*H25 -> #DIV/0! | W25: =IF(F25="Offiho",J25,IF(_xlfn.XLOOKUP(F25,Proveedores!A$2:A$50,Proveedores!E$2:E$50,"")="Nacional",(J25/0.5)+(V25*H25),((J25/0.3/0.5)+(V25*H25)))) -> #DIV/0! | X25: =(W25*H25) -> #DIV/0! | Y25: =IF(F25="Sunon Inc",$AJ$577,IF(F25="Alma - Exterior",$AJ$578,IF(F25="Yabo - Hotelería",$AJ$579,IF(F25="OSJ - Medical",$AJ$580,IF(F25="Seezo - Home",$AJ$581,IF(F25="A&D - Home",$AJ$582,IF(F25="Encore Alfombras Hoteleria Asia",$AJ$583,IF(F25="Zhong Xian - Leds",$AJ$584,IF(F25="Tarkett Europa",$AJ$585,IF(F25="2tec2",$AJ$586,IF(F25="Balsan Europa",$AJ$587,IF(F25="Armstrong Pisos USA",$AJ$588,IF(F25="Tarkett USA",$AJ$589,IF(F25="Tarkett Brasil",$AJ$590,IF(F25="Tarkett MX",$AJ$591,IF(F25="Jome",$AJ$592,IF(F25="Offiho",$AJ$593,IF(F25="Lumbro",$AJ$594,IF(F25="Sunon Mty",$AJ$595,IF(F25="Conceptos Sofas",$AJ$596,IF(F25="Lauco Sofas",$AJ$597,IF(F25="CR Global - Mesas Ajustables",$AJ$598,IF(F25="Vandesk",$AJ$599,IF(F25="Mamparas Tela",$AJ$600,IF(F25="Mampara Cristales",$AJ$601,IF(F25="Herrajes",$AJ$602,IF(F25="MetalWork",$AJ$603,IF(F25="Requiez",$AJ$604,IF(F25="Labenze",$AJ$605,IF(F25="Infinity",$AJ$606,IF(F25="Proveedor Externo",$AJ$607))))))))))))))))))))))))))))))) -> FALSE | Z25: 0 | AA25: =W25*Z25 -> #DIV/0! | AB25: =IF(Z25>Y25,"ERROR",(W25-AA25)) -> #DIV/0! | AC25: =AB25*H25 -> #DIV/0! | AD25: =IF(A26=TRUE,MAX(0,1-(AE25/W25)),"NA") -> #DIV/0! | AE25: =IF(A24=FALSE,"NO APLICA",AB25*1.2) -> #DIV/0! | AF25: =AE25*H25 -> #DIV/0! | AG25: =(AC25-N25)/AC25 -> #DIV/0! | AH25: =IF(AG25<30%,"ERROR","OK") -> #DIV/0!
A26: =$A$13 -> TRUE | B26: =A26 -> TRUE | C26: =$C$13 -> Dólares | G26: =IFERROR(VLOOKUP(F26,Tabla_Proveedores_1,2,0)," ") | H26: 0 | I26: =IFERROR(VLOOKUP(G26,Proveedores!B:C,2,0)," ") | J26: 0 | L26: =K26*H26 -> 0 | M26: =IF(F26="Offiho", J26*0.55, IF(AND(F26<>"Sunon Inc",F26<>"Alma - Exterior",F26<>"Yabo - Hotelería",F26<>"OSJ - Medical",F26<>"Seezo - Home",F26<>"A&D -Home",F26<>"Encore Alfombras Hoteleria Asia",F26<>"Zhong Xian - Leds",F26<>"Tarkett Europa",F26<>"2tec2",F26<>"Balsan Europa",F26<>"Armstrong Pisos USA",F26<>"Tarkett USA",F26<>"Tarkett Brasil"),J26,IFERROR(IF(J585<=$AO$578,J26*2.14,IF(J585<=$AN$579,J26*1.8,IF(J585>$AN$580,J26*1.5))),J26))*1.1) -> 0 | N26: =M26*H26 -> 0 | O26: =IFERROR(VLOOKUP(G26,Proveedores!B:D,3,0)," ") | Q26: =VLOOKUP(E26,Tabla_Fletes,3,FALSE) -> #N/A | R26: =IF(P26="Centro",Q26,IF(P26="Norte",Q26*1.6,IF(P26="Occidente",Q26*1.2,IF(P26="Sur",Q26*2)))) -> FALSE | S26: =VLOOKUP(E26,Tabla_Instalacion,2,FALSE) -> #N/A | T26: =IF(P26="Centro",S26,IF(P26="Norte",S26*1.1,IF(P26="Occidente",S26*1.1,IF(P26="Sur",S26*1.1)))) -> FALSE | U26: =IF(F26="Offiho",0,R26+T26) -> 0 | V26: =IF(K26=0,U26/$H$573,U26*(K26/L26))*H26 -> #DIV/0! | W26: =IF(F26="Offiho",J26,IF(_xlfn.XLOOKUP(F26,Proveedores!A$2:A$50,Proveedores!E$2:E$50,"")="Nacional",(J26/0.5)+(V26*H26),((J26/0.3/0.5)+(V26*H26)))) -> #DIV/0! | X26: =(W26*H26) -> #DIV/0! | Y26: =IF(F26="Sunon Inc",$AJ$577,IF(F26="Alma - Exterior",$AJ$578,IF(F26="Yabo - Hotelería",$AJ$579,IF(F26="OSJ - Medical",$AJ$580,IF(F26="Seezo - Home",$AJ$581,IF(F26="A&D - Home",$AJ$582,IF(F26="Encore Alfombras Hoteleria Asia",$AJ$583,IF(F26="Zhong Xian - Leds",$AJ$584,IF(F26="Tarkett Europa",$AJ$585,IF(F26="2tec2",$AJ$586,IF(F26="Balsan Europa",$AJ$587,IF(F26="Armstrong Pisos USA",$AJ$588,IF(F26="Tarkett USA",$AJ$589,IF(F26="Tarkett Brasil",$AJ$590,IF(F26="Tarkett MX",$AJ$591,IF(F26="Jome",$AJ$592,IF(F26="Offiho",$AJ$593,IF(F26="Lumbro",$AJ$594,IF(F26="Sunon Mty",$AJ$595,IF(F26="Conceptos Sofas",$AJ$596,IF(F26="Lauco Sofas",$AJ$597,IF(F26="CR Global - Mesas Ajustables",$AJ$598,IF(F26="Vandesk",$AJ$599,IF(F26="Mamparas Tela",$AJ$600,IF(F26="Mampara Cristales",$AJ$601,IF(F26="Herrajes",$AJ$602,IF(F26="MetalWork",$AJ$603,IF(F26="Requiez",$AJ$604,IF(F26="Labenze",$AJ$605,IF(F26="Infinity",$AJ$606,IF(F26="Proveedor Externo",$AJ$607))))))))))))))))))))))))))))))) -> FALSE | Z26: 0 | AA26: =W26*Z26 -> #DIV/0! | AB26: =IF(Z26>Y26,"ERROR",(W26-AA26)) -> #DIV/0! | AC26: =AB26*H26 -> #DIV/0! | AD26: =IF(A27=TRUE,MAX(0,1-(AE26/W26)),"NA") -> #DIV/0! | AE26: =IF(A25=FALSE,"NO APLICA",AB26*1.2) -> #DIV/0! | AF26: =AE26*H26 -> #DIV/0! | AG26: =(AC26-N26)/AC26 -> #DIV/0! | AH26: =IF(AG26<30%,"ERROR","OK") -> #DIV/0!
A27: =$A$13 -> TRUE | B27: =A27 -> TRUE | C27: =$C$13 -> Dólares | G27: =IFERROR(VLOOKUP(F27,Tabla_Proveedores_1,2,0)," ") | H27: 0 | I27: =IFERROR(VLOOKUP(G27,Proveedores!B:C,2,0)," ") | J27: 0 | L27: =K27*H27 -> 0 | M27: =IF(F27="Offiho", J27*0.55, IF(AND(F27<>"Sunon Inc",F27<>"Alma - Exterior",F27<>"Yabo - Hotelería",F27<>"OSJ - Medical",F27<>"Seezo - Home",F27<>"A&D -Home",F27<>"Encore Alfombras Hoteleria Asia",F27<>"Zhong Xian - Leds",F27<>"Tarkett Europa",F27<>"2tec2",F27<>"Balsan Europa",F27<>"Armstrong Pisos USA",F27<>"Tarkett USA",F27<>"Tarkett Brasil"),J27,IFERROR(IF(J586<=$AO$578,J27*2.14,IF(J586<=$AN$579,J27*1.8,IF(J586>$AN$580,J27*1.5))),J27))*1.1) -> 0 | N27: =M27*H27 -> 0 | O27: =IFERROR(VLOOKUP(G27,Proveedores!B:D,3,0)," ") | Q27: =VLOOKUP(E27,Tabla_Fletes,3,FALSE) -> #N/A | R27: =IF(P27="Centro",Q27,IF(P27="Norte",Q27*1.6,IF(P27="Occidente",Q27*1.2,IF(P27="Sur",Q27*2)))) -> FALSE | S27: =VLOOKUP(E27,Tabla_Instalacion,2,FALSE) -> #N/A | T27: =IF(P27="Centro",S27,IF(P27="Norte",S27*1.1,IF(P27="Occidente",S27*1.1,IF(P27="Sur",S27*1.1)))) -> FALSE | U27: =IF(F27="Offiho",0,R27+T27) -> 0 | V27: =IF(K27=0,U27/$H$573,U27*(K27/L27))*H27 -> #DIV/0! | W27: =IF(F27="Offiho",J27,IF(_xlfn.XLOOKUP(F27,Proveedores!A$2:A$50,Proveedores!E$2:E$50,"")="Nacional",(J27/0.5)+(V27*H27),((J27/0.3/0.5)+(V27*H27)))) -> #DIV/0! | X27: =(W27*H27) -> #DIV/0! | Y27: =IF(F27="Sunon Inc",$AJ$577,IF(F27="Alma - Exterior",$AJ$578,IF(F27="Yabo - Hotelería",$AJ$579,IF(F27="OSJ - Medical",$AJ$580,IF(F27="Seezo - Home",$AJ$581,IF(F27="A&D - Home",$AJ$582,IF(F27="Encore Alfombras Hoteleria Asia",$AJ$583,IF(F27="Zhong Xian - Leds",$AJ$584,IF(F27="Tarkett Europa",$AJ$585,IF(F27="2tec2",$AJ$586,IF(F27="Balsan Europa",$AJ$587,IF(F27="Armstrong Pisos USA",$AJ$588,IF(F27="Tarkett USA",$AJ$589,IF(F27="Tarkett Brasil",$AJ$590,IF(F27="Tarkett MX",$AJ$591,IF(F27="Jome",$AJ$592,IF(F27="Offiho",$AJ$593,IF(F27="Lumbro",$AJ$594,IF(F27="Sunon Mty",$AJ$595,IF(F27="Conceptos Sofas",$AJ$596,IF(F27="Lauco Sofas",$AJ$597,IF(F27="CR Global - Mesas Ajustables",$AJ$598,IF(F27="Vandesk",$AJ$599,IF(F27="Mamparas Tela",$AJ$600,IF(F27="Mampara Cristales",$AJ$601,IF(F27="Herrajes",$AJ$602,IF(F27="MetalWork",$AJ$603,IF(F27="Requiez",$AJ$604,IF(F27="Labenze",$AJ$605,IF(F27="Infinity",$AJ$606,IF(F27="Proveedor Externo",$AJ$607))))))))))))))))))))))))))))))) -> FALSE | Z27: 0 | AA27: =W27*Z27 -> #DIV/0! | AB27: =IF(Z27>Y27,"ERROR",(W27-AA27)) -> #DIV/0! | AC27: =AB27*H27 -> #DIV/0! | AD27: =IF(A28=TRUE,MAX(0,1-(AE27/W27)),"NA") -> #DIV/0! | AE27: =IF(A26=FALSE,"NO APLICA",AB27*1.2) -> #DIV/0! | AF27: =AE27*H27 -> #DIV/0! | AG27: =(AC27-N27)/AC27 -> #DIV/0! | AH27: =IF(AG27<30%,"ERROR","OK") -> #DIV/0!
A28: =$A$13 -> TRUE | B28: =A28 -> TRUE | C28: =$C$13 -> Dólares | G28: =IFERROR(VLOOKUP(F28,Tabla_Proveedores_1,2,0)," ") | H28: 0 | I28: =IFERROR(VLOOKUP(G28,Proveedores!B:C,2,0)," ") | J28: 0 | L28: =K28*H28 -> 0 | M28: =IF(F28="Offiho", J28*0.55, IF(AND(F28<>"Sunon Inc",F28<>"Alma - Exterior",F28<>"Yabo - Hotelería",F28<>"OSJ - Medical",F28<>"Seezo - Home",F28<>"A&D -Home",F28<>"Encore Alfombras Hoteleria Asia",F28<>"Zhong Xian - Leds",F28<>"Tarkett Europa",F28<>"2tec2",F28<>"Balsan Europa",F28<>"Armstrong Pisos USA",F28<>"Tarkett USA",F28<>"Tarkett Brasil"),J28,IFERROR(IF(J587<=$AO$578,J28*2.14,IF(J587<=$AN$579,J28*1.8,IF(J587>$AN$580,J28*1.5))),J28))*1.1) -> 0 | N28: =M28*H28 -> 0 | O28: =IFERROR(VLOOKUP(G28,Proveedores!B:D,3,0)," ") | Q28: =VLOOKUP(E28,Tabla_Fletes,3,FALSE) -> #N/A | R28: =IF(P28="Centro",Q28,IF(P28="Norte",Q28*1.6,IF(P28="Occidente",Q28*1.2,IF(P28="Sur",Q28*2)))) -> FALSE | S28: =VLOOKUP(E28,Tabla_Instalacion,2,FALSE) -> #N/A | T28: =IF(P28="Centro",S28,IF(P28="Norte",S28*1.1,IF(P28="Occidente",S28*1.1,IF(P28="Sur",S28*1.1)))) -> FALSE | U28: =IF(F28="Offiho",0,R28+T28) -> 0 | V28: =IF(K28=0,U28/$H$573,U28*(K28/L28))*H28 -> #DIV/0! | W28: =IF(F28="Offiho",J28,IF(_xlfn.XLOOKUP(F28,Proveedores!A$2:A$50,Proveedores!E$2:E$50,"")="Nacional",(J28/0.5)+(V28*H28),((J28/0.3/0.5)+(V28*H28)))) -> #DIV/0! | X28: =(W28*H28) -> #DIV/0! | Y28: =IF(F28="Sunon Inc",$AJ$577,IF(F28="Alma - Exterior",$AJ$578,IF(F28="Yabo - Hotelería",$AJ$579,IF(F28="OSJ - Medical",$AJ$580,IF(F28="Seezo - Home",$AJ$581,IF(F28="A&D - Home",$AJ$582,IF(F28="Encore Alfombras Hoteleria Asia",$AJ$583,IF(F28="Zhong Xian - Leds",$AJ$584,IF(F28="Tarkett Europa",$AJ$585,IF(F28="2tec2",$AJ$586,IF(F28="Balsan Europa",$AJ$587,IF(F28="Armstrong Pisos USA",$AJ$588,IF(F28="Tarkett USA",$AJ$589,IF(F28="Tarkett Brasil",$AJ$590,IF(F28="Tarkett MX",$AJ$591,IF(F28="Jome",$AJ$592,IF(F28="Offiho",$AJ$593,IF(F28="Lumbro",$AJ$594,IF(F28="Sunon Mty",$AJ$595,IF(F28="Conceptos Sofas",$AJ$596,IF(F28="Lauco Sofas",$AJ$597,IF(F28="CR Global - Mesas Ajustables",$AJ$598,IF(F28="Vandesk",$AJ$599,IF(F28="Mamparas Tela",$AJ$600,IF(F28="Mampara Cristales",$AJ$601,IF(F28="Herrajes",$AJ$602,IF(F28="MetalWork",$AJ$603,IF(F28="Requiez",$AJ$604,IF(F28="Labenze",$AJ$605,IF(F28="Infinity",$AJ$606,IF(F28="Proveedor Externo",$AJ$607))))))))))))))))))))))))))))))) -> FALSE | Z28: 0 | AA28: =W28*Z28 -> #DIV/0! | AB28: =IF(Z28>Y28,"ERROR",(W28-AA28)) -> #DIV/0! | AC28: =AB28*H28 -> #DIV/0! | AD28: =IF(A29=TRUE,MAX(0,1-(AE28/W28)),"NA") -> #DIV/0! | AE28: =IF(A27=FALSE,"NO APLICA",AB28*1.2) -> #DIV/0! | AF28: =AE28*H28 -> #DIV/0! | AG28: =(AC28-N28)/AC28 -> #DIV/0! | AH28: =IF(AG28<30%,"ERROR","OK") -> #DIV/0!
A29: =$A$13 -> TRUE | B29: =A29 -> TRUE | C29: =$C$13 -> Dólares | G29: =IFERROR(VLOOKUP(F29,Tabla_Proveedores_1,2,0)," ") | H29: 0 | I29: =IFERROR(VLOOKUP(G29,Proveedores!B:C,2,0)," ") | J29: 0 | L29: =K29*H29 -> 0 | M29: =IF(F29="Offiho", J29*0.55, IF(AND(F29<>"Sunon Inc",F29<>"Alma - Exterior",F29<>"Yabo - Hotelería",F29<>"OSJ - Medical",F29<>"Seezo - Home",F29<>"A&D -Home",F29<>"Encore Alfombras Hoteleria Asia",F29<>"Zhong Xian - Leds",F29<>"Tarkett Europa",F29<>"2tec2",F29<>"Balsan Europa",F29<>"Armstrong Pisos USA",F29<>"Tarkett USA",F29<>"Tarkett Brasil"),J29,IFERROR(IF(J588<=$AO$578,J29*2.14,IF(J588<=$AN$579,J29*1.8,IF(J588>$AN$580,J29*1.5))),J29))*1.1) -> 0 | N29: =M29*H29 -> 0 | O29: =IFERROR(VLOOKUP(G29,Proveedores!B:D,3,0)," ") | Q29: =VLOOKUP(E29,Tabla_Fletes,3,FALSE) -> #N/A | R29: =IF(P29="Centro",Q29,IF(P29="Norte",Q29*1.6,IF(P29="Occidente",Q29*1.2,IF(P29="Sur",Q29*2)))) -> FALSE | S29: =VLOOKUP(E29,Tabla_Instalacion,2,FALSE) -> #N/A | T29: =IF(P29="Centro",S29,IF(P29="Norte",S29*1.1,IF(P29="Occidente",S29*1.1,IF(P29="Sur",S29*1.1)))) -> FALSE | U29: =IF(F29="Offiho",0,R29+T29) -> 0 | V29: =IF(K29=0,U29/$H$573,U29*(K29/L29))*H29 -> #DIV/0! | W29: =IF(F29="Offiho",J29,IF(_xlfn.XLOOKUP(F29,Proveedores!A$2:A$50,Proveedores!E$2:E$50,"")="Nacional",(J29/0.5)+(V29*H29),((J29/0.3/0.5)+(V29*H29)))) -> #DIV/0! | X29: =(W29*H29) -> #DIV/0! | Y29: =IF(F29="Sunon Inc",$AJ$577,IF(F29="Alma - Exterior",$AJ$578,IF(F29="Yabo - Hotelería",$AJ$579,IF(F29="OSJ - Medical",$AJ$580,IF(F29="Seezo - Home",$AJ$581,IF(F29="A&D - Home",$AJ$582,IF(F29="Encore Alfombras Hoteleria Asia",$AJ$583,IF(F29="Zhong Xian - Leds",$AJ$584,IF(F29="Tarkett Europa",$AJ$585,IF(F29="2tec2",$AJ$586,IF(F29="Balsan Europa",$AJ$587,IF(F29="Armstrong Pisos USA",$AJ$588,IF(F29="Tarkett USA",$AJ$589,IF(F29="Tarkett Brasil",$AJ$590,IF(F29="Tarkett MX",$AJ$591,IF(F29="Jome",$AJ$592,IF(F29="Offiho",$AJ$593,IF(F29="Lumbro",$AJ$594,IF(F29="Sunon Mty",$AJ$595,IF(F29="Conceptos Sofas",$AJ$596,IF(F29="Lauco Sofas",$AJ$597,IF(F29="CR Global - Mesas Ajustables",$AJ$598,IF(F29="Vandesk",$AJ$599,IF(F29="Mamparas Tela",$AJ$600,IF(F29="Mampara Cristales",$AJ$601,IF(F29="Herrajes",$AJ$602,IF(F29="MetalWork",$AJ$603,IF(F29="Requiez",$AJ$604,IF(F29="Labenze",$AJ$605,IF(F29="Infinity",$AJ$606,IF(F29="Proveedor Externo",$AJ$607))))))))))))))))))))))))))))))) -> FALSE | Z29: 0 | AA29: =W29*Z29 -> #DIV/0! | AB29: =IF(Z29>Y29,"ERROR",(W29-AA29)) -> #DIV/0! | AC29: =AB29*H29 -> #DIV/0! | AD29: =IF(A30=TRUE,MAX(0,1-(AE29/W29)),"NA") -> #DIV/0! | AE29: =IF(A28=FALSE,"NO APLICA",AB29*1.2) -> #DIV/0! | AF29: =AE29*H29 -> #DIV/0! | AG29: =(AC29-N29)/AC29 -> #DIV/0! | AH29: =IF(AG29<30%,"ERROR","OK") -> #DIV/0!
A30: =$A$13 -> TRUE | B30: =A30 -> TRUE | C30: =$C$13 -> Dólares | G30: =IFERROR(VLOOKUP(F30,Tabla_Proveedores_1,2,0)," ") | H30: 0 | I30: =IFERROR(VLOOKUP(G30,Proveedores!B:C,2,0)," ") | J30: 0 | L30: =K30*H30 -> 0 | M30: =IF(F30="Offiho", J30*0.55, IF(AND(F30<>"Sunon Inc",F30<>"Alma - Exterior",F30<>"Yabo - Hotelería",F30<>"OSJ - Medical",F30<>"Seezo - Home",F30<>"A&D -Home",F30<>"Encore Alfombras Hoteleria Asia",F30<>"Zhong Xian - Leds",F30<>"Tarkett Europa",F30<>"2tec2",F30<>"Balsan Europa",F30<>"Armstrong Pisos USA",F30<>"Tarkett USA",F30<>"Tarkett Brasil"),J30,IFERROR(IF(J589<=$AO$578,J30*2.14,IF(J589<=$AN$579,J30*1.8,IF(J589>$AN$580,J30*1.5))),J30))*1.1) -> 0 | N30: =M30*H30 -> 0 | O30: =IFERROR(VLOOKUP(G30,Proveedores!B:D,3,0)," ") | Q30: =VLOOKUP(E30,Tabla_Fletes,3,FALSE) -> #N/A | R30: =IF(P30="Centro",Q30,IF(P30="Norte",Q30*1.6,IF(P30="Occidente",Q30*1.2,IF(P30="Sur",Q30*2)))) -> FALSE | S30: =VLOOKUP(E30,Tabla_Instalacion,2,FALSE) -> #N/A | T30: =IF(P30="Centro",S30,IF(P30="Norte",S30*1.1,IF(P30="Occidente",S30*1.1,IF(P30="Sur",S30*1.1)))) -> FALSE | U30: =IF(F30="Offiho",0,R30+T30) -> 0 | V30: =IF(K30=0,U30/$H$573,U30*(K30/L30))*H30 -> #DIV/0! | W30: =IF(F30="Offiho",J30,IF(_xlfn.XLOOKUP(F30,Proveedores!A$2:A$50,Proveedores!E$2:E$50,"")="Nacional",(J30/0.5)+(V30*H30),((J30/0.3/0.5)+(V30*H30)))) -> #DIV/0! | X30: =(W30*H30) -> #DIV/0! | Y30: =IF(F30="Sunon Inc",$AJ$577,IF(F30="Alma - Exterior",$AJ$578,IF(F30="Yabo - Hotelería",$AJ$579,IF(F30="OSJ - Medical",$AJ$580,IF(F30="Seezo - Home",$AJ$581,IF(F30="A&D - Home",$AJ$582,IF(F30="Encore Alfombras Hoteleria Asia",$AJ$583,IF(F30="Zhong Xian - Leds",$AJ$584,IF(F30="Tarkett Europa",$AJ$585,IF(F30="2tec2",$AJ$586,IF(F30="Balsan Europa",$AJ$587,IF(F30="Armstrong Pisos USA",$AJ$588,IF(F30="Tarkett USA",$AJ$589,IF(F30="Tarkett Brasil",$AJ$590,IF(F30="Tarkett MX",$AJ$591,IF(F30="Jome",$AJ$592,IF(F30="Offiho",$AJ$593,IF(F30="Lumbro",$AJ$594,IF(F30="Sunon Mty",$AJ$595,IF(F30="Conceptos Sofas",$AJ$596,IF(F30="Lauco Sofas",$AJ$597,IF(F30="CR Global - Mesas Ajustables",$AJ$598,IF(F30="Vandesk",$AJ$599,IF(F30="Mamparas Tela",$AJ$600,IF(F30="Mampara Cristales",$AJ$601,IF(F30="Herrajes",$AJ$602,IF(F30="MetalWork",$AJ$603,IF(F30="Requiez",$AJ$604,IF(F30="Labenze",$AJ$605,IF(F30="Infinity",$AJ$606,IF(F30="Proveedor Externo",$AJ$607))))))))))))))))))))))))))))))) -> FALSE | Z30: 0 | AA30: =W30*Z30 -> #DIV/0! | AB30: =IF(Z30>Y30,"ERROR",(W30-AA30)) -> #DIV/0! | AC30: =AB30*H30 -> #DIV/0! | AD30: =IF(A31=TRUE,MAX(0,1-(AE30/W30)),"NA") -> #DIV/0! | AE30: =IF(A29=FALSE,"NO APLICA",AB30*1.2) -> #DIV/0! | AF30: =AE30*H30 -> #DIV/0! | AG30: =(AC30-N30)/AC30 -> #DIV/0! | AH30: =IF(AG30<30%,"ERROR","OK") -> #DIV/0!
A31: =$A$13 -> TRUE | B31: =A31 -> TRUE | C31: =$C$13 -> Dólares | G31: =IFERROR(VLOOKUP(F31,Tabla_Proveedores_1,2,0)," ") | H31: 0 | I31: =IFERROR(VLOOKUP(G31,Proveedores!B:C,2,0)," ") | J31: 0 | L31: =K31*H31 -> 0 | M31: =IF(F31="Offiho", J31*0.55, IF(AND(F31<>"Sunon Inc",F31<>"Alma - Exterior",F31<>"Yabo - Hotelería",F31<>"OSJ - Medical",F31<>"Seezo - Home",F31<>"A&D -Home",F31<>"Encore Alfombras Hoteleria Asia",F31<>"Zhong Xian - Leds",F31<>"Tarkett Europa",F31<>"2tec2",F31<>"Balsan Europa",F31<>"Armstrong Pisos USA",F31<>"Tarkett USA",F31<>"Tarkett Brasil"),J31,IFERROR(IF(J590<=$AO$578,J31*2.14,IF(J590<=$AN$579,J31*1.8,IF(J590>$AN$580,J31*1.5))),J31))*1.1) -> 0 | N31: =M31*H31 -> 0 | O31: =IFERROR(VLOOKUP(G31,Proveedores!B:D,3,0)," ") | Q31: =VLOOKUP(E31,Tabla_Fletes,3,FALSE) -> #N/A | R31: =IF(P31="Centro",Q31,IF(P31="Norte",Q31*1.6,IF(P31="Occidente",Q31*1.2,IF(P31="Sur",Q31*2)))) -> FALSE | S31: =VLOOKUP(E31,Tabla_Instalacion,2,FALSE) -> #N/A | T31: =IF(P31="Centro",S31,IF(P31="Norte",S31*1.1,IF(P31="Occidente",S31*1.1,IF(P31="Sur",S31*1.1)))) -> FALSE | U31: =IF(F31="Offiho",0,R31+T31) -> 0 | V31: =IF(K31=0,U31/$H$573,U31*(K31/L31))*H31 -> #DIV/0! | W31: =IF(F31="Offiho",J31,IF(_xlfn.XLOOKUP(F31,Proveedores!A$2:A$50,Proveedores!E$2:E$50,"")="Nacional",(J31/0.5)+(V31*H31),((J31/0.3/0.5)+(V31*H31)))) -> #DIV/0! | X31: =(W31*H31) -> #DIV/0! | Y31: =IF(F31="Sunon Inc",$AJ$577,IF(F31="Alma - Exterior",$AJ$578,IF(F31="Yabo - Hotelería",$AJ$579,IF(F31="OSJ - Medical",$AJ$580,IF(F31="Seezo - Home",$AJ$581,IF(F31="A&D - Home",$AJ$582,IF(F31="Encore Alfombras Hoteleria Asia",$AJ$583,IF(F31="Zhong Xian - Leds",$AJ$584,IF(F31="Tarkett Europa",$AJ$585,IF(F31="2tec2",$AJ$586,IF(F31="Balsan Europa",$AJ$587,IF(F31="Armstrong Pisos USA",$AJ$588,IF(F31="Tarkett USA",$AJ$589,IF(F31="Tarkett Brasil",$AJ$590,IF(F31="Tarkett MX",$AJ$591,IF(F31="Jome",$AJ$592,IF(F31="Offiho",$AJ$593,IF(F31="Lumbro",$AJ$594,IF(F31="Sunon Mty",$AJ$595,IF(F31="Conceptos Sofas",$AJ$596,IF(F31="Lauco Sofas",$AJ$597,IF(F31="CR Global - Mesas Ajustables",$AJ$598,IF(F31="Vandesk",$AJ$599,IF(F31="Mamparas Tela",$AJ$600,IF(F31="Mampara Cristales",$AJ$601,IF(F31="Herrajes",$AJ$602,IF(F31="MetalWork",$AJ$603,IF(F31="Requiez",$AJ$604,IF(F31="Labenze",$AJ$605,IF(F31="Infinity",$AJ$606,IF(F31="Proveedor Externo",$AJ$607))))))))))))))))))))))))))))))) -> FALSE | Z31: 0 | AA31: =W31*Z31 -> #DIV/0! | AB31: =IF(Z31>Y31,"ERROR",(W31-AA31)) -> #DIV/0! | AC31: =AB31*H31 -> #DIV/0! | AD31: =IF(A32=TRUE,MAX(0,1-(AE31/W31)),"NA") -> #DIV/0! | AE31: =IF(A30=FALSE,"NO APLICA",AB31*1.2) -> #DIV/0! | AF31: =AE31*H31 -> #DIV/0! | AG31: =(AC31-N31)/AC31 -> #DIV/0! | AH31: =IF(AG31<30%,"ERROR","OK") -> #DIV/0!
... A46: =$A$13 -> TRUE | B46: =A46 -> TRUE | C46: =$C$13 -> Dólares | G46: =IFERROR(VLOOKUP(F46,Tabla_Proveedores_1,2,0)," ") | H46: 0 | I46: =IFERROR(VLOOKUP(G46,Proveedores!B:C,2,0)," ") | J46: 0 | L46: =K46*H46 -> 0 | M46: =IF(F46="Offiho", J46*0.55, IF(AND(F46<>"Sunon Inc",F46<>"Alma - Exterior",F46<>"Yabo - Hotelería",F46<>"OSJ - Medical",F46<>"Seezo - Home",F46<>"A&D -Home",F46<>"Encore Alfombras Hoteleria Asia",F46<>"Zhong Xian - Leds",F46<>"Tarkett Europa",F46<>"2tec2",F46<>"Balsan Europa",F46<>"Armstrong Pisos USA",F46<>"Tarkett USA",F46<>"Tarkett Brasil"),J46,IFERROR(IF(J605<=$AO$578,J46*2.14,IF(J605<=$AN$579,J46*1.8,IF(J605>$AN$580,J46*1.5))),J46))*1.1) -> 0 | N46: =M46*H46 -> 0 | O46: =IFERROR(VLOOKUP(G46,Proveedores!B:D,3,0)," ") | Q46: =VLOOKUP(E46,Tabla_Fletes,3,FALSE) -> #N/A | R46: =IF(P46="Centro",Q46,IF(P46="Norte",Q46*1.6,IF(P46="Occidente",Q46*1.2,IF(P46="Sur",Q46*2)))) -> FALSE | S46: =VLOOKUP(E46,Tabla_Instalacion,2,FALSE) -> #N/A | T46: =IF(P46="Centro",S46,IF(P46="Norte",S46*1.1,IF(P46="Occidente",S46*1.1,IF(P46="Sur",S46*1.1)))) -> FALSE | U46: =IF(F46="Offiho",0,R46+T46) -> 0 | V46: =IF(K46=0,U46/$H$573,U46*(K46/L46))*H46 -> #DIV/0! | W46: =IF(F46="Offiho",J46,IF(_xlfn.XLOOKUP(F46,Proveedores!A$2:A$50,Proveedores!E$2:E$50,"")="Nacional",(J46/0.5)+(V46*H46),((J46/0.3/0.5)+(V46*H46)))) -> #DIV/0! | X46: =(W46*H46) -> #DIV/0! | Y46: =IF(F46="Sunon Inc",$AJ$577,IF(F46="Alma - Exterior",$AJ$578,IF(F46="Yabo - Hotelería",$AJ$579,IF(F46="OSJ - Medical",$AJ$580,IF(F46="Seezo - Home",$AJ$581,IF(F46="A&D - Home",$AJ$582,IF(F46="Encore Alfombras Hoteleria Asia",$AJ$583,IF(F46="Zhong Xian - Leds",$AJ$584,IF(F46="Tarkett Europa",$AJ$585,IF(F46="2tec2",$AJ$586,IF(F46="Balsan Europa",$AJ$587,IF(F46="Armstrong Pisos USA",$AJ$588,IF(F46="Tarkett USA",$AJ$589,IF(F46="Tarkett Brasil",$AJ$590,IF(F46="Tarkett MX",$AJ$591,IF(F46="Jome",$AJ$592,IF(F46="Offiho",$AJ$593,IF(F46="Lumbro",$AJ$594,IF(F46="Sunon Mty",$AJ$595,IF(F46="Conceptos Sofas",$AJ$596,IF(F46="Lauco Sofas",$AJ$597,IF(F46="CR Global - Mesas Ajustables",$AJ$598,IF(F46="Vandesk",$AJ$599,IF(F46="Mamparas Tela",$AJ$600,IF(F46="Mampara Cristales",$AJ$601,IF(F46="Herrajes",$AJ$602,IF(F46="MetalWork",$AJ$603,IF(F46="Requiez",$AJ$604,IF(F46="Labenze",$AJ$605,IF(F46="Infinity",$AJ$606,IF(F46="Proveedor Externo",$AJ$607))))))))))))))))))))))))))))))) -> FALSE | Z46: 0 | AA46: =W46*Z46 -> #DIV/0! | AB46: =IF(Z46>Y46,"ERROR",(W46-AA46)) -> #DIV/0! | AC46: =AB46*H46 -> #DIV/0! | AD46: =IF(A47=TRUE,MAX(0,1-(AE46/W46)),"NA") -> NA | AE46: =IF(A45=FALSE,"NO APLICA",AB46*1.2) -> #DIV/0! | AF46: =AE46*H46 -> #DIV/0! | AG46: =(AC46-N46)/AC46 -> #DIV/0! | AH46: =IF(AG46<30%,"ERROR","OK") -> #DIV/0!
A47: Subtotales Sección 1 | H47: {=SUM(IFERROR(H14:H46,0))} -> 0 | L47: {=SUM(IFERROR(L14:L46,0))} -> 0 | N47: {=SUM(IFERROR(N14:N46,0))} -> 0 | X47: {=SUM(IFERROR(X14:X46,0))} -> 0 | AC47: {=SUM(IFERROR(AC14:AC46,0))} -> 0 | AD47: {=AVERAGE(IFERROR(AD14:AD46,""))} -> #DIV/0! | AF47: {=SUM(IFERROR(AF14:AF46,0))} -> 0 | AG47: =IFERROR(1-(N47/AC47),0) -> 0
A48: Sección 2 - NOMBRE
A49: =$A$13 -> TRUE | B49: =A49 -> TRUE | C49: =$C$13 -> Dólares | G49: =IFERROR(VLOOKUP(F49,Tabla_Proveedores_1,2,0)," ") | H49: 0 | I49: =IFERROR(VLOOKUP(G49,Proveedores!B:C,2,0)," ") | J49: 0 | K49: =#REF! -> #REF! | L49: =K49*H49 -> #REF! | M49: =IF(F49="Offiho", J49*0.55, IF(AND(F49<>"Sunon Inc",F49<>"Alma - Exterior",F49<>"Yabo - Hotelería",F49<>"OSJ - Medical",F49<>"Seezo - Home",F49<>"A&D -Home",F49<>"Encore Alfombras Hoteleria Asia",F49<>"Zhong Xian - Leds",F49<>"Tarkett Europa",F49<>"2tec2",F49<>"Balsan Europa",F49<>"Armstrong Pisos USA",F49<>"Tarkett USA",F49<>"Tarkett Brasil"),J49,IFERROR(IF(K608<=$AO$578,J49*2.14,IF(K608<=$AN$579,J49*1.8,IF(K608>$AN$580,J49*1.5))),J49))*1.1) -> 0 | N49: =M49*H49 -> 0 | O49: =IFERROR(VLOOKUP(G49,Proveedores!B:D,3,0)," ") | Q49: =VLOOKUP(E49,Tabla_Fletes,3,FALSE) -> #N/A | R49: =IF(P49="Centro",Q49,IF(P49="Norte",Q49*1.6,IF(P49="Occidente",Q49*1.2,IF(P49="Sur",Q49*2)))) -> FALSE | S49: =VLOOKUP(E49,Tabla_Instalacion,2,FALSE) -> #N/A | T49: =IF(P49="Centro",S49,IF(P49="Norte",S49*1.1,IF(P49="Occidente",S49*1.1,IF(P49="Sur",S49*1.1)))) -> FALSE | U49: =IF(F49="Offiho",0,Q49+S49) -> #N/A | V49: =IF(K49=0,U49/$H$573,U49*(K49/L49))*H49 -> #REF! | W49: =IF(F49="Offiho",J49,IF(_xlfn.XLOOKUP(F49,Proveedores!A$2:A$50,Proveedores!E$2:E$50,"")="Nacional",(J49/0.5)+(V49*H49),((J49/0.3/0.5)+(V49*H49)))) -> #REF! | X49: =W49*H49 -> #REF! | Y49: =IF(F49="Sunon Inc",$AJ$577,IF(F49="Alma - Exterior",$AJ$578,IF(F49="Yabo - Hotelería",$AJ$579,IF(F49="OSJ - Medical",$AJ$580,IF(F49="Seezo - Home",$AJ$581,IF(F49="A&D - Home",$AJ$582,IF(F49="Encore Alfombras Hoteleria Asia",$AJ$583,IF(F49="Zhong Xian - Leds",$AJ$584,IF(F49="Tarkett Europa",$AJ$585,IF(F49="2tec2",$AJ$586,IF(F49="Balsan Europa",$AJ$587,IF(F49="Armstrong Pisos USA",$AJ$588,IF(F49="Tarkett USA",$AJ$589,IF(F49="Tarkett Brasil",$AJ$590,IF(F49="Tarkett MX",$AJ$591,IF(F49="Jome",$AJ$592,IF(F49="Offiho",$AJ$593,IF(F49="Lumbro",$AJ$594,IF(F49="Sunon Mty",$AJ$595,IF(F49="Conceptos Sofas",$AJ$596,IF(F49="Lauco Sofas",$AJ$597,IF(F49="CR Global - Mesas Ajustables",$AJ$598,IF(F49="Vandesk",$AJ$599,IF(F49="Mamparas Tela",$AJ$600,IF(F49="Mampara Cristales",$AJ$601,IF(F49="Herrajes",$AJ$602,IF(F49="MetalWork",$AJ$603,IF(F49="Requiez",$AJ$604,IF(F49="Labenze",$AJ$605,IF(F49="Infinity",$AJ$606,IF(F49="Proveedor Externo",$AJ$607))))))))))))))))))))))))))))))) -> FALSE | Z49: 0 | AA49: =W49*Z49 -> #REF! | AB49: =IF(Z49>Y49,"ERROR",(W49-AA49)) -> #REF! | AC49: =AB49*H49 -> #REF! | AD49: =IF(A50=TRUE,MAX(0,1-(AE49/W49)),"NA") -> #REF! | AE49: =IF(A48=FALSE,"NO APLICA",AB49*1.2) -> #REF! | AF49: =AE49*H49 -> #REF! | AG49: =(AC49-N49)/AC49 -> #REF! | AH49: =IF(AG49<30%,"ERROR","OK") -> #REF!
A50: =$A$13 -> TRUE | B50: =A50 -> TRUE | C50: =$C$13 -> Dólares | G50: =IFERROR(VLOOKUP(F50,Tabla_Proveedores_1,2,0)," ") | H50: 0 | I50: =IFERROR(VLOOKUP(G50,Proveedores!B:C,2,0)," ") | J50: 0 | K50: =#REF! -> #REF! | L50: =K50*H50 -> #REF! | M50: =IF(F50="Offiho", J50*0.55, IF(AND(F50<>"Sunon Inc",F50<>"Alma - Exterior",F50<>"Yabo - Hotelería",F50<>"OSJ - Medical",F50<>"Seezo - Home",F50<>"A&D -Home",F50<>"Encore Alfombras Hoteleria Asia",F50<>"Zhong Xian - Leds",F50<>"Tarkett Europa",F50<>"2tec2",F50<>"Balsan Europa",F50<>"Armstrong Pisos USA",F50<>"Tarkett USA",F50<>"Tarkett Brasil"),J50,IFERROR(IF(K609<=$AO$578,J50*2.14,IF(K609<=$AN$579,J50*1.8,IF(K609>$AN$580,J50*1.5))),J50))*1.1) -> 0 | N50: =M50*H50 -> 0 | O50: =IFERROR(VLOOKUP(G50,Proveedores!B:D,3,0)," ") | Q50: =VLOOKUP(E50,Tabla_Fletes,3,FALSE) -> #N/A | R50: =IF(P50="Centro",Q50,IF(P50="Norte",Q50*1.6,IF(P50="Occidente",Q50*1.2,IF(P50="Sur",Q50*2)))) -> FALSE | S50: =VLOOKUP(E50,Tabla_Instalacion,2,FALSE) -> #N/A | T50: =IF(P50="Centro",S50,IF(P50="Norte",S50*1.1,IF(P50="Occidente",S50*1.1,IF(P50="Sur",S50*1.1)))) -> FALSE | U50: =IF(F50="Offiho",0,Q50+S50) -> #N/A | V50: =IF(K50=0,U50/$H$573,U50*(K50/L50))*H50 -> #REF! | W50: =IF(F50="Offiho",J50,IF(_xlfn.XLOOKUP(F50,Proveedores!A$2:A$50,Proveedores!E$2:E$50,"")="Nacional",(J50/0.5)+(V50*H50),((J50/0.3/0.5)+(V50*H50)))) -> #REF! | X50: =W50*H50 -> #REF! | Y50: =IF(F50="Sunon Inc",$AJ$577,IF(F50="Alma - Exterior",$AJ$578,IF(F50="Yabo - Hotelería",$AJ$579,IF(F50="OSJ - Medical",$AJ$580,IF(F50="Seezo - Home",$AJ$581,IF(F50="A&D - Home",$AJ$582,IF(F50="Encore Alfombras Hoteleria Asia",$AJ$583,IF(F50="Zhong Xian - Leds",$AJ$584,IF(F50="Tarkett Europa",$AJ$585,IF(F50="2tec2",$AJ$586,IF(F50="Balsan Europa",$AJ$587,IF(F50="Armstrong Pisos USA",$AJ$588,IF(F50="Tarkett USA",$AJ$589,IF(F50="Tarkett Brasil",$AJ$590,IF(F50="Tarkett MX",$AJ$591,IF(F50="Jome",$AJ$592,IF(F50="Offiho",$AJ$593,IF(F50="Lumbro",$AJ$594,IF(F50="Sunon Mty",$AJ$595,IF(F50="Conceptos Sofas",$AJ$596,IF(F50="Lauco Sofas",$AJ$597,IF(F50="CR Global - Mesas Ajustables",$AJ$598,IF(F50="Vandesk",$AJ$599,IF(F50="Mamparas Tela",$AJ$600,IF(F50="Mampara Cristales",$AJ$601,IF(F50="Herrajes",$AJ$602,IF(F50="MetalWork",$AJ$603,IF(F50="Requiez",$AJ$604,IF(F50="Labenze",$AJ$605,IF(F50="Infinity",$AJ$606,IF(F50="Proveedor Externo",$AJ$607))))))))))))))))))))))))))))))) -> FALSE | Z50: 0 | AA50: =W50*Z50 -> #REF! | AB50: =IF(Z50>Y50,"ERROR",(W50-AA50)) -> #REF! | AC50: =AB50*H50 -> #REF! | AD50: =IF(A51=TRUE,MAX(0,1-(AE50/W50)),"NA") -> #REF! | AE50: =IF(A49=FALSE,"NO APLICA",AB50*1.2) -> #REF! | AF50: =AE50*H50 -> #REF! | AG50: =(AC50-N50)/AC50 -> #REF! | AH50: =IF(AG50<30%,"ERROR","OK") -> #REF!
A51: =$A$13 -> TRUE | B51: =A51 -> TRUE | C51: =$C$13 -> Dólares | G51: =IFERROR(VLOOKUP(F51,Tabla_Proveedores_1,2,0)," ") | H51: 0 | I51: =IFERROR(VLOOKUP(G51,Proveedores!B:C,2,0)," ") | J51: 0 | K51: =#REF! -> #REF! | L51: =K51*H51 -> #REF! | M51: =IF(F51="Offiho", J51*0.55, IF(AND(F51<>"Sunon Inc",F51<>"Alma - Exterior",F51<>"Yabo - Hotelería",F51<>"OSJ - Medical",F51<>"Seezo - Home",F51<>"A&D -Home",F51<>"Encore Alfombras Hoteleria Asia",F51<>"Zhong Xian - Leds",F51<>"Tarkett Europa",F51<>"2tec2",F51<>"Balsan Europa",F51<>"Armstrong Pisos USA",F51<>"Tarkett USA",F51<>"Tarkett Brasil"),J51,IFERROR(IF(K610<=$AO$578,J51*2.14,IF(K610<=$AN$579,J51*1.8,IF(K610>$AN$580,J51*1.5))),J51))*1.1) -> 0 | N51: =(M51*H51) -> 0 | O51: =IFERROR(VLOOKUP(G51,Proveedores!B:D,3,0)," ") | Q51: =VLOOKUP(E51,Tabla_Fletes,3,FALSE) -> #N/A | R51: =IF(P51="Centro",Q51,IF(P51="Norte",Q51*1.6,IF(P51="Occidente",Q51*1.2,IF(P51="Sur",Q51*2)))) -> FALSE | S51: =VLOOKUP(E51,Tabla_Instalacion,2,FALSE) -> #N/A | T51: =IF(P51="Centro",S51,IF(P51="Norte",S51*1.1,IF(P51="Occidente",S51*1.1,IF(P51="Sur",S51*1.1)))) -> FALSE | U51: =IF(F51="Offiho",0,Q51+S51) -> #N/A | V51: =IF(K51=0,U51/$H$573,U51*(K51/L51))*H51 -> #REF! | W51: =IF(F51="Offiho",J51,IF(_xlfn.XLOOKUP(F51,Proveedores!A$2:A$50,Proveedores!E$2:E$50,"")="Nacional",(J51/0.5)+(V51*H51),((J51/0.3/0.5)+(V51*H51)))) -> #REF! | X51: =W51*H51 -> #REF! | Y51: =IF(F51="Sunon Inc",$AJ$577,IF(F51="Alma - Exterior",$AJ$578,IF(F51="Yabo - Hotelería",$AJ$579,IF(F51="OSJ - Medical",$AJ$580,IF(F51="Seezo - Home",$AJ$581,IF(F51="A&D - Home",$AJ$582,IF(F51="Encore Alfombras Hoteleria Asia",$AJ$583,IF(F51="Zhong Xian - Leds",$AJ$584,IF(F51="Tarkett Europa",$AJ$585,IF(F51="2tec2",$AJ$586,IF(F51="Balsan Europa",$AJ$587,IF(F51="Armstrong Pisos USA",$AJ$588,IF(F51="Tarkett USA",$AJ$589,IF(F51="Tarkett Brasil",$AJ$590,IF(F51="Tarkett MX",$AJ$591,IF(F51="Jome",$AJ$592,IF(F51="Offiho",$AJ$593,IF(F51="Lumbro",$AJ$594,IF(F51="Sunon Mty",$AJ$595,IF(F51="Conceptos Sofas",$AJ$596,IF(F51="Lauco Sofas",$AJ$597,IF(F51="CR Global - Mesas Ajustables",$AJ$598,IF(F51="Vandesk",$AJ$599,IF(F51="Mamparas Tela",$AJ$600,IF(F51="Mampara Cristales",$AJ$601,IF(F51="Herrajes",$AJ$602,IF(F51="MetalWork",$AJ$603,IF(F51="Requiez",$AJ$604,IF(F51="Labenze",$AJ$605,IF(F51="Infinity",$AJ$606,IF(F51="Proveedor Externo",$AJ$607))))))))))))))))))))))))))))))) -> FALSE | Z51: 0 | AA51: =W51*Z51 -> #REF! | AB51: =IF(Z51>Y51,"ERROR",(W51-AA51)) -> #REF! | AC51: =AB51*H51 -> #REF! | AD51: =IF(A52=TRUE,MAX(0,1-(AE51/W51)),"NA") -> #REF! | AE51: =IF(A50=FALSE,"NO APLICA",AB51*1.2) -> #REF! | AF51: =AE51*H51 -> #REF! | AG51: =(AC51-N51)/AC51 -> #REF! | AH51: =IF(AG51<30%,"ERROR","OK") -> #REF!
A52: =$A$13 -> TRUE | B52: =A52 -> TRUE | C52: =$C$13 -> Dólares | G52: =IFERROR(VLOOKUP(F52,Tabla_Proveedores_1,2,0)," ") | H52: 0 | I52: =IFERROR(VLOOKUP(G52,Proveedores!B:C,2,0)," ") | J52: 0 | K52: =#REF! -> #REF! | L52: =K52*H52 -> #REF! | M52: =IF(F52="Offiho", J52*0.55, IF(AND(F52<>"Sunon Inc",F52<>"Alma - Exterior",F52<>"Yabo - Hotelería",F52<>"OSJ - Medical",F52<>"Seezo - Home",F52<>"A&D -Home",F52<>"Encore Alfombras Hoteleria Asia",F52<>"Zhong Xian - Leds",F52<>"Tarkett Europa",F52<>"2tec2",F52<>"Balsan Europa",F52<>"Armstrong Pisos USA",F52<>"Tarkett USA",F52<>"Tarkett Brasil"),J52,IFERROR(IF(K611<=$AO$578,J52*2.14,IF(K611<=$AN$579,J52*1.8,IF(K611>$AN$580,J52*1.5))),J52))*1.1) -> 0 | N52: =M52*H52 -> 0 | O52: =IFERROR(VLOOKUP(G52,Proveedores!B:D,3,0)," ") | Q52: =VLOOKUP(E52,Tabla_Fletes,3,FALSE) -> #N/A | R52: =IF(P52="Centro",Q52,IF(P52="Norte",Q52*1.6,IF(P52="Occidente",Q52*1.2,IF(P52="Sur",Q52*2)))) -> FALSE | S52: =VLOOKUP(E52,Tabla_Instalacion,2,FALSE) -> #N/A | T52: =IF(P52="Centro",S52,IF(P52="Norte",S52*1.1,IF(P52="Occidente",S52*1.1,IF(P52="Sur",S52*1.1)))) -> FALSE | U52: =IF(F52="Offiho",0,Q52+S52) -> #N/A | V52: =IF(K52=0,U52/$H$573,U52*(K52/L52))*H52 -> #REF! | W52: =IF(F52="Offiho",J52,IF(_xlfn.XLOOKUP(F52,Proveedores!A$2:A$50,Proveedores!E$2:E$50,"")="Nacional",(J52/0.5)+(V52*H52),((J52/0.3/0.5)+(V52*H52)))) -> #REF! | X52: =W52*H52 -> #REF! | Y52: =IF(F52="Sunon Inc",$AJ$577,IF(F52="Alma - Exterior",$AJ$578,IF(F52="Yabo - Hotelería",$AJ$579,IF(F52="OSJ - Medical",$AJ$580,IF(F52="Seezo - Home",$AJ$581,IF(F52="A&D - Home",$AJ$582,IF(F52="Encore Alfombras Hoteleria Asia",$AJ$583,IF(F52="Zhong Xian - Leds",$AJ$584,IF(F52="Tarkett Europa",$AJ$585,IF(F52="2tec2",$AJ$586,IF(F52="Balsan Europa",$AJ$587,IF(F52="Armstrong Pisos USA",$AJ$588,IF(F52="Tarkett USA",$AJ$589,IF(F52="Tarkett Brasil",$AJ$590,IF(F52="Tarkett MX",$AJ$591,IF(F52="Jome",$AJ$592,IF(F52="Offiho",$AJ$593,IF(F52="Lumbro",$AJ$594,IF(F52="Sunon Mty",$AJ$595,IF(F52="Conceptos Sofas",$AJ$596,IF(F52="Lauco Sofas",$AJ$597,IF(F52="CR Global - Mesas Ajustables",$AJ$598,IF(F52="Vandesk",$AJ$599,IF(F52="Mamparas Tela",$AJ$600,IF(F52="Mampara Cristales",$AJ$601,IF(F52="Herrajes",$AJ$602,IF(F52="MetalWork",$AJ$603,IF(F52="Requiez",$AJ$604,IF(F52="Labenze",$AJ$605,IF(F52="Infinity",$AJ$606,IF(F52="Proveedor Externo",$AJ$607))))))))))))))))))))))))))))))) -> FALSE | Z52: 0 | AA52: =W52*Z52 -> #REF! | AB52: =IF(Z52>Y52,"ERROR",(W52-AA52)) -> #REF! | AC52: =AB52*H52 -> #REF! | AD52: =IF(A53=TRUE,MAX(0,1-(AE52/W52)),"NA") -> #REF! | AE52: =IF(A51=FALSE,"NO APLICA",AB52*1.2) -> #REF! | AF52: =AE52*H52 -> #REF! | AG52: =(AC52-N52)/AC52 -> #REF! | AH52: =IF(AG52<30%,"ERROR","OK") -> #REF!
A53: =$A$13 -> TRUE | B53: =A53 -> TRUE | C53: =$C$13 -> Dólares | G53: =IFERROR(VLOOKUP(F53,Tabla_Proveedores_1,2,0)," ") | H53: 0 | I53: =IFERROR(VLOOKUP(G53,Proveedores!B:C,2,0)," ") | J53: 0 | K53: =#REF! -> #REF! | L53: =K53*H53 -> #REF! | M53: =IF(F53="Offiho", J53*0.55, IF(AND(F53<>"Sunon Inc",F53<>"Alma - Exterior",F53<>"Yabo - Hotelería",F53<>"OSJ - Medical",F53<>"Seezo - Home",F53<>"A&D -Home",F53<>"Encore Alfombras Hoteleria Asia",F53<>"Zhong Xian - Leds",F53<>"Tarkett Europa",F53<>"2tec2",F53<>"Balsan Europa",F53<>"Armstrong Pisos USA",F53<>"Tarkett USA",F53<>"Tarkett Brasil"),J53,IFERROR(IF(K612<=$AO$578,J53*2.14,IF(K612<=$AN$579,J53*1.8,IF(K612>$AN$580,J53*1.5))),J53))*1.1) -> 0 | N53: =M53*H53 -> 0 | O53: =IFERROR(VLOOKUP(G53,Proveedores!B:D,3,0)," ") | Q53: =VLOOKUP(E53,Tabla_Fletes,3,FALSE) -> #N/A | R53: =IF(P53="Centro",Q53,IF(P53="Norte",Q53*1.6,IF(P53="Occidente",Q53*1.2,IF(P53="Sur",Q53*2)))) -> FALSE | S53: =VLOOKUP(E53,Tabla_Instalacion,2,FALSE) -> #N/A | T53: =IF(P53="Centro",S53,IF(P53="Norte",S53*1.1,IF(P53="Occidente",S53*1.1,IF(P53="Sur",S53*1.1)))) -> FALSE | U53: =IF(F53="Offiho",0,Q53+S53) -> #N/A | V53: =IF(K53=0,U53/$H$573,U53*(K53/L53))*H53 -> #REF! | W53: =IF(F53="Offiho",J53,IF(_xlfn.XLOOKUP(F53,Proveedores!A$2:A$50,Proveedores!E$2:E$50,"")="Nacional",(J53/0.5)+(V53*H53),((J53/0.3/0.5)+(V53*H53)))) -> #REF! | X53: =W53*H53 -> #REF! | Y53: =IF(F53="Sunon Inc",$AJ$577,IF(F53="Alma - Exterior",$AJ$578,IF(F53="Yabo - Hotelería",$AJ$579,IF(F53="OSJ - Medical",$AJ$580,IF(F53="Seezo - Home",$AJ$581,IF(F53="A&D - Home",$AJ$582,IF(F53="Encore Alfombras Hoteleria Asia",$AJ$583,IF(F53="Zhong Xian - Leds",$AJ$584,IF(F53="Tarkett Europa",$AJ$585,IF(F53="2tec2",$AJ$586,IF(F53="Balsan Europa",$AJ$587,IF(F53="Armstrong Pisos USA",$AJ$588,IF(F53="Tarkett USA",$AJ$589,IF(F53="Tarkett Brasil",$AJ$590,IF(F53="Tarkett MX",$AJ$591,IF(F53="Jome",$AJ$592,IF(F53="Offiho",$AJ$593,IF(F53="Lumbro",$AJ$594,IF(F53="Sunon Mty",$AJ$595,IF(F53="Conceptos Sofas",$AJ$596,IF(F53="Lauco Sofas",$AJ$597,IF(F53="CR Global - Mesas Ajustables",$AJ$598,IF(F53="Vandesk",$AJ$599,IF(F53="Mamparas Tela",$AJ$600,IF(F53="Mampara Cristales",$AJ$601,IF(F53="Herrajes",$AJ$602,IF(F53="MetalWork",$AJ$603,IF(F53="Requiez",$AJ$604,IF(F53="Labenze",$AJ$605,IF(F53="Infinity",$AJ$606,IF(F53="Proveedor Externo",$AJ$607))))))))))))))))))))))))))))))) -> FALSE | Z53: 0 | AA53: =W53*Z53 -> #REF! | AB53: =IF(Z53>Y53,"ERROR",(W53-AA53)) -> #REF! | AC53: =AB53*H53 -> #REF! | AD53: =IF(A54=TRUE,MAX(0,1-(AE53/W53)),"NA") -> #REF! | AE53: =IF(A52=FALSE,"NO APLICA",AB53*1.2) -> #REF! | AF53: =AE53*H53 -> #REF! | AG53: =(AC53-N53)/AC53 -> #REF! | AH53: =IF(AG53<30%,"ERROR","OK") -> #REF!
A54: =$A$13 -> TRUE | B54: =A54 -> TRUE | C54: =$C$13 -> Dólares | G54: =IFERROR(VLOOKUP(F54,Tabla_Proveedores_1,2,0)," ") | H54: 0 | I54: =IFERROR(VLOOKUP(G54,Proveedores!B:C,2,0)," ") | J54: 0 | K54: =#REF! -> #REF! | L54: =K54*H54 -> #REF! | M54: =IF(F54="Offiho", J54*0.55, IF(AND(F54<>"Sunon Inc",F54<>"Alma - Exterior",F54<>"Yabo - Hotelería",F54<>"OSJ - Medical",F54<>"Seezo - Home",F54<>"A&D -Home",F54<>"Encore Alfombras Hoteleria Asia",F54<>"Zhong Xian - Leds",F54<>"Tarkett Europa",F54<>"2tec2",F54<>"Balsan Europa",F54<>"Armstrong Pisos USA",F54<>"Tarkett USA",F54<>"Tarkett Brasil"),J54,IFERROR(IF(K613<=$AO$578,J54*2.14,IF(K613<=$AN$579,J54*1.8,IF(K613>$AN$580,J54*1.5))),J54))*1.1) -> 0 | N54: =M54*H54 -> 0 | O54: =IFERROR(VLOOKUP(G54,Proveedores!B:D,3,0)," ") | Q54: =VLOOKUP(E54,Tabla_Fletes,3,FALSE) -> #N/A | R54: =IF(P54="Centro",Q54,IF(P54="Norte",Q54*1.6,IF(P54="Occidente",Q54*1.2,IF(P54="Sur",Q54*2)))) -> FALSE | S54: =VLOOKUP(E54,Tabla_Instalacion,2,FALSE) -> #N/A | T54: =IF(P54="Centro",S54,IF(P54="Norte",S54*1.1,IF(P54="Occidente",S54*1.1,IF(P54="Sur",S54*1.1)))) -> FALSE | U54: =IF(F54="Offiho",0,Q54+S54) -> #N/A | V54: =IF(K54=0,U54/$H$573,U54*(K54/L54))*H54 -> #REF! | W54: =IF(F54="Offiho",J54,IF(_xlfn.XLOOKUP(F54,Proveedores!A$2:A$50,Proveedores!E$2:E$50,"")="Nacional",(J54/0.5)+(V54*H54),((J54/0.3/0.5)+(V54*H54)))) -> #REF! | X54: =W54*H54 -> #REF! | Y54: =IF(F54="Sunon Inc",$AJ$577,IF(F54="Alma - Exterior",$AJ$578,IF(F54="Yabo - Hotelería",$AJ$579,IF(F54="OSJ - Medical",$AJ$580,IF(F54="Seezo - Home",$AJ$581,IF(F54="A&D - Home",$AJ$582,IF(F54="Encore Alfombras Hoteleria Asia",$AJ$583,IF(F54="Zhong Xian - Leds",$AJ$584,IF(F54="Tarkett Europa",$AJ$585,IF(F54="2tec2",$AJ$586,IF(F54="Balsan Europa",$AJ$587,IF(F54="Armstrong Pisos USA",$AJ$588,IF(F54="Tarkett USA",$AJ$589,IF(F54="Tarkett Brasil",$AJ$590,IF(F54="Tarkett MX",$AJ$591,IF(F54="Jome",$AJ$592,IF(F54="Offiho",$AJ$593,IF(F54="Lumbro",$AJ$594,IF(F54="Sunon Mty",$AJ$595,IF(F54="Conceptos Sofas",$AJ$596,IF(F54="Lauco Sofas",$AJ$597,IF(F54="CR Global - Mesas Ajustables",$AJ$598,IF(F54="Vandesk",$AJ$599,IF(F54="Mamparas Tela",$AJ$600,IF(F54="Mampara Cristales",$AJ$601,IF(F54="Herrajes",$AJ$602,IF(F54="MetalWork",$AJ$603,IF(F54="Requiez",$AJ$604,IF(F54="Labenze",$AJ$605,IF(F54="Infinity",$AJ$606,IF(F54="Proveedor Externo",$AJ$607))))))))))))))))))))))))))))))) -> FALSE | Z54: 0 | AA54: =W54*Z54 -> #REF! | AB54: =IF(Z54>Y54,"ERROR",(W54-AA54)) -> #REF! | AC54: =AB54*H54 -> #REF! | AD54: =IF(A55=TRUE,MAX(0,1-(AE54/W54)),"NA") -> #REF! | AE54: =IF(A53=FALSE,"NO APLICA",AB54*1.2) -> #REF! | AF54: =AE54*H54 -> #REF! | AG54: =(AC54-N54)/AC54 -> #REF! | AH54: =IF(AG54<30%,"ERROR","OK") -> #REF!
A55: =$A$13 -> TRUE | B55: =A55 -> TRUE | C55: =$C$13 -> Dólares | G55: =IFERROR(VLOOKUP(F55,Tabla_Proveedores_1,2,0)," ") | H55: 0 | I55: =IFERROR(VLOOKUP(G55,Proveedores!B:C,2,0)," ") | J55: 0 | K55: =#REF! -> #REF! | L55: =K55*H55 -> #REF! | M55: =IF(F55="Offiho", J55*0.55, IF(AND(F55<>"Sunon Inc",F55<>"Alma - Exterior",F55<>"Yabo - Hotelería",F55<>"OSJ - Medical",F55<>"Seezo - Home",F55<>"A&D -Home",F55<>"Encore Alfombras Hoteleria Asia",F55<>"Zhong Xian - Leds",F55<>"Tarkett Europa",F55<>"2tec2",F55<>"Balsan Europa",F55<>"Armstrong Pisos USA",F55<>"Tarkett USA",F55<>"Tarkett Brasil"),J55,IFERROR(IF(K614<=$AO$578,J55*2.14,IF(K614<=$AN$579,J55*1.8,IF(K614>$AN$580,J55*1.5))),J55))*1.1) -> 0 | N55: =M55*H55 -> 0 | O55: =IFERROR(VLOOKUP(G55,Proveedores!B:D,3,0)," ") | Q55: =VLOOKUP(E55,Tabla_Fletes,3,FALSE) -> #N/A | R55: =IF(P55="Centro",Q55,IF(P55="Norte",Q55*1.6,IF(P55="Occidente",Q55*1.2,IF(P55="Sur",Q55*2)))) -> FALSE | S55: =VLOOKUP(E55,Tabla_Instalacion,2,FALSE) -> #N/A | T55: =IF(P55="Centro",S55,IF(P55="Norte",S55*1.1,IF(P55="Occidente",S55*1.1,IF(P55="Sur",S55*1.1)))) -> FALSE | U55: =IF(F55="Offiho",0,Q55+S55) -> #N/A | V55: =IF(K55=0,U55/$H$573,U55*(K55/L55))*H55 -> #REF! | W55: =IF(F55="Offiho",J55,IF(_xlfn.XLOOKUP(F55,Proveedores!A$2:A$50,Proveedores!E$2:E$50,"")="Nacional",(J55/0.5)+(V55*H55),((J55/0.3/0.5)+(V55*H55)))) -> #REF! | X55: =W55*H55 -> #REF! | Y55: =IF(F55="Sunon Inc",$AJ$577,IF(F55="Alma - Exterior",$AJ$578,IF(F55="Yabo - Hotelería",$AJ$579,IF(F55="OSJ - Medical",$AJ$580,IF(F55="Seezo - Home",$AJ$581,IF(F55="A&D - Home",$AJ$582,IF(F55="Encore Alfombras Hoteleria Asia",$AJ$583,IF(F55="Zhong Xian - Leds",$AJ$584,IF(F55="Tarkett Europa",$AJ$585,IF(F55="2tec2",$AJ$586,IF(F55="Balsan Europa",$AJ$587,IF(F55="Armstrong Pisos USA",$AJ$588,IF(F55="Tarkett USA",$AJ$589,IF(F55="Tarkett Brasil",$AJ$590,IF(F55="Tarkett MX",$AJ$591,IF(F55="Jome",$AJ$592,IF(F55="Offiho",$AJ$593,IF(F55="Lumbro",$AJ$594,IF(F55="Sunon Mty",$AJ$595,IF(F55="Conceptos Sofas",$AJ$596,IF(F55="Lauco Sofas",$AJ$597,IF(F55="CR Global - Mesas Ajustables",$AJ$598,IF(F55="Vandesk",$AJ$599,IF(F55="Mamparas Tela",$AJ$600,IF(F55="Mampara Cristales",$AJ$601,IF(F55="Herrajes",$AJ$602,IF(F55="MetalWork",$AJ$603,IF(F55="Requiez",$AJ$604,IF(F55="Labenze",$AJ$605,IF(F55="Infinity",$AJ$606,IF(F55="Proveedor Externo",$AJ$607))))))))))))))))))))))))))))))) -> FALSE | Z55: 0 | AA55: =W55*Z55 -> #REF! | AB55: =IF(Z55>Y55,"ERROR",(W55-AA55)) -> #REF! | AC55: =AB55*H55 -> #REF! | AD55: =IF(A56=TRUE,MAX(0,1-(AE55/W55)),"NA") -> #REF! | AE55: =IF(A54=FALSE,"NO APLICA",AB55*1.2) -> #REF! | AF55: =AE55*H55 -> #REF! | AG55: =(AC55-N55)/AC55 -> #REF! | AH55: =IF(AG55<30%,"ERROR","OK") -> #REF!
A56: =$A$13 -> TRUE | B56: =A56 -> TRUE | C56: =$C$13 -> Dólares | G56: =IFERROR(VLOOKUP(F56,Tabla_Proveedores_1,2,0)," ") | H56: 0 | I56: =IFERROR(VLOOKUP(G56,Proveedores!B:C,2,0)," ") | J56: 0 | K56: =#REF! -> #REF! | L56: =K56*H56 -> #REF! | M56: =IF(F56="Offiho", J56*0.55, IF(AND(F56<>"Sunon Inc",F56<>"Alma - Exterior",F56<>"Yabo - Hotelería",F56<>"OSJ - Medical",F56<>"Seezo - Home",F56<>"A&D -Home",F56<>"Encore Alfombras Hoteleria Asia",F56<>"Zhong Xian - Leds",F56<>"Tarkett Europa",F56<>"2tec2",F56<>"Balsan Europa",F56<>"Armstrong Pisos USA",F56<>"Tarkett USA",F56<>"Tarkett Brasil"),J56,IFERROR(IF(K615<=$AO$578,J56*2.14,IF(K615<=$AN$579,J56*1.8,IF(K615>$AN$580,J56*1.5))),J56))*1.1) -> 0 | N56: =M56*H56 -> 0 | O56: =IFERROR(VLOOKUP(G56,Proveedores!B:D,3,0)," ") | Q56: =VLOOKUP(E56,Tabla_Fletes,3,FALSE) -> #N/A | R56: =IF(P56="Centro",Q56,IF(P56="Norte",Q56*1.6,IF(P56="Occidente",Q56*1.2,IF(P56="Sur",Q56*2)))) -> FALSE | S56: =VLOOKUP(E56,Tabla_Instalacion,2,FALSE) -> #N/A | T56: =IF(P56="Centro",S56,IF(P56="Norte",S56*1.1,IF(P56="Occidente",S56*1.1,IF(P56="Sur",S56*1.1)))) -> FALSE | U56: =IF(F56="Offiho",0,Q56+S56) -> #N/A | V56: =IF(K56=0,U56/$H$573,U56*(K56/L56))*H56 -> #REF! | W56: =IF(F56="Offiho",J56,IF(_xlfn.XLOOKUP(F56,Proveedores!A$2:A$50,Proveedores!E$2:E$50,"")="Nacional",(J56/0.5)+(V56*H56),((J56/0.3/0.5)+(V56*H56)))) -> #REF! | X56: =W56*H56 -> #REF! | Y56: =IF(F56="Sunon Inc",$AJ$577,IF(F56="Alma - Exterior",$AJ$578,IF(F56="Yabo - Hotelería",$AJ$579,IF(F56="OSJ - Medical",$AJ$580,IF(F56="Seezo - Home",$AJ$581,IF(F56="A&D - Home",$AJ$582,IF(F56="Encore Alfombras Hoteleria Asia",$AJ$583,IF(F56="Zhong Xian - Leds",$AJ$584,IF(F56="Tarkett Europa",$AJ$585,IF(F56="2tec2",$AJ$586,IF(F56="Balsan Europa",$AJ$587,IF(F56="Armstrong Pisos USA",$AJ$588,IF(F56="Tarkett USA",$AJ$589,IF(F56="Tarkett Brasil",$AJ$590,IF(F56="Tarkett MX",$AJ$591,IF(F56="Jome",$AJ$592,IF(F56="Offiho",$AJ$593,IF(F56="Lumbro",$AJ$594,IF(F56="Sunon Mty",$AJ$595,IF(F56="Conceptos Sofas",$AJ$596,IF(F56="Lauco Sofas",$AJ$597,IF(F56="CR Global - Mesas Ajustables",$AJ$598,IF(F56="Vandesk",$AJ$599,IF(F56="Mamparas Tela",$AJ$600,IF(F56="Mampara Cristales",$AJ$601,IF(F56="Herrajes",$AJ$602,IF(F56="MetalWork",$AJ$603,IF(F56="Requiez",$AJ$604,IF(F56="Labenze",$AJ$605,IF(F56="Infinity",$AJ$606,IF(F56="Proveedor Externo",$AJ$607))))))))))))))))))))))))))))))) -> FALSE | Z56: 0 | AA56: =W56*Z56 -> #REF! | AB56: =IF(Z56>Y56,"ERROR",(W56-AA56)) -> #REF! | AC56: =AB56*H56 -> #REF! | AD56: =IF(A57=TRUE,MAX(0,1-(AE56/W56)),"NA") -> #REF! | AE56: =IF(A55=FALSE,"NO APLICA",AB56*1.2) -> #REF! | AF56: =AE56*H56 -> #REF! | AG56: =(AC56-N56)/AC56 -> #REF! | AH56: =IF(AG56<30%,"ERROR","OK") -> #REF!
A57: =$A$13 -> TRUE | B57: =A57 -> TRUE | C57: =$C$13 -> Dólares | G57: =IFERROR(VLOOKUP(F57,Tabla_Proveedores_1,2,0)," ") | H57: 0 | I57: =IFERROR(VLOOKUP(G57,Proveedores!B:C,2,0)," ") | J57: 0 | K57: =#REF! -> #REF! | L57: =K57*H57 -> #REF! | M57: =IF(F57="Offiho", J57*0.55, IF(AND(F57<>"Sunon Inc",F57<>"Alma - Exterior",F57<>"Yabo - Hotelería",F57<>"OSJ - Medical",F57<>"Seezo - Home",F57<>"A&D -Home",F57<>"Encore Alfombras Hoteleria Asia",F57<>"Zhong Xian - Leds",F57<>"Tarkett Europa",F57<>"2tec2",F57<>"Balsan Europa",F57<>"Armstrong Pisos USA",F57<>"Tarkett USA",F57<>"Tarkett Brasil"),J57,IFERROR(IF(K616<=$AO$578,J57*2.14,IF(K616<=$AN$579,J57*1.8,IF(K616>$AN$580,J57*1.5))),J57))*1.1) -> 0 | N57: =M57*H57 -> 0 | O57: =IFERROR(VLOOKUP(G57,Proveedores!B:D,3,0)," ") | Q57: =VLOOKUP(E57,Tabla_Fletes,3,FALSE) -> #N/A | R57: =IF(P57="Centro",Q57,IF(P57="Norte",Q57*1.6,IF(P57="Occidente",Q57*1.2,IF(P57="Sur",Q57*2)))) -> FALSE | S57: =VLOOKUP(E57,Tabla_Instalacion,2,FALSE) -> #N/A | T57: =IF(P57="Centro",S57,IF(P57="Norte",S57*1.1,IF(P57="Occidente",S57*1.1,IF(P57="Sur",S57*1.1)))) -> FALSE | U57: =IF(F57="Offiho",0,Q57+S57) -> #N/A | V57: =IF(K57=0,U57/$H$573,U57*(K57/L57))*H57 -> #REF! | W57: =IF(F57="Offiho",J57,IF(_xlfn.XLOOKUP(F57,Proveedores!A$2:A$50,Proveedores!E$2:E$50,"")="Nacional",(J57/0.5)+(V57*H57),((J57/0.3/0.5)+(V57*H57)))) -> #REF! | X57: =W57*H57 -> #REF! | Y57: =IF(F57="Sunon Inc",$AJ$577,IF(F57="Alma - Exterior",$AJ$578,IF(F57="Yabo - Hotelería",$AJ$579,IF(F57="OSJ - Medical",$AJ$580,IF(F57="Seezo - Home",$AJ$581,IF(F57="A&D - Home",$AJ$582,IF(F57="Encore Alfombras Hoteleria Asia",$AJ$583,IF(F57="Zhong Xian - Leds",$AJ$584,IF(F57="Tarkett Europa",$AJ$585,IF(F57="2tec2",$AJ$586,IF(F57="Balsan Europa",$AJ$587,IF(F57="Armstrong Pisos USA",$AJ$588,IF(F57="Tarkett USA",$AJ$589,IF(F57="Tarkett Brasil",$AJ$590,IF(F57="Tarkett MX",$AJ$591,IF(F57="Jome",$AJ$592,IF(F57="Offiho",$AJ$593,IF(F57="Lumbro",$AJ$594,IF(F57="Sunon Mty",$AJ$595,IF(F57="Conceptos Sofas",$AJ$596,IF(F57="Lauco Sofas",$AJ$597,IF(F57="CR Global - Mesas Ajustables",$AJ$598,IF(F57="Vandesk",$AJ$599,IF(F57="Mamparas Tela",$AJ$600,IF(F57="Mampara Cristales",$AJ$601,IF(F57="Herrajes",$AJ$602,IF(F57="MetalWork",$AJ$603,IF(F57="Requiez",$AJ$604,IF(F57="Labenze",$AJ$605,IF(F57="Infinity",$AJ$606,IF(F57="Proveedor Externo",$AJ$607))))))))))))))))))))))))))))))) -> FALSE | Z57: 0 | AA57: =W57*Z57 -> #REF! | AB57: =IF(Z57>Y57,"ERROR",(W57-AA57)) -> #REF! | AC57: =AB57*H57 -> #REF! | AD57: =IF(A58=TRUE,MAX(0,1-(AE57/W57)),"NA") -> #REF! | AE57: =IF(A56=FALSE,"NO APLICA",AB57*1.2) -> #REF! | AF57: =AE57*H57 -> #REF! | AG57: =(AC57-N57)/AC57 -> #REF! | AH57: =IF(AG57<30%,"ERROR","OK") -> #REF!
A58: =$A$13 -> TRUE | B58: =A58 -> TRUE | C58: =$C$13 -> Dólares | G58: =IFERROR(VLOOKUP(F58,Tabla_Proveedores_1,2,0)," ") | H58: 0 | I58: =IFERROR(VLOOKUP(G58,Proveedores!B:C,2,0)," ") | J58: 0 | K58: =#REF! -> #REF! | L58: =K58*H58 -> #REF! | M58: =IF(F58="Offiho", J58*0.55, IF(AND(F58<>"Sunon Inc",F58<>"Alma - Exterior",F58<>"Yabo - Hotelería",F58<>"OSJ - Medical",F58<>"Seezo - Home",F58<>"A&D -Home",F58<>"Encore Alfombras Hoteleria Asia",F58<>"Zhong Xian - Leds",F58<>"Tarkett Europa",F58<>"2tec2",F58<>"Balsan Europa",F58<>"Armstrong Pisos USA",F58<>"Tarkett USA",F58<>"Tarkett Brasil"),J58,IFERROR(IF(K617<=$AO$578,J58*2.14,IF(K617<=$AN$579,J58*1.8,IF(K617>$AN$580,J58*1.5))),J58))*1.1) -> 0 | N58: =M58*H58 -> 0 | O58: =IFERROR(VLOOKUP(G58,Proveedores!B:D,3,0)," ") | Q58: =VLOOKUP(E58,Tabla_Fletes,3,FALSE) -> #N/A | R58: =IF(P58="Centro",Q58,IF(P58="Norte",Q58*1.6,IF(P58="Occidente",Q58*1.2,IF(P58="Sur",Q58*2)))) -> FALSE | S58: =VLOOKUP(E58,Tabla_Instalacion,2,FALSE) -> #N/A | T58: =IF(P58="Centro",S58,IF(P58="Norte",S58*1.1,IF(P58="Occidente",S58*1.1,IF(P58="Sur",S58*1.1)))) -> FALSE | U58: =IF(F58="Offiho",0,Q58+S58) -> #N/A | V58: =IF(K58=0,U58/$H$573,U58*(K58/L58))*H58 -> #REF! | W58: =IF(F58="Offiho",J58,IF(_xlfn.XLOOKUP(F58,Proveedores!A$2:A$50,Proveedores!E$2:E$50,"")="Nacional",(J58/0.5)+(V58*H58),((J58/0.3/0.5)+(V58*H58)))) -> #REF! | X58: =W58*H58 -> #REF! | Y58: =IF(F58="Sunon Inc",$AJ$577,IF(F58="Alma - Exterior",$AJ$578,IF(F58="Yabo - Hotelería",$AJ$579,IF(F58="OSJ - Medical",$AJ$580,IF(F58="Seezo - Home",$AJ$581,IF(F58="A&D - Home",$AJ$582,IF(F58="Encore Alfombras Hoteleria Asia",$AJ$583,IF(F58="Zhong Xian - Leds",$AJ$584,IF(F58="Tarkett Europa",$AJ$585,IF(F58="2tec2",$AJ$586,IF(F58="Balsan Europa",$AJ$587,IF(F58="Armstrong Pisos USA",$AJ$588,IF(F58="Tarkett USA",$AJ$589,IF(F58="Tarkett Brasil",$AJ$590,IF(F58="Tarkett MX",$AJ$591,IF(F58="Jome",$AJ$592,IF(F58="Offiho",$AJ$593,IF(F58="Lumbro",$AJ$594,IF(F58="Sunon Mty",$AJ$595,IF(F58="Conceptos Sofas",$AJ$596,IF(F58="Lauco Sofas",$AJ$597,IF(F58="CR Global - Mesas Ajustables",$AJ$598,IF(F58="Vandesk",$AJ$599,IF(F58="Mamparas Tela",$AJ$600,IF(F58="Mampara Cristales",$AJ$601,IF(F58="Herrajes",$AJ$602,IF(F58="MetalWork",$AJ$603,IF(F58="Requiez",$AJ$604,IF(F58="Labenze",$AJ$605,IF(F58="Infinity",$AJ$606,IF(F58="Proveedor Externo",$AJ$607))))))))))))))))))))))))))))))) -> FALSE | Z58: 0 | AA58: =W58*Z58 -> #REF! | AB58: =IF(Z58>Y58,"ERROR",(W58-AA58)) -> #REF! | AC58: =AB58*H58 -> #REF! | AD58: =IF(A59=TRUE,MAX(0,1-(AE58/W58)),"NA") -> #REF! | AE58: =IF(A57=FALSE,"NO APLICA",AB58*1.2) -> #REF! | AF58: =AE58*H58 -> #REF! | AG58: =(AC58-N58)/AC58 -> #REF! | AH58: =IF(AG58<30%,"ERROR","OK") -> #REF!
A59: =$A$13 -> TRUE | B59: =A59 -> TRUE | C59: =$C$13 -> Dólares | G59: =IFERROR(VLOOKUP(F59,Tabla_Proveedores_1,2,0)," ") | H59: 0 | I59: =IFERROR(VLOOKUP(G59,Proveedores!B:C,2,0)," ") | J59: 0 | K59: =#REF! -> #REF! | L59: =K59*H59 -> #REF! | M59: =IF(F59="Offiho", J59*0.55, IF(AND(F59<>"Sunon Inc",F59<>"Alma - Exterior",F59<>"Yabo - Hotelería",F59<>"OSJ - Medical",F59<>"Seezo - Home",F59<>"A&D -Home",F59<>"Encore Alfombras Hoteleria Asia",F59<>"Zhong Xian - Leds",F59<>"Tarkett Europa",F59<>"2tec2",F59<>"Balsan Europa",F59<>"Armstrong Pisos USA",F59<>"Tarkett USA",F59<>"Tarkett Brasil"),J59,IFERROR(IF(K618<=$AO$578,J59*2.14,IF(K618<=$AN$579,J59*1.8,IF(K618>$AN$580,J59*1.5))),J59))*1.1) -> 0 | N59: =M59*H59 -> 0 | O59: =IFERROR(VLOOKUP(G59,Proveedores!B:D,3,0)," ") | Q59: =VLOOKUP(E59,Tabla_Fletes,3,FALSE) -> #N/A | R59: =IF(P59="Centro",Q59,IF(P59="Norte",Q59*1.6,IF(P59="Occidente",Q59*1.2,IF(P59="Sur",Q59*2)))) -> FALSE | S59: =VLOOKUP(E59,Tabla_Instalacion,2,FALSE) -> #N/A | T59: =IF(P59="Centro",S59,IF(P59="Norte",S59*1.1,IF(P59="Occidente",S59*1.1,IF(P59="Sur",S59*1.1)))) -> FALSE | U59: =IF(F59="Offiho",0,Q59+S59) -> #N/A | V59: =IF(K59=0,U59/$H$573,U59*(K59/L59))*H59 -> #REF! | W59: =IF(F59="Offiho",J59,IF(_xlfn.XLOOKUP(F59,Proveedores!A$2:A$50,Proveedores!E$2:E$50,"")="Nacional",(J59/0.5)+(V59*H59),((J59/0.3/0.5)+(V59*H59)))) -> #REF! | X59: =W59*H59 -> #REF! | Y59: =IF(F59="Sunon Inc",$AJ$577,IF(F59="Alma - Exterior",$AJ$578,IF(F59="Yabo - Hotelería",$AJ$579,IF(F59="OSJ - Medical",$AJ$580,IF(F59="Seezo - Home",$AJ$581,IF(F59="A&D - Home",$AJ$582,IF(F59="Encore Alfombras Hoteleria Asia",$AJ$583,IF(F59="Zhong Xian - Leds",$AJ$584,IF(F59="Tarkett Europa",$AJ$585,IF(F59="2tec2",$AJ$586,IF(F59="Balsan Europa",$AJ$587,IF(F59="Armstrong Pisos USA",$AJ$588,IF(F59="Tarkett USA",$AJ$589,IF(F59="Tarkett Brasil",$AJ$590,IF(F59="Tarkett MX",$AJ$591,IF(F59="Jome",$AJ$592,IF(F59="Offiho",$AJ$593,IF(F59="Lumbro",$AJ$594,IF(F59="Sunon Mty",$AJ$595,IF(F59="Conceptos Sofas",$AJ$596,IF(F59="Lauco Sofas",$AJ$597,IF(F59="CR Global - Mesas Ajustables",$AJ$598,IF(F59="Vandesk",$AJ$599,IF(F59="Mamparas Tela",$AJ$600,IF(F59="Mampara Cristales",$AJ$601,IF(F59="Herrajes",$AJ$602,IF(F59="MetalWork",$AJ$603,IF(F59="Requiez",$AJ$604,IF(F59="Labenze",$AJ$605,IF(F59="Infinity",$AJ$606,IF(F59="Proveedor Externo",$AJ$607))))))))))))))))))))))))))))))) -> FALSE | Z59: 0 | AA59: =W59*Z59 -> #REF! | AB59: =IF(Z59>Y59,"ERROR",(W59-AA59)) -> #REF! | AC59: =AB59*H59 -> #REF! | AD59: =IF(A60=TRUE,MAX(0,1-(AE59/W59)),"NA") -> #REF! | AE59: =IF(A58=FALSE,"NO APLICA",AB59*1.2) -> #REF! | AF59: =AE59*H59 -> #REF! | AG59: =(AC59-N59)/AC59 -> #REF! | AH59: =IF(AG59<30%,"ERROR","OK") -> #REF!
A60: =$A$13 -> TRUE | B60: =A60 -> TRUE | C60: =$C$13 -> Dólares | G60: =IFERROR(VLOOKUP(F60,Tabla_Proveedores_1,2,0)," ") | H60: 0 | I60: =IFERROR(VLOOKUP(G60,Proveedores!B:C,2,0)," ") | J60: 0 | K60: =#REF! -> #REF! | L60: =K60*H60 -> #REF! | M60: =IF(F60="Offiho", J60*0.55, IF(AND(F60<>"Sunon Inc",F60<>"Alma - Exterior",F60<>"Yabo - Hotelería",F60<>"OSJ - Medical",F60<>"Seezo - Home",F60<>"A&D -Home",F60<>"Encore Alfombras Hoteleria Asia",F60<>"Zhong Xian - Leds",F60<>"Tarkett Europa",F60<>"2tec2",F60<>"Balsan Europa",F60<>"Armstrong Pisos USA",F60<>"Tarkett USA",F60<>"Tarkett Brasil"),J60,IFERROR(IF(K619<=$AO$578,J60*2.14,IF(K619<=$AN$579,J60*1.8,IF(K619>$AN$580,J60*1.5))),J60))*1.1) -> 0 | N60: =M60*H60 -> 0 | O60: =IFERROR(VLOOKUP(G60,Proveedores!B:D,3,0)," ") | Q60: =VLOOKUP(E60,Tabla_Fletes,3,FALSE) -> #N/A | R60: =IF(P60="Centro",Q60,IF(P60="Norte",Q60*1.6,IF(P60="Occidente",Q60*1.2,IF(P60="Sur",Q60*2)))) -> FALSE | S60: =VLOOKUP(E60,Tabla_Instalacion,2,FALSE) -> #N/A | T60: =IF(P60="Centro",S60,IF(P60="Norte",S60*1.1,IF(P60="Occidente",S60*1.1,IF(P60="Sur",S60*1.1)))) -> FALSE | U60: =IF(F60="Offiho",0,Q60+S60) -> #N/A | V60: =IF(K60=0,U60/$H$573,U60*(K60/L60))*H60 -> #REF! | W60: =IF(F60="Offiho",J60,IF(_xlfn.XLOOKUP(F60,Proveedores!A$2:A$50,Proveedores!E$2:E$50,"")="Nacional",(J60/0.5)+(V60*H60),((J60/0.3/0.5)+(V60*H60)))) -> #REF! | X60: =W60*H60 -> #REF! | Y60: =IF(F60="Sunon Inc",$AJ$577,IF(F60="Alma - Exterior",$AJ$578,IF(F60="Yabo - Hotelería",$AJ$579,IF(F60="OSJ - Medical",$AJ$580,IF(F60="Seezo - Home",$AJ$581,IF(F60="A&D - Home",$AJ$582,IF(F60="Encore Alfombras Hoteleria Asia",$AJ$583,IF(F60="Zhong Xian - Leds",$AJ$584,IF(F60="Tarkett Europa",$AJ$585,IF(F60="2tec2",$AJ$586,IF(F60="Balsan Europa",$AJ$587,IF(F60="Armstrong Pisos USA",$AJ$588,IF(F60="Tarkett USA",$AJ$589,IF(F60="Tarkett Brasil",$AJ$590,IF(F60="Tarkett MX",$AJ$591,IF(F60="Jome",$AJ$592,IF(F60="Offiho",$AJ$593,IF(F60="Lumbro",$AJ$594,IF(F60="Sunon Mty",$AJ$595,IF(F60="Conceptos Sofas",$AJ$596,IF(F60="Lauco Sofas",$AJ$597,IF(F60="CR Global - Mesas Ajustables",$AJ$598,IF(F60="Vandesk",$AJ$599,IF(F60="Mamparas Tela",$AJ$600,IF(F60="Mampara Cristales",$AJ$601,IF(F60="Herrajes",$AJ$602,IF(F60="MetalWork",$AJ$603,IF(F60="Requiez",$AJ$604,IF(F60="Labenze",$AJ$605,IF(F60="Infinity",$AJ$606,IF(F60="Proveedor Externo",$AJ$607))))))))))))))))))))))))))))))) -> FALSE | Z60: 0 | AA60: =W60*Z60 -> #REF! | AB60: =IF(Z60>Y60,"ERROR",(W60-AA60)) -> #REF! | AC60: =AB60*H60 -> #REF! | AD60: =IF(A61=TRUE,MAX(0,1-(AE60/W60)),"NA") -> #REF! | AE60: =IF(A59=FALSE,"NO APLICA",AB60*1.2) -> #REF! | AF60: =AE60*H60 -> #REF! | AG60: =(AC60-N60)/AC60 -> #REF! | AH60: =IF(AG60<30%,"ERROR","OK") -> #REF!
A61: =$A$13 -> TRUE | B61: =A61 -> TRUE | C61: =$C$13 -> Dólares | G61: =IFERROR(VLOOKUP(F61,Tabla_Proveedores_1,2,0)," ") | H61: 0 | I61: =IFERROR(VLOOKUP(G61,Proveedores!B:C,2,0)," ") | J61: 0 | K61: =#REF! -> #REF! | L61: =K61*H61 -> #REF! | M61: =IF(F61="Offiho", J61*0.55, IF(AND(F61<>"Sunon Inc",F61<>"Alma - Exterior",F61<>"Yabo - Hotelería",F61<>"OSJ - Medical",F61<>"Seezo - Home",F61<>"A&D -Home",F61<>"Encore Alfombras Hoteleria Asia",F61<>"Zhong Xian - Leds",F61<>"Tarkett Europa",F61<>"2tec2",F61<>"Balsan Europa",F61<>"Armstrong Pisos USA",F61<>"Tarkett USA",F61<>"Tarkett Brasil"),J61,IFERROR(IF(K620<=$AO$578,J61*2.14,IF(K620<=$AN$579,J61*1.8,IF(K620>$AN$580,J61*1.5))),J61))*1.1) -> 0 | N61: =M61*H61 -> 0 | O61: =IFERROR(VLOOKUP(G61,Proveedores!B:D,3,0)," ") | Q61: =VLOOKUP(E61,Tabla_Fletes,3,FALSE) -> #N/A | R61: =IF(P61="Centro",Q61,IF(P61="Norte",Q61*1.6,IF(P61="Occidente",Q61*1.2,IF(P61="Sur",Q61*2)))) -> FALSE | S61: =VLOOKUP(E61,Tabla_Instalacion,2,FALSE) -> #N/A | T61: =IF(P61="Centro",S61,IF(P61="Norte",S61*1.1,IF(P61="Occidente",S61*1.1,IF(P61="Sur",S61*1.1)))) -> FALSE | U61: =IF(F61="Offiho",0,Q61+S61) -> #N/A | V61: =IF(K61=0,U61/$H$573,U61*(K61/L61))*H61 -> #REF! | W61: =IF(F61="Offiho",J61,IF(_xlfn.XLOOKUP(F61,Proveedores!A$2:A$50,Proveedores!E$2:E$50,"")="Nacional",(J61/0.5)+(V61*H61),((J61/0.3/0.5)+(V61*H61)))) -> #REF! | X61: =W61*H61 -> #REF! | Y61: =IF(F61="Sunon Inc",$AJ$577,IF(F61="Alma - Exterior",$AJ$578,IF(F61="Yabo - Hotelería",$AJ$579,IF(F61="OSJ - Medical",$AJ$580,IF(F61="Seezo - Home",$AJ$581,IF(F61="A&D - Home",$AJ$582,IF(F61="Encore Alfombras Hoteleria Asia",$AJ$583,IF(F61="Zhong Xian - Leds",$AJ$584,IF(F61="Tarkett Europa",$AJ$585,IF(F61="2tec2",$AJ$586,IF(F61="Balsan Europa",$AJ$587,IF(F61="Armstrong Pisos USA",$AJ$588,IF(F61="Tarkett USA",$AJ$589,IF(F61="Tarkett Brasil",$AJ$590,IF(F61="Tarkett MX",$AJ$591,IF(F61="Jome",$AJ$592,IF(F61="Offiho",$AJ$593,IF(F61="Lumbro",$AJ$594,IF(F61="Sunon Mty",$AJ$595,IF(F61="Conceptos Sofas",$AJ$596,IF(F61="Lauco Sofas",$AJ$597,IF(F61="CR Global - Mesas Ajustables",$AJ$598,IF(F61="Vandesk",$AJ$599,IF(F61="Mamparas Tela",$AJ$600,IF(F61="Mampara Cristales",$AJ$601,IF(F61="Herrajes",$AJ$602,IF(F61="MetalWork",$AJ$603,IF(F61="Requiez",$AJ$604,IF(F61="Labenze",$AJ$605,IF(F61="Infinity",$AJ$606,IF(F61="Proveedor Externo",$AJ$607))))))))))))))))))))))))))))))) -> FALSE | Z61: 0 | AA61: =W61*Z61 -> #REF! | AB61: =IF(Z61>Y61,"ERROR",(W61-AA61)) -> #REF! | AC61: =AB61*H61 -> #REF! | AD61: =IF(A62=TRUE,MAX(0,1-(AE61/W61)),"NA") -> #REF! | AE61: =IF(A60=FALSE,"NO APLICA",AB61*1.2) -> #REF! | AF61: =AE61*H61 -> #REF! | AG61: =(AC61-N61)/AC61 -> #REF! | AH61: =IF(AG61<30%,"ERROR","OK") -> #REF!
A62: =$A$13 -> TRUE | B62: =A62 -> TRUE | C62: =$C$13 -> Dólares | G62: =IFERROR(VLOOKUP(F62,Tabla_Proveedores_1,2,0)," ") | H62: 0 | I62: =IFERROR(VLOOKUP(G62,Proveedores!B:C,2,0)," ") | J62: 0 | K62: =#REF! -> #REF! | L62: =K62*H62 -> #REF! | M62: =IF(F62="Offiho", J62*0.55, IF(AND(F62<>"Sunon Inc",F62<>"Alma - Exterior",F62<>"Yabo - Hotelería",F62<>"OSJ - Medical",F62<>"Seezo - Home",F62<>"A&D -Home",F62<>"Encore Alfombras Hoteleria Asia",F62<>"Zhong Xian - Leds",F62<>"Tarkett Europa",F62<>"2tec2",F62<>"Balsan Europa",F62<>"Armstrong Pisos USA",F62<>"Tarkett USA",F62<>"Tarkett Brasil"),J62,IFERROR(IF(K621<=$AO$578,J62*2.14,IF(K621<=$AN$579,J62*1.8,IF(K621>$AN$580,J62*1.5))),J62))*1.1) -> 0 | N62: =M62*H62 -> 0 | O62: =IFERROR(VLOOKUP(G62,Proveedores!B:D,3,0)," ") | Q62: =VLOOKUP(E62,Tabla_Fletes,3,FALSE) -> #N/A | R62: =IF(P62="Centro",Q62,IF(P62="Norte",Q62*1.6,IF(P62="Occidente",Q62*1.2,IF(P62="Sur",Q62*2)))) -> FALSE | S62: =VLOOKUP(E62,Tabla_Instalacion,2,FALSE) -> #N/A | T62: =IF(P62="Centro",S62,IF(P62="Norte",S62*1.1,IF(P62="Occidente",S62*1.1,IF(P62="Sur",S62*1.1)))) -> FALSE | U62: =IF(F62="Offiho",0,Q62+S62) -> #N/A | V62: =IF(K62=0,U62/$H$573,U62*(K62/L62))*H62 -> #REF! | W62: =IF(F62="Offiho",J62,IF(_xlfn.XLOOKUP(F62,Proveedores!A$2:A$50,Proveedores!E$2:E$50,"")="Nacional",(J62/0.5)+(V62*H62),((J62/0.3/0.5)+(V62*H62)))) -> #REF! | X62: =W62*H62 -> #REF! | Y62: =IF(F62="Sunon Inc",$AJ$577,IF(F62="Alma - Exterior",$AJ$578,IF(F62="Yabo - Hotelería",$AJ$579,IF(F62="OSJ - Medical",$AJ$580,IF(F62="Seezo - Home",$AJ$581,IF(F62="A&D - Home",$AJ$582,IF(F62="Encore Alfombras Hoteleria Asia",$AJ$583,IF(F62="Zhong Xian - Leds",$AJ$584,IF(F62="Tarkett Europa",$AJ$585,IF(F62="2tec2",$AJ$586,IF(F62="Balsan Europa",$AJ$587,IF(F62="Armstrong Pisos USA",$AJ$588,IF(F62="Tarkett USA",$AJ$589,IF(F62="Tarkett Brasil",$AJ$590,IF(F62="Tarkett MX",$AJ$591,IF(F62="Jome",$AJ$592,IF(F62="Offiho",$AJ$593,IF(F62="Lumbro",$AJ$594,IF(F62="Sunon Mty",$AJ$595,IF(F62="Conceptos Sofas",$AJ$596,IF(F62="Lauco Sofas",$AJ$597,IF(F62="CR Global - Mesas Ajustables",$AJ$598,IF(F62="Vandesk",$AJ$599,IF(F62="Mamparas Tela",$AJ$600,IF(F62="Mampara Cristales",$AJ$601,IF(F62="Herrajes",$AJ$602,IF(F62="MetalWork",$AJ$603,IF(F62="Requiez",$AJ$604,IF(F62="Labenze",$AJ$605,IF(F62="Infinity",$AJ$606,IF(F62="Proveedor Externo",$AJ$607))))))))))))))))))))))))))))))) -> FALSE | Z62: 0 | AA62: =W62*Z62 -> #REF! | AB62: =IF(Z62>Y62,"ERROR",(W62-AA62)) -> #REF! | AC62: =AB62*H62 -> #REF! | AD62: =IF(A63=TRUE,MAX(0,1-(AE62/W62)),"NA") -> #REF! | AE62: =IF(A61=FALSE,"NO APLICA",AB62*1.2) -> #REF! | AF62: =AE62*H62 -> #REF! | AG62: =(AC62-N62)/AC62 -> #REF! | AH62: =IF(AG62<30%,"ERROR","OK") -> #REF!
A63: =$A$13 -> TRUE | B63: =A63 -> TRUE | C63: =$C$13 -> Dólares | G63: =IFERROR(VLOOKUP(F63,Tabla_Proveedores_1,2,0)," ") | H63: 0 | I63: =IFERROR(VLOOKUP(G63,Proveedores!B:C,2,0)," ") | J63: 0 | K63: =#REF! -> #REF! | L63: =K63*H63 -> #REF! | M63: =IF(F63="Offiho", J63*0.55, IF(AND(F63<>"Sunon Inc",F63<>"Alma - Exterior",F63<>"Yabo - Hotelería",F63<>"OSJ - Medical",F63<>"Seezo - Home",F63<>"A&D -Home",F63<>"Encore Alfombras Hoteleria Asia",F63<>"Zhong Xian - Leds",F63<>"Tarkett Europa",F63<>"2tec2",F63<>"Balsan Europa",F63<>"Armstrong Pisos USA",F63<>"Tarkett USA",F63<>"Tarkett Brasil"),J63,IFERROR(IF(K622<=$AO$578,J63*2.14,IF(K622<=$AN$579,J63*1.8,IF(K622>$AN$580,J63*1.5))),J63))*1.1) -> 0 | N63: =M63*H63 -> 0 | O63: =IFERROR(VLOOKUP(G63,Proveedores!B:D,3,0)," ") | Q63: =VLOOKUP(E63,Tabla_Fletes,3,FALSE) -> #N/A | R63: =IF(P63="Centro",Q63,IF(P63="Norte",Q63*1.6,IF(P63="Occidente",Q63*1.2,IF(P63="Sur",Q63*2)))) -> FALSE | S63: =VLOOKUP(E63,Tabla_Instalacion,2,FALSE) -> #N/A | T63: =IF(P63="Centro",S63,IF(P63="Norte",S63*1.1,IF(P63="Occidente",S63*1.1,IF(P63="Sur",S63*1.1)))) -> FALSE | U63: =IF(F63="Offiho",0,Q63+S63) -> #N/A | V63: =IF(K63=0,U63/$H$573,U63*(K63/L63))*H63 -> #REF! | W63: =IF(F63="Offiho",J63,IF(_xlfn.XLOOKUP(F63,Proveedores!A$2:A$50,Proveedores!E$2:E$50,"")="Nacional",(J63/0.5)+(V63*H63),((J63/0.3/0.5)+(V63*H63)))) -> #REF! | X63: =W63*H63 -> #REF! | Y63: =IF(F63="Sunon Inc",$AJ$577,IF(F63="Alma - Exterior",$AJ$578,IF(F63="Yabo - Hotelería",$AJ$579,IF(F63="OSJ - Medical",$AJ$580,IF(F63="Seezo - Home",$AJ$581,IF(F63="A&D - Home",$AJ$582,IF(F63="Encore Alfombras Hoteleria Asia",$AJ$583,IF(F63="Zhong Xian - Leds",$AJ$584,IF(F63="Tarkett Europa",$AJ$585,IF(F63="2tec2",$AJ$586,IF(F63="Balsan Europa",$AJ$587,IF(F63="Armstrong Pisos USA",$AJ$588,IF(F63="Tarkett USA",$AJ$589,IF(F63="Tarkett Brasil",$AJ$590,IF(F63="Tarkett MX",$AJ$591,IF(F63="Jome",$AJ$592,IF(F63="Offiho",$AJ$593,IF(F63="Lumbro",$AJ$594,IF(F63="Sunon Mty",$AJ$595,IF(F63="Conceptos Sofas",$AJ$596,IF(F63="Lauco Sofas",$AJ$597,IF(F63="CR Global - Mesas Ajustables",$AJ$598,IF(F63="Vandesk",$AJ$599,IF(F63="Mamparas Tela",$AJ$600,IF(F63="Mampara Cristales",$AJ$601,IF(F63="Herrajes",$AJ$602,IF(F63="MetalWork",$AJ$603,IF(F63="Requiez",$AJ$604,IF(F63="Labenze",$AJ$605,IF(F63="Infinity",$AJ$606,IF(F63="Proveedor Externo",$AJ$607))))))))))))))))))))))))))))))) -> FALSE | Z63: 0 | AA63: =W63*Z63 -> #REF! | AB63: =IF(Z63>Y63,"ERROR",(W63-AA63)) -> #REF! | AC63: =AB63*H63 -> #REF! | AD63: =IF(A64=TRUE,MAX(0,1-(AE63/W63)),"NA") -> #REF! | AE63: =IF(A62=FALSE,"NO APLICA",AB63*1.2) -> #REF! | AF63: =AE63*H63 -> #REF! | AG63: =(AC63-N63)/AC63 -> #REF! | AH63: =IF(AG63<30%,"ERROR","OK") -> #REF!
... A80: =$A$13 -> TRUE | B80: =A80 -> TRUE | C80: =$C$13 -> Dólares | G80: =IFERROR(VLOOKUP(F80,Tabla_Proveedores_1,2,0)," ") | H80: 0 | I80: =IFERROR(VLOOKUP(G80,Proveedores!B:C,2,0)," ") | J80: 0 | K80: =#REF! -> #REF! | L80: =K80*H80 -> #REF! | M80: =IF(F80="Offiho", J80*0.55, IF(AND(F80<>"Sunon Inc",F80<>"Alma - Exterior",F80<>"Yabo - Hotelería",F80<>"OSJ - Medical",F80<>"Seezo - Home",F80<>"A&D -Home",F80<>"Encore Alfombras Hoteleria Asia",F80<>"Zhong Xian - Leds",F80<>"Tarkett Europa",F80<>"2tec2",F80<>"Balsan Europa",F80<>"Armstrong Pisos USA",F80<>"Tarkett USA",F80<>"Tarkett Brasil"),J80,IFERROR(IF(K639<=$AO$578,J80*2.14,IF(K639<=$AN$579,J80*1.8,IF(K639>$AN$580,J80*1.5))),J80))*1.1) -> 0 | N80: =M80*H80 -> 0 | O80: =IFERROR(VLOOKUP(G80,Proveedores!B:D,3,0)," ") | Q80: =VLOOKUP(E80,Tabla_Fletes,3,FALSE) -> #N/A | R80: =IF(P80="Centro",Q80,IF(P80="Norte",Q80*1.6,IF(P80="Occidente",Q80*1.2,IF(P80="Sur",Q80*2)))) -> FALSE | S80: =VLOOKUP(E80,Tabla_Instalacion,2,FALSE) -> #N/A | T80: =IF(P80="Centro",S80,IF(P80="Norte",S80*1.1,IF(P80="Occidente",S80*1.1,IF(P80="Sur",S80*1.1)))) -> FALSE | U80: =IF(F80="Offiho",0,Q80+S80) -> #N/A | V80: =IF(K80=0,U80/$H$573,U80*(K80/L80))*H80 -> #REF! | W80: =IF(F80="Offiho",J80,IF(_xlfn.XLOOKUP(F80,Proveedores!A$2:A$50,Proveedores!E$2:E$50,"")="Nacional",(J80/0.5)+(V80*H80),((J80/0.3/0.5)+(V80*H80)))) -> #REF! | X80: =W80*H80 -> #REF! | Y80: =IF(F80="Sunon Inc",$AJ$577,IF(F80="Alma - Exterior",$AJ$578,IF(F80="Yabo - Hotelería",$AJ$579,IF(F80="OSJ - Medical",$AJ$580,IF(F80="Seezo - Home",$AJ$581,IF(F80="A&D - Home",$AJ$582,IF(F80="Encore Alfombras Hoteleria Asia",$AJ$583,IF(F80="Zhong Xian - Leds",$AJ$584,IF(F80="Tarkett Europa",$AJ$585,IF(F80="2tec2",$AJ$586,IF(F80="Balsan Europa",$AJ$587,IF(F80="Armstrong Pisos USA",$AJ$588,IF(F80="Tarkett USA",$AJ$589,IF(F80="Tarkett Brasil",$AJ$590,IF(F80="Tarkett MX",$AJ$591,IF(F80="Jome",$AJ$592,IF(F80="Offiho",$AJ$593,IF(F80="Lumbro",$AJ$594,IF(F80="Sunon Mty",$AJ$595,IF(F80="Conceptos Sofas",$AJ$596,IF(F80="Lauco Sofas",$AJ$597,IF(F80="CR Global - Mesas Ajustables",$AJ$598,IF(F80="Vandesk",$AJ$599,IF(F80="Mamparas Tela",$AJ$600,IF(F80="Mampara Cristales",$AJ$601,IF(F80="Herrajes",$AJ$602,IF(F80="MetalWork",$AJ$603,IF(F80="Requiez",$AJ$604,IF(F80="Labenze",$AJ$605,IF(F80="Infinity",$AJ$606,IF(F80="Proveedor Externo",$AJ$607))))))))))))))))))))))))))))))) -> FALSE | Z80: 0 | AA80: =W80*Z80 -> #REF! | AB80: =IF(Z80>Y80,"ERROR",(W80-AA80)) -> #REF! | AC80: =AB80*H80 -> #REF! | AD80: =IF(A81=TRUE,MAX(0,1-(AE80/W80)),"NA") -> #REF! | AE80: =IF(A79=FALSE,"NO APLICA",AB80*1.2) -> #REF! | AF80: =AE80*H80 -> #REF! | AG80: =(AC80-N80)/AC80 -> #REF! | AH80: =IF(AG80<30%,"ERROR","OK") -> #REF!
A81: =$A$13 -> TRUE | B81: =A81 -> TRUE | C81: =$C$13 -> Dólares | G81: =IFERROR(VLOOKUP(F81,Tabla_Proveedores_1,2,0)," ") | H81: 0 | I81: =IFERROR(VLOOKUP(G81,Proveedores!B:C,2,0)," ") | J81: 0 | K81: 0 | L81: =K81*H81 -> 0 | M81: =IF(F81="Offiho", J81*0.55, IF(AND(F81<>"Sunon Inc",F81<>"Alma - Exterior",F81<>"Yabo - Hotelería",F81<>"OSJ - Medical",F81<>"Seezo - Home",F81<>"A&D -Home",F81<>"Encore Alfombras Hoteleria Asia",F81<>"Zhong Xian - Leds",F81<>"Tarkett Europa",F81<>"2tec2",F81<>"Balsan Europa",F81<>"Armstrong Pisos USA",F81<>"Tarkett USA",F81<>"Tarkett Brasil"),J81,IFERROR(IF(K640<=$AO$578,J81*2.14,IF(K640<=$AN$579,J81*1.8,IF(K640>$AN$580,J81*1.5))),J81))*1.1) -> 0 | N81: =M81*H81 -> 0 | O81: =IFERROR(VLOOKUP(G81,Proveedores!B:D,3,0)," ") | Q81: =VLOOKUP(E81,Tabla_Fletes,3,FALSE) -> #N/A | R81: =IF(P81="Centro",Q81,IF(P81="Norte",Q81*1.6,IF(P81="Occidente",Q81*1.2,IF(P81="Sur",Q81*2)))) -> FALSE | S81: =VLOOKUP(E81,Tabla_Instalacion,2,FALSE) -> #N/A | T81: =IF(P81="Centro",S81,IF(P81="Norte",S81*1.1,IF(P81="Occidente",S81*1.1,IF(P81="Sur",S81*1.1)))) -> FALSE | U81: =IF(F81="Offiho",0,Q81+S81) -> #N/A | V81: =IF(K81=0,U81/$H$573,U81*(K81/L81))*H81 -> #N/A | W81: =IF(F81="Offiho",J81,IF(_xlfn.XLOOKUP(F81,Proveedores!A$2:A$50,Proveedores!E$2:E$50,"")="Nacional",(J81/0.5)+(V81*H81),((J81/0.3/0.5)+(V81*H81)))) -> #N/A | X81: =W81*H81 -> #N/A | Y81: =IF(F81="Sunon Inc",$AJ$577,IF(F81="Alma - Exterior",$AJ$578,IF(F81="Yabo - Hotelería",$AJ$579,IF(F81="OSJ - Medical",$AJ$580,IF(F81="Seezo - Home",$AJ$581,IF(F81="A&D - Home",$AJ$582,IF(F81="Encore Alfombras Hoteleria Asia",$AJ$583,IF(F81="Zhong Xian - Leds",$AJ$584,IF(F81="Tarkett Europa",$AJ$585,IF(F81="2tec2",$AJ$586,IF(F81="Balsan Europa",$AJ$587,IF(F81="Armstrong Pisos USA",$AJ$588,IF(F81="Tarkett USA",$AJ$589,IF(F81="Tarkett Brasil",$AJ$590,IF(F81="Tarkett MX",$AJ$591,IF(F81="Jome",$AJ$592,IF(F81="Offiho",$AJ$593,IF(F81="Lumbro",$AJ$594,IF(F81="Sunon Mty",$AJ$595,IF(F81="Conceptos Sofas",$AJ$596,IF(F81="Lauco Sofas",$AJ$597,IF(F81="CR Global - Mesas Ajustables",$AJ$598,IF(F81="Vandesk",$AJ$599,IF(F81="Mamparas Tela",$AJ$600,IF(F81="Mampara Cristales",$AJ$601,IF(F81="Herrajes",$AJ$602,IF(F81="MetalWork",$AJ$603,IF(F81="Requiez",$AJ$604,IF(F81="Labenze",$AJ$605,IF(F81="Infinity",$AJ$606,IF(F81="Proveedor Externo",$AJ$607))))))))))))))))))))))))))))))) -> FALSE | Z81: 0 | AA81: =W81*Z81 -> #N/A | AB81: =IF(Z81>Y81,"ERROR",(W81-AA81)) -> #N/A | AC81: =AB81*H81 -> #N/A | AD81: =IF(A82=TRUE,MAX(0,1-(AE81/W81)),"NA") -> NA | AE81: =IF(A80=FALSE,"NO APLICA",AB81*1.2) -> #N/A | AF81: =AE81*H81 -> #N/A | AG81: =(AC81-N81)/AC81 -> #N/A | AH81: =IF(AG81<30%,"ERROR","OK") -> #N/A
A82: Subtotales Sección 2 | H82: {=SUM(IFERROR(H49:H81,0))} -> 0 | L82: {=SUM(IFERROR(L49:L81,0))} -> 0 | N82: {=SUM(IFERROR(N49:N81,0))} -> 0 | X82: {=SUM(IFERROR(X49:X81,0))} -> 0 | AC82: {=SUM(IFERROR(AC49:AC81,0))} -> 0 | AF82: {=SUM(IFERROR(AF49:AF81,0))} -> 0 | AG82: =IFERROR(1-(N82/AC82),0) -> 0
A83: Sección 3 - NOMBRE
A84: =$A$13 -> TRUE | B84: =A84 -> TRUE | C84: =$C$13 -> Dólares | G84: =IFERROR(VLOOKUP(F84,Tabla_Proveedores_1,2,0)," ") | H84: 0 | I84: =IFERROR(VLOOKUP(G84,Proveedores!B:C,2,0)," ") | J84: 0 | L84: =K84*H84 -> 0 | M84: =IF(F84="Offiho", J84*0.55, IF(AND(F84<>"Sunon Inc",F84<>"Alma - Exterior",F84<>"Yabo - Hotelería",F84<>"OSJ - Medical",F84<>"Seezo - Home",F84<>"A&D -Home",F84<>"Encore Alfombras Hoteleria Asia",F84<>"Zhong Xian - Leds",F84<>"Tarkett Europa",F84<>"2tec2",F84<>"Balsan Europa",F84<>"Armstrong Pisos USA",F84<>"Tarkett USA",F84<>"Tarkett Brasil"),J84,IFERROR(IF(K643<=$AO$578,J84*2.14,IF(K643<=$AN$579,J84*1.8,IF(K643>$AN$580,J84*1.5))),J84))*1.1) -> 0 | N84: =M84*H84 -> 0 | O84: =IFERROR(VLOOKUP(G84,Proveedores!B:D,3,0)," ") | Q84: =VLOOKUP(E84,Tabla_Fletes,3,FALSE) -> #N/A | R84: =IF(P84="Centro",Q84,IF(P84="Norte",Q84*1.6,IF(P84="Occidente",Q84*1.2,IF(P84="Sur",Q84*2)))) -> FALSE | S84: =VLOOKUP(E84,Tabla_Instalacion,2,FALSE) -> #N/A | T84: =IF(P84="Centro",S84,IF(P84="Norte",S84*1.1,IF(P84="Occidente",S84*1.1,IF(P84="Sur",S84*1.1)))) -> FALSE | U84: =IF(F84="Offiho",0,Q84+S84) -> #N/A | V84: =IF(K84=0,U84/$H$573,U84*(K84/L84))*H84 -> #N/A | W84: =IF(F84="Offiho",J84,IF(_xlfn.XLOOKUP(F84,Proveedores!A$2:A$50,Proveedores!E$2:E$50,"")="Nacional",(J84/0.5)+(V84*H84),((J84/0.3/0.5)+(V84*H84)))) -> #N/A | X84: =W84*H84 -> #N/A | Y84: =IF(F84="Sunon Inc",$AJ$577,IF(F84="Alma - Exterior",$AJ$578,IF(F84="Yabo - Hotelería",$AJ$579,IF(F84="OSJ - Medical",$AJ$580,IF(F84="Seezo - Home",$AJ$581,IF(F84="A&D - Home",$AJ$582,IF(F84="Encore Alfombras Hoteleria Asia",$AJ$583,IF(F84="Zhong Xian - Leds",$AJ$584,IF(F84="Tarkett Europa",$AJ$585,IF(F84="2tec2",$AJ$586,IF(F84="Balsan Europa",$AJ$587,IF(F84="Armstrong Pisos USA",$AJ$588,IF(F84="Tarkett USA",$AJ$589,IF(F84="Tarkett Brasil",$AJ$590,IF(F84="Tarkett MX",$AJ$591,IF(F84="Jome",$AJ$592,IF(F84="Offiho",$AJ$593,IF(F84="Lumbro",$AJ$594,IF(F84="Sunon Mty",$AJ$595,IF(F84="Conceptos Sofas",$AJ$596,IF(F84="Lauco Sofas",$AJ$597,IF(F84="CR Global - Mesas Ajustables",$AJ$598,IF(F84="Vandesk",$AJ$599,IF(F84="Mamparas Tela",$AJ$600,IF(F84="Mampara Cristales",$AJ$601,IF(F84="Herrajes",$AJ$602,IF(F84="MetalWork",$AJ$603,IF(F84="Requiez",$AJ$604,IF(F84="Labenze",$AJ$605,IF(F84="Infinity",$AJ$606,IF(F84="Proveedor Externo",$AJ$607))))))))))))))))))))))))))))))) -> FALSE | Z84: 0 | AA84: =W84*Z84 -> #N/A | AB84: =IF(Z84>Y84,"ERROR",(W84-AA84)) -> #N/A | AC84: =AB84*H84 -> #N/A | AD84: =IF(A85=TRUE,MAX(0,1-(AE84/W84)),"NA") -> #N/A | AE84: =IF(A83=FALSE,"NO APLICA",AB84*1.2) -> #N/A | AF84: =AE84*H84 -> #N/A | AG84: =(AC84-N84)/AC84 -> #N/A | AH84: =IF(AG84<30%,"ERROR","OK") -> #N/A
A85: =$A$13 -> TRUE | B85: =A85 -> TRUE | C85: =$C$13 -> Dólares | G85: =IFERROR(VLOOKUP(F85,Tabla_Proveedores_1,2,0)," ") | H85: 0 | I85: =IFERROR(VLOOKUP(G85,Proveedores!B:C,2,0)," ") | J85: 0 | L85: =K85*H85 -> 0 | M85: =IF(F85="Offiho", J85*0.55, IF(AND(F85<>"Sunon Inc",F85<>"Alma - Exterior",F85<>"Yabo - Hotelería",F85<>"OSJ - Medical",F85<>"Seezo - Home",F85<>"A&D -Home",F85<>"Encore Alfombras Hoteleria Asia",F85<>"Zhong Xian - Leds",F85<>"Tarkett Europa",F85<>"2tec2",F85<>"Balsan Europa",F85<>"Armstrong Pisos USA",F85<>"Tarkett USA",F85<>"Tarkett Brasil"),J85,IFERROR(IF(K644<=$AO$578,J85*2.14,IF(K644<=$AN$579,J85*1.8,IF(K644>$AN$580,J85*1.5))),J85))*1.1) -> 0 | N85: =M85*H85 -> 0 | O85: =IFERROR(VLOOKUP(G85,Proveedores!B:D,3,0)," ") | Q85: =VLOOKUP(E85,Tabla_Fletes,3,FALSE) -> #N/A | R85: =IF(P85="Centro",Q85,IF(P85="Norte",Q85*1.6,IF(P85="Occidente",Q85*1.2,IF(P85="Sur",Q85*2)))) -> FALSE | S85: =VLOOKUP(E85,Tabla_Instalacion,2,FALSE) -> #N/A | T85: =IF(P85="Centro",S85,IF(P85="Norte",S85*1.1,IF(P85="Occidente",S85*1.1,IF(P85="Sur",S85*1.1)))) -> FALSE | U85: =IF(F85="Offiho",0,Q85+S85) -> #N/A | V85: =IF(K85=0,U85/$H$573,U85*(K85/L85))*H85 -> #N/A | W85: =IF(F85="Offiho",J85,IF(_xlfn.XLOOKUP(F85,Proveedores!A$2:A$50,Proveedores!E$2:E$50,"")="Nacional",(J85/0.5)+(V85*H85),((J85/0.3/0.5)+(V85*H85)))) -> #N/A | X85: =W85*H85 -> #N/A | Y85: =IF(F85="Sunon Inc",$AJ$577,IF(F85="Alma - Exterior",$AJ$578,IF(F85="Yabo - Hotelería",$AJ$579,IF(F85="OSJ - Medical",$AJ$580,IF(F85="Seezo - Home",$AJ$581,IF(F85="A&D - Home",$AJ$582,IF(F85="Encore Alfombras Hoteleria Asia",$AJ$583,IF(F85="Zhong Xian - Leds",$AJ$584,IF(F85="Tarkett Europa",$AJ$585,IF(F85="2tec2",$AJ$586,IF(F85="Balsan Europa",$AJ$587,IF(F85="Armstrong Pisos USA",$AJ$588,IF(F85="Tarkett USA",$AJ$589,IF(F85="Tarkett Brasil",$AJ$590,IF(F85="Tarkett MX",$AJ$591,IF(F85="Jome",$AJ$592,IF(F85="Offiho",$AJ$593,IF(F85="Lumbro",$AJ$594,IF(F85="Sunon Mty",$AJ$595,IF(F85="Conceptos Sofas",$AJ$596,IF(F85="Lauco Sofas",$AJ$597,IF(F85="CR Global - Mesas Ajustables",$AJ$598,IF(F85="Vandesk",$AJ$599,IF(F85="Mamparas Tela",$AJ$600,IF(F85="Mampara Cristales",$AJ$601,IF(F85="Herrajes",$AJ$602,IF(F85="MetalWork",$AJ$603,IF(F85="Requiez",$AJ$604,IF(F85="Labenze",$AJ$605,IF(F85="Infinity",$AJ$606,IF(F85="Proveedor Externo",$AJ$607))))))))))))))))))))))))))))))) -> FALSE | Z85: 0 | AA85: =W85*Z85 -> #N/A | AB85: =IF(Z85>Y85,"ERROR",(W85-AA85)) -> #N/A | AC85: =AB85*H85 -> #N/A | AD85: =IF(A86=TRUE,MAX(0,1-(AE85/W85)),"NA") -> #N/A | AE85: =IF(A84=FALSE,"NO APLICA",AB85*1.2) -> #N/A | AF85: =AE85*H85 -> #N/A | AG85: =(AC85-N85)/AC85 -> #N/A | AH85: =IF(AG85<30%,"ERROR","OK") -> #N/A
A86: =$A$13 -> TRUE | B86: =A86 -> TRUE | C86: =$C$13 -> Dólares | G86: =IFERROR(VLOOKUP(F86,Tabla_Proveedores_1,2,0)," ") | H86: 0 | I86: =IFERROR(VLOOKUP(G86,Proveedores!B:C,2,0)," ") | J86: 0 | L86: =K86*H86 -> 0 | M86: =IF(F86="Offiho", J86*0.55, IF(AND(F86<>"Sunon Inc",F86<>"Alma - Exterior",F86<>"Yabo - Hotelería",F86<>"OSJ - Medical",F86<>"Seezo - Home",F86<>"A&D -Home",F86<>"Encore Alfombras Hoteleria Asia",F86<>"Zhong Xian - Leds",F86<>"Tarkett Europa",F86<>"2tec2",F86<>"Balsan Europa",F86<>"Armstrong Pisos USA",F86<>"Tarkett USA",F86<>"Tarkett Brasil"),J86,IFERROR(IF(K645<=$AO$578,J86*2.14,IF(K645<=$AN$579,J86*1.8,IF(K645>$AN$580,J86*1.5))),J86))*1.1) -> 0 | N86: =(M86*H86) -> 0 | O86: =IFERROR(VLOOKUP(G86,Proveedores!B:D,3,0)," ") | Q86: =VLOOKUP(E86,Tabla_Fletes,3,FALSE) -> #N/A | R86: =IF(P86="Centro",Q86,IF(P86="Norte",Q86*1.6,IF(P86="Occidente",Q86*1.2,IF(P86="Sur",Q86*2)))) -> FALSE | S86: =VLOOKUP(E86,Tabla_Instalacion,2,FALSE) -> #N/A | T86: =IF(P86="Centro",S86,IF(P86="Norte",S86*1.1,IF(P86="Occidente",S86*1.1,IF(P86="Sur",S86*1.1)))) -> FALSE | U86: =IF(F86="Offiho",0,Q86+S86) -> #N/A | V86: =IF(K86=0,U86/$H$573,U86*(K86/L86))*H86 -> #N/A | W86: =IF(F86="Offiho",J86,IF(_xlfn.XLOOKUP(F86,Proveedores!A$2:A$50,Proveedores!E$2:E$50,"")="Nacional",(J86/0.5)+(V86*H86),((J86/0.3/0.5)+(V86*H86)))) -> #N/A | X86: =W86*H86 -> #N/A | Y86: =IF(F86="Sunon Inc",$AJ$577,IF(F86="Alma - Exterior",$AJ$578,IF(F86="Yabo - Hotelería",$AJ$579,IF(F86="OSJ - Medical",$AJ$580,IF(F86="Seezo - Home",$AJ$581,IF(F86="A&D - Home",$AJ$582,IF(F86="Encore Alfombras Hoteleria Asia",$AJ$583,IF(F86="Zhong Xian - Leds",$AJ$584,IF(F86="Tarkett Europa",$AJ$585,IF(F86="2tec2",$AJ$586,IF(F86="Balsan Europa",$AJ$587,IF(F86="Armstrong Pisos USA",$AJ$588,IF(F86="Tarkett USA",$AJ$589,IF(F86="Tarkett Brasil",$AJ$590,IF(F86="Tarkett MX",$AJ$591,IF(F86="Jome",$AJ$592,IF(F86="Offiho",$AJ$593,IF(F86="Lumbro",$AJ$594,IF(F86="Sunon Mty",$AJ$595,IF(F86="Conceptos Sofas",$AJ$596,IF(F86="Lauco Sofas",$AJ$597,IF(F86="CR Global - Mesas Ajustables",$AJ$598,IF(F86="Vandesk",$AJ$599,IF(F86="Mamparas Tela",$AJ$600,IF(F86="Mampara Cristales",$AJ$601,IF(F86="Herrajes",$AJ$602,IF(F86="MetalWork",$AJ$603,IF(F86="Requiez",$AJ$604,IF(F86="Labenze",$AJ$605,IF(F86="Infinity",$AJ$606,IF(F86="Proveedor Externo",$AJ$607))))))))))))))))))))))))))))))) -> FALSE | Z86: 0 | AA86: =W86*Z86 -> #N/A | AB86: =IF(Z86>Y86,"ERROR",(W86-AA86)) -> #N/A | AC86: =AB86*H86 -> #N/A | AD86: =IF(A87=TRUE,MAX(0,1-(AE86/W86)),"NA") -> #N/A | AE86: =IF(A85=FALSE,"NO APLICA",AB86*1.2) -> #N/A | AF86: =AE86*H86 -> #N/A | AG86: =(AC86-N86)/AC86 -> #N/A | AH86: =IF(AG86<30%,"ERROR","OK") -> #N/A
A87: =$A$13 -> TRUE | B87: =A87 -> TRUE | C87: =$C$13 -> Dólares | G87: =IFERROR(VLOOKUP(F87,Tabla_Proveedores_1,2,0)," ") | H87: 0 | I87: =IFERROR(VLOOKUP(G87,Proveedores!B:C,2,0)," ") | J87: 0 | L87: =K87*H87 -> 0 | M87: =IF(F87="Offiho", J87*0.55, IF(AND(F87<>"Sunon Inc",F87<>"Alma - Exterior",F87<>"Yabo - Hotelería",F87<>"OSJ - Medical",F87<>"Seezo - Home",F87<>"A&D -Home",F87<>"Encore Alfombras Hoteleria Asia",F87<>"Zhong Xian - Leds",F87<>"Tarkett Europa",F87<>"2tec2",F87<>"Balsan Europa",F87<>"Armstrong Pisos USA",F87<>"Tarkett USA",F87<>"Tarkett Brasil"),J87,IFERROR(IF(K646<=$AO$578,J87*2.14,IF(K646<=$AN$579,J87*1.8,IF(K646>$AN$580,J87*1.5))),J87))*1.1) -> 0 | N87: =M87*H87 -> 0 | O87: =IFERROR(VLOOKUP(G87,Proveedores!B:D,3,0)," ") | Q87: =VLOOKUP(E87,Tabla_Fletes,3,FALSE) -> #N/A | R87: =IF(P87="Centro",Q87,IF(P87="Norte",Q87*1.6,IF(P87="Occidente",Q87*1.2,IF(P87="Sur",Q87*2)))) -> FALSE | S87: =VLOOKUP(E87,Tabla_Instalacion,2,FALSE) -> #N/A | T87: =IF(P87="Centro",S87,IF(P87="Norte",S87*1.1,IF(P87="Occidente",S87*1.1,IF(P87="Sur",S87*1.1)))) -> FALSE | U87: =IF(F87="Offiho",0,Q87+S87) -> #N/A | V87: =IF(K87=0,U87/$H$573,U87*(K87/L87))*H87 -> #N/A | W87: =IF(F87="Offiho",J87,IF(_xlfn.XLOOKUP(F87,Proveedores!A$2:A$50,Proveedores!E$2:E$50,"")="Nacional",(J87/0.5)+(V87*H87),((J87/0.3/0.5)+(V87*H87)))) -> #N/A | X87: =W87*H87 -> #N/A | Y87: =IF(F87="Sunon Inc",$AJ$577,IF(F87="Alma - Exterior",$AJ$578,IF(F87="Yabo - Hotelería",$AJ$579,IF(F87="OSJ - Medical",$AJ$580,IF(F87="Seezo - Home",$AJ$581,IF(F87="A&D - Home",$AJ$582,IF(F87="Encore Alfombras Hoteleria Asia",$AJ$583,IF(F87="Zhong Xian - Leds",$AJ$584,IF(F87="Tarkett Europa",$AJ$585,IF(F87="2tec2",$AJ$586,IF(F87="Balsan Europa",$AJ$587,IF(F87="Armstrong Pisos USA",$AJ$588,IF(F87="Tarkett USA",$AJ$589,IF(F87="Tarkett Brasil",$AJ$590,IF(F87="Tarkett MX",$AJ$591,IF(F87="Jome",$AJ$592,IF(F87="Offiho",$AJ$593,IF(F87="Lumbro",$AJ$594,IF(F87="Sunon Mty",$AJ$595,IF(F87="Conceptos Sofas",$AJ$596,IF(F87="Lauco Sofas",$AJ$597,IF(F87="CR Global - Mesas Ajustables",$AJ$598,IF(F87="Vandesk",$AJ$599,IF(F87="Mamparas Tela",$AJ$600,IF(F87="Mampara Cristales",$AJ$601,IF(F87="Herrajes",$AJ$602,IF(F87="MetalWork",$AJ$603,IF(F87="Requiez",$AJ$604,IF(F87="Labenze",$AJ$605,IF(F87="Infinity",$AJ$606,IF(F87="Proveedor Externo",$AJ$607))))))))))))))))))))))))))))))) -> FALSE | Z87: 0 | AA87: =W87*Z87 -> #N/A | AB87: =IF(Z87>Y87,"ERROR",(W87-AA87)) -> #N/A | AC87: =AB87*H87 -> #N/A | AD87: =IF(A88=TRUE,MAX(0,1-(AE87/W87)),"NA") -> #N/A | AE87: =IF(A86=FALSE,"NO APLICA",AB87*1.2) -> #N/A | AF87: =AE87*H87 -> #N/A | AG87: =(AC87-N87)/AC87 -> #N/A | AH87: =IF(AG87<30%,"ERROR","OK") -> #N/A
A88: =$A$13 -> TRUE | B88: =A88 -> TRUE | C88: =$C$13 -> Dólares | G88: =IFERROR(VLOOKUP(F88,Tabla_Proveedores_1,2,0)," ") | H88: 0 | I88: =IFERROR(VLOOKUP(G88,Proveedores!B:C,2,0)," ") | J88: 0 | L88: =K88*H88 -> 0 | M88: =IF(F88="Offiho", J88*0.55, IF(AND(F88<>"Sunon Inc",F88<>"Alma - Exterior",F88<>"Yabo - Hotelería",F88<>"OSJ - Medical",F88<>"Seezo - Home",F88<>"A&D -Home",F88<>"Encore Alfombras Hoteleria Asia",F88<>"Zhong Xian - Leds",F88<>"Tarkett Europa",F88<>"2tec2",F88<>"Balsan Europa",F88<>"Armstrong Pisos USA",F88<>"Tarkett USA",F88<>"Tarkett Brasil"),J88,IFERROR(IF(K647<=$AO$578,J88*2.14,IF(K647<=$AN$579,J88*1.8,IF(K647>$AN$580,J88*1.5))),J88))*1.1) -> 0 | N88: =M88*H88 -> 0 | O88: =IFERROR(VLOOKUP(G88,Proveedores!B:D,3,0)," ") | Q88: =VLOOKUP(E88,Tabla_Fletes,3,FALSE) -> #N/A | R88: =IF(P88="Centro",Q88,IF(P88="Norte",Q88*1.6,IF(P88="Occidente",Q88*1.2,IF(P88="Sur",Q88*2)))) -> FALSE | S88: =VLOOKUP(E88,Tabla_Instalacion,2,FALSE) -> #N/A | T88: =IF(P88="Centro",S88,IF(P88="Norte",S88*1.1,IF(P88="Occidente",S88*1.1,IF(P88="Sur",S88*1.1)))) -> FALSE | U88: =IF(F88="Offiho",0,Q88+S88) -> #N/A | V88: =IF(K88=0,U88/$H$573,U88*(K88/L88))*H88 -> #N/A | W88: =IF(F88="Offiho",J88,IF(_xlfn.XLOOKUP(F88,Proveedores!A$2:A$50,Proveedores!E$2:E$50,"")="Nacional",(J88/0.5)+(V88*H88),((J88/0.3/0.5)+(V88*H88)))) -> #N/A | X88: =W88*H88 -> #N/A | Y88: =IF(F88="Sunon Inc",$AJ$577,IF(F88="Alma - Exterior",$AJ$578,IF(F88="Yabo - Hotelería",$AJ$579,IF(F88="OSJ - Medical",$AJ$580,IF(F88="Seezo - Home",$AJ$581,IF(F88="A&D - Home",$AJ$582,IF(F88="Encore Alfombras Hoteleria Asia",$AJ$583,IF(F88="Zhong Xian - Leds",$AJ$584,IF(F88="Tarkett Europa",$AJ$585,IF(F88="2tec2",$AJ$586,IF(F88="Balsan Europa",$AJ$587,IF(F88="Armstrong Pisos USA",$AJ$588,IF(F88="Tarkett USA",$AJ$589,IF(F88="Tarkett Brasil",$AJ$590,IF(F88="Tarkett MX",$AJ$591,IF(F88="Jome",$AJ$592,IF(F88="Offiho",$AJ$593,IF(F88="Lumbro",$AJ$594,IF(F88="Sunon Mty",$AJ$595,IF(F88="Conceptos Sofas",$AJ$596,IF(F88="Lauco Sofas",$AJ$597,IF(F88="CR Global - Mesas Ajustables",$AJ$598,IF(F88="Vandesk",$AJ$599,IF(F88="Mamparas Tela",$AJ$600,IF(F88="Mampara Cristales",$AJ$601,IF(F88="Herrajes",$AJ$602,IF(F88="MetalWork",$AJ$603,IF(F88="Requiez",$AJ$604,IF(F88="Labenze",$AJ$605,IF(F88="Infinity",$AJ$606,IF(F88="Proveedor Externo",$AJ$607))))))))))))))))))))))))))))))) -> FALSE | Z88: 0 | AA88: =W88*Z88 -> #N/A | AB88: =IF(Z88>Y88,"ERROR",(W88-AA88)) -> #N/A | AC88: =AB88*H88 -> #N/A | AD88: =IF(A89=TRUE,MAX(0,1-(AE88/W88)),"NA") -> #N/A | AE88: =IF(A87=FALSE,"NO APLICA",AB88*1.2) -> #N/A | AF88: =AE88*H88 -> #N/A | AG88: =(AC88-N88)/AC88 -> #N/A | AH88: =IF(AG88<30%,"ERROR","OK") -> #N/A
A89: =$A$13 -> TRUE | B89: =A89 -> TRUE | C89: =$C$13 -> Dólares | G89: =IFERROR(VLOOKUP(F89,Tabla_Proveedores_1,2,0)," ") | H89: 0 | I89: =IFERROR(VLOOKUP(G89,Proveedores!B:C,2,0)," ") | J89: 0 | L89: =K89*H89 -> 0 | M89: =IF(F89="Offiho", J89*0.55, IF(AND(F89<>"Sunon Inc",F89<>"Alma - Exterior",F89<>"Yabo - Hotelería",F89<>"OSJ - Medical",F89<>"Seezo - Home",F89<>"A&D -Home",F89<>"Encore Alfombras Hoteleria Asia",F89<>"Zhong Xian - Leds",F89<>"Tarkett Europa",F89<>"2tec2",F89<>"Balsan Europa",F89<>"Armstrong Pisos USA",F89<>"Tarkett USA",F89<>"Tarkett Brasil"),J89,IFERROR(IF(K648<=$AO$578,J89*2.14,IF(K648<=$AN$579,J89*1.8,IF(K648>$AN$580,J89*1.5))),J89))*1.1) -> 0 | N89: =M89*H89 -> 0 | O89: =IFERROR(VLOOKUP(G89,Proveedores!B:D,3,0)," ") | Q89: =VLOOKUP(E89,Tabla_Fletes,3,FALSE) -> #N/A | R89: =IF(P89="Centro",Q89,IF(P89="Norte",Q89*1.6,IF(P89="Occidente",Q89*1.2,IF(P89="Sur",Q89*2)))) -> FALSE | S89: =VLOOKUP(E89,Tabla_Instalacion,2,FALSE) -> #N/A | T89: =IF(P89="Centro",S89,IF(P89="Norte",S89*1.1,IF(P89="Occidente",S89*1.1,IF(P89="Sur",S89*1.1)))) -> FALSE | U89: =IF(F89="Offiho",0,Q89+S89) -> #N/A | V89: =IF(K89=0,U89/$H$573,U89*(K89/L89))*H89 -> #N/A | W89: =IF(F89="Offiho",J89,IF(_xlfn.XLOOKUP(F89,Proveedores!A$2:A$50,Proveedores!E$2:E$50,"")="Nacional",(J89/0.5)+(V89*H89),((J89/0.3/0.5)+(V89*H89)))) -> #N/A | X89: =W89*H89 -> #N/A | Y89: =IF(F89="Sunon Inc",$AJ$577,IF(F89="Alma - Exterior",$AJ$578,IF(F89="Yabo - Hotelería",$AJ$579,IF(F89="OSJ - Medical",$AJ$580,IF(F89="Seezo - Home",$AJ$581,IF(F89="A&D - Home",$AJ$582,IF(F89="Encore Alfombras Hoteleria Asia",$AJ$583,IF(F89="Zhong Xian - Leds",$AJ$584,IF(F89="Tarkett Europa",$AJ$585,IF(F89="2tec2",$AJ$586,IF(F89="Balsan Europa",$AJ$587,IF(F89="Armstrong Pisos USA",$AJ$588,IF(F89="Tarkett USA",$AJ$589,IF(F89="Tarkett Brasil",$AJ$590,IF(F89="Tarkett MX",$AJ$591,IF(F89="Jome",$AJ$592,IF(F89="Offiho",$AJ$593,IF(F89="Lumbro",$AJ$594,IF(F89="Sunon Mty",$AJ$595,IF(F89="Conceptos Sofas",$AJ$596,IF(F89="Lauco Sofas",$AJ$597,IF(F89="CR Global - Mesas Ajustables",$AJ$598,IF(F89="Vandesk",$AJ$599,IF(F89="Mamparas Tela",$AJ$600,IF(F89="Mampara Cristales",$AJ$601,IF(F89="Herrajes",$AJ$602,IF(F89="MetalWork",$AJ$603,IF(F89="Requiez",$AJ$604,IF(F89="Labenze",$AJ$605,IF(F89="Infinity",$AJ$606,IF(F89="Proveedor Externo",$AJ$607))))))))))))))))))))))))))))))) -> FALSE | Z89: 0 | AA89: =W89*Z89 -> #N/A | AB89: =IF(Z89>Y89,"ERROR",(W89-AA89)) -> #N/A | AC89: =AB89*H89 -> #N/A | AD89: =IF(A90=TRUE,MAX(0,1-(AE89/W89)),"NA") -> #N/A | AE89: =IF(A88=FALSE,"NO APLICA",AB89*1.2) -> #N/A | AF89: =AE89*H89 -> #N/A | AG89: =(AC89-N89)/AC89 -> #N/A | AH89: =IF(AG89<30%,"ERROR","OK") -> #N/A
A90: =$A$13 -> TRUE | B90: =A90 -> TRUE | C90: =$C$13 -> Dólares | G90: =IFERROR(VLOOKUP(F90,Tabla_Proveedores_1,2,0)," ") | H90: 0 | I90: =IFERROR(VLOOKUP(G90,Proveedores!B:C,2,0)," ") | J90: 0 | L90: =K90*H90 -> 0 | M90: =IF(F90="Offiho", J90*0.55, IF(AND(F90<>"Sunon Inc",F90<>"Alma - Exterior",F90<>"Yabo - Hotelería",F90<>"OSJ - Medical",F90<>"Seezo - Home",F90<>"A&D -Home",F90<>"Encore Alfombras Hoteleria Asia",F90<>"Zhong Xian - Leds",F90<>"Tarkett Europa",F90<>"2tec2",F90<>"Balsan Europa",F90<>"Armstrong Pisos USA",F90<>"Tarkett USA",F90<>"Tarkett Brasil"),J90,IFERROR(IF(K649<=$AO$578,J90*2.14,IF(K649<=$AN$579,J90*1.8,IF(K649>$AN$580,J90*1.5))),J90))*1.1) -> 0 | N90: =M90*H90 -> 0 | O90: =IFERROR(VLOOKUP(G90,Proveedores!B:D,3,0)," ") | Q90: =VLOOKUP(E90,Tabla_Fletes,3,FALSE) -> #N/A | R90: =IF(P90="Centro",Q90,IF(P90="Norte",Q90*1.6,IF(P90="Occidente",Q90*1.2,IF(P90="Sur",Q90*2)))) -> FALSE | S90: =VLOOKUP(E90,Tabla_Instalacion,2,FALSE) -> #N/A | T90: =IF(P90="Centro",S90,IF(P90="Norte",S90*1.1,IF(P90="Occidente",S90*1.1,IF(P90="Sur",S90*1.1)))) -> FALSE | U90: =IF(F90="Offiho",0,Q90+S90) -> #N/A | V90: =IF(K90=0,U90/$H$573,U90*(K90/L90))*H90 -> #N/A | W90: =IF(F90="Offiho",J90,IF(_xlfn.XLOOKUP(F90,Proveedores!A$2:A$50,Proveedores!E$2:E$50,"")="Nacional",(J90/0.5)+(V90*H90),((J90/0.3/0.5)+(V90*H90)))) -> #N/A | X90: =W90*H90 -> #N/A | Y90: =IF(F90="Sunon Inc",$AJ$577,IF(F90="Alma - Exterior",$AJ$578,IF(F90="Yabo - Hotelería",$AJ$579,IF(F90="OSJ - Medical",$AJ$580,IF(F90="Seezo - Home",$AJ$581,IF(F90="A&D - Home",$AJ$582,IF(F90="Encore Alfombras Hoteleria Asia",$AJ$583,IF(F90="Zhong Xian - Leds",$AJ$584,IF(F90="Tarkett Europa",$AJ$585,IF(F90="2tec2",$AJ$586,IF(F90="Balsan Europa",$AJ$587,IF(F90="Armstrong Pisos USA",$AJ$588,IF(F90="Tarkett USA",$AJ$589,IF(F90="Tarkett Brasil",$AJ$590,IF(F90="Tarkett MX",$AJ$591,IF(F90="Jome",$AJ$592,IF(F90="Offiho",$AJ$593,IF(F90="Lumbro",$AJ$594,IF(F90="Sunon Mty",$AJ$595,IF(F90="Conceptos Sofas",$AJ$596,IF(F90="Lauco Sofas",$AJ$597,IF(F90="CR Global - Mesas Ajustables",$AJ$598,IF(F90="Vandesk",$AJ$599,IF(F90="Mamparas Tela",$AJ$600,IF(F90="Mampara Cristales",$AJ$601,IF(F90="Herrajes",$AJ$602,IF(F90="MetalWork",$AJ$603,IF(F90="Requiez",$AJ$604,IF(F90="Labenze",$AJ$605,IF(F90="Infinity",$AJ$606,IF(F90="Proveedor Externo",$AJ$607))))))))))))))))))))))))))))))) -> FALSE | Z90: 0 | AA90: =W90*Z90 -> #N/A | AB90: =IF(Z90>Y90,"ERROR",(W90-AA90)) -> #N/A | AC90: =AB90*H90 -> #N/A | AD90: =IF(A91=TRUE,MAX(0,1-(AE90/W90)),"NA") -> #N/A | AE90: =IF(A89=FALSE,"NO APLICA",AB90*1.2) -> #N/A | AF90: =AE90*H90 -> #N/A | AG90: =(AC90-N90)/AC90 -> #N/A | AH90: =IF(AG90<30%,"ERROR","OK") -> #N/A
A91: =$A$13 -> TRUE | B91: =A91 -> TRUE | C91: =$C$13 -> Dólares | G91: =IFERROR(VLOOKUP(F91,Tabla_Proveedores_1,2,0)," ") | H91: 0 | I91: =IFERROR(VLOOKUP(G91,Proveedores!B:C,2,0)," ") | J91: 0 | L91: =K91*H91 -> 0 | M91: =IF(F91="Offiho", J91*0.55, IF(AND(F91<>"Sunon Inc",F91<>"Alma - Exterior",F91<>"Yabo - Hotelería",F91<>"OSJ - Medical",F91<>"Seezo - Home",F91<>"A&D -Home",F91<>"Encore Alfombras Hoteleria Asia",F91<>"Zhong Xian - Leds",F91<>"Tarkett Europa",F91<>"2tec2",F91<>"Balsan Europa",F91<>"Armstrong Pisos USA",F91<>"Tarkett USA",F91<>"Tarkett Brasil"),J91,IFERROR(IF(K650<=$AO$578,J91*2.14,IF(K650<=$AN$579,J91*1.8,IF(K650>$AN$580,J91*1.5))),J91))*1.1) -> 0 | N91: =M91*H91 -> 0 | O91: =IFERROR(VLOOKUP(G91,Proveedores!B:D,3,0)," ") | Q91: =VLOOKUP(E91,Tabla_Fletes,3,FALSE) -> #N/A | R91: =IF(P91="Centro",Q91,IF(P91="Norte",Q91*1.6,IF(P91="Occidente",Q91*1.2,IF(P91="Sur",Q91*2)))) -> FALSE | S91: =VLOOKUP(E91,Tabla_Instalacion,2,FALSE) -> #N/A | T91: =IF(P91="Centro",S91,IF(P91="Norte",S91*1.1,IF(P91="Occidente",S91*1.1,IF(P91="Sur",S91*1.1)))) -> FALSE | U91: =IF(F91="Offiho",0,Q91+S91) -> #N/A | V91: =IF(K91=0,U91/$H$573,U91*(K91/L91))*H91 -> #N/A | W91: =IF(F91="Offiho",J91,IF(_xlfn.XLOOKUP(F91,Proveedores!A$2:A$50,Proveedores!E$2:E$50,"")="Nacional",(J91/0.5)+(V91*H91),((J91/0.3/0.5)+(V91*H91)))) -> #N/A | X91: =W91*H91 -> #N/A | Y91: =IF(F91="Sunon Inc",$AJ$577,IF(F91="Alma - Exterior",$AJ$578,IF(F91="Yabo - Hotelería",$AJ$579,IF(F91="OSJ - Medical",$AJ$580,IF(F91="Seezo - Home",$AJ$581,IF(F91="A&D - Home",$AJ$582,IF(F91="Encore Alfombras Hoteleria Asia",$AJ$583,IF(F91="Zhong Xian - Leds",$AJ$584,IF(F91="Tarkett Europa",$AJ$585,IF(F91="2tec2",$AJ$586,IF(F91="Balsan Europa",$AJ$587,IF(F91="Armstrong Pisos USA",$AJ$588,IF(F91="Tarkett USA",$AJ$589,IF(F91="Tarkett Brasil",$AJ$590,IF(F91="Tarkett MX",$AJ$591,IF(F91="Jome",$AJ$592,IF(F91="Offiho",$AJ$593,IF(F91="Lumbro",$AJ$594,IF(F91="Sunon Mty",$AJ$595,IF(F91="Conceptos Sofas",$AJ$596,IF(F91="Lauco Sofas",$AJ$597,IF(F91="CR Global - Mesas Ajustables",$AJ$598,IF(F91="Vandesk",$AJ$599,IF(F91="Mamparas Tela",$AJ$600,IF(F91="Mampara Cristales",$AJ$601,IF(F91="Herrajes",$AJ$602,IF(F91="MetalWork",$AJ$603,IF(F91="Requiez",$AJ$604,IF(F91="Labenze",$AJ$605,IF(F91="Infinity",$AJ$606,IF(F91="Proveedor Externo",$AJ$607))))))))))))))))))))))))))))))) -> FALSE | Z91: 0 | AA91: =W91*Z91 -> #N/A | AB91: =IF(Z91>Y91,"ERROR",(W91-AA91)) -> #N/A | AC91: =AB91*H91 -> #N/A | AD91: =IF(A92=TRUE,MAX(0,1-(AE91/W91)),"NA") -> #N/A | AE91: =IF(A90=FALSE,"NO APLICA",AB91*1.2) -> #N/A | AF91: =AE91*H91 -> #N/A | AG91: =(AC91-N91)/AC91 -> #N/A | AH91: =IF(AG91<30%,"ERROR","OK") -> #N/A
A92: =$A$13 -> TRUE | B92: =A92 -> TRUE | C92: =$C$13 -> Dólares | G92: =IFERROR(VLOOKUP(F92,Tabla_Proveedores_1,2,0)," ") | H92: 0 | I92: =IFERROR(VLOOKUP(G92,Proveedores!B:C,2,0)," ") | J92: 0 | L92: =K92*H92 -> 0 | M92: =IF(F92="Offiho", J92*0.55, IF(AND(F92<>"Sunon Inc",F92<>"Alma - Exterior",F92<>"Yabo - Hotelería",F92<>"OSJ - Medical",F92<>"Seezo - Home",F92<>"A&D -Home",F92<>"Encore Alfombras Hoteleria Asia",F92<>"Zhong Xian - Leds",F92<>"Tarkett Europa",F92<>"2tec2",F92<>"Balsan Europa",F92<>"Armstrong Pisos USA",F92<>"Tarkett USA",F92<>"Tarkett Brasil"),J92,IFERROR(IF(K651<=$AO$578,J92*2.14,IF(K651<=$AN$579,J92*1.8,IF(K651>$AN$580,J92*1.5))),J92))*1.1) -> 0 | N92: =M92*H92 -> 0 | O92: =IFERROR(VLOOKUP(G92,Proveedores!B:D,3,0)," ") | Q92: =VLOOKUP(E92,Tabla_Fletes,3,FALSE) -> #N/A | R92: =IF(P92="Centro",Q92,IF(P92="Norte",Q92*1.6,IF(P92="Occidente",Q92*1.2,IF(P92="Sur",Q92*2)))) -> FALSE | S92: =VLOOKUP(E92,Tabla_Instalacion,2,FALSE) -> #N/A | T92: =IF(P92="Centro",S92,IF(P92="Norte",S92*1.1,IF(P92="Occidente",S92*1.1,IF(P92="Sur",S92*1.1)))) -> FALSE | U92: =IF(F92="Offiho",0,Q92+S92) -> #N/A | V92: =IF(K92=0,U92/$H$573,U92*(K92/L92))*H92 -> #N/A | W92: =IF(F92="Offiho",J92,IF(_xlfn.XLOOKUP(F92,Proveedores!A$2:A$50,Proveedores!E$2:E$50,"")="Nacional",(J92/0.5)+(V92*H92),((J92/0.3/0.5)+(V92*H92)))) -> #N/A | X92: =W92*H92 -> #N/A | Y92: =IF(F92="Sunon Inc",$AJ$577,IF(F92="Alma - Exterior",$AJ$578,IF(F92="Yabo - Hotelería",$AJ$579,IF(F92="OSJ - Medical",$AJ$580,IF(F92="Seezo - Home",$AJ$581,IF(F92="A&D - Home",$AJ$582,IF(F92="Encore Alfombras Hoteleria Asia",$AJ$583,IF(F92="Zhong Xian - Leds",$AJ$584,IF(F92="Tarkett Europa",$AJ$585,IF(F92="2tec2",$AJ$586,IF(F92="Balsan Europa",$AJ$587,IF(F92="Armstrong Pisos USA",$AJ$588,IF(F92="Tarkett USA",$AJ$589,IF(F92="Tarkett Brasil",$AJ$590,IF(F92="Tarkett MX",$AJ$591,IF(F92="Jome",$AJ$592,IF(F92="Offiho",$AJ$593,IF(F92="Lumbro",$AJ$594,IF(F92="Sunon Mty",$AJ$595,IF(F92="Conceptos Sofas",$AJ$596,IF(F92="Lauco Sofas",$AJ$597,IF(F92="CR Global - Mesas Ajustables",$AJ$598,IF(F92="Vandesk",$AJ$599,IF(F92="Mamparas Tela",$AJ$600,IF(F92="Mampara Cristales",$AJ$601,IF(F92="Herrajes",$AJ$602,IF(F92="MetalWork",$AJ$603,IF(F92="Requiez",$AJ$604,IF(F92="Labenze",$AJ$605,IF(F92="Infinity",$AJ$606,IF(F92="Proveedor Externo",$AJ$607))))))))))))))))))))))))))))))) -> FALSE | Z92: 0 | AA92: =W92*Z92 -> #N/A | AB92: =IF(Z92>Y92,"ERROR",(W92-AA92)) -> #N/A | AC92: =AB92*H92 -> #N/A | AD92: =IF(A93=TRUE,MAX(0,1-(AE92/W92)),"NA") -> #N/A | AE92: =IF(A91=FALSE,"NO APLICA",AB92*1.2) -> #N/A | AF92: =AE92*H92 -> #N/A | AG92: =(AC92-N92)/AC92 -> #N/A | AH92: =IF(AG92<30%,"ERROR","OK") -> #N/A
A93: =$A$13 -> TRUE | B93: =A93 -> TRUE | C93: =$C$13 -> Dólares | G93: =IFERROR(VLOOKUP(F93,Tabla_Proveedores_1,2,0)," ") | H93: 0 | I93: =IFERROR(VLOOKUP(G93,Proveedores!B:C,2,0)," ") | J93: 0 | L93: =K93*H93 -> 0 | M93: =IF(F93="Offiho", J93*0.55, IF(AND(F93<>"Sunon Inc",F93<>"Alma - Exterior",F93<>"Yabo - Hotelería",F93<>"OSJ - Medical",F93<>"Seezo - Home",F93<>"A&D -Home",F93<>"Encore Alfombras Hoteleria Asia",F93<>"Zhong Xian - Leds",F93<>"Tarkett Europa",F93<>"2tec2",F93<>"Balsan Europa",F93<>"Armstrong Pisos USA",F93<>"Tarkett USA",F93<>"Tarkett Brasil"),J93,IFERROR(IF(K652<=$AO$578,J93*2.14,IF(K652<=$AN$579,J93*1.8,IF(K652>$AN$580,J93*1.5))),J93))*1.1) -> 0 | N93: =M93*H93 -> 0 | O93: =IFERROR(VLOOKUP(G93,Proveedores!B:D,3,0)," ") | Q93: =VLOOKUP(E93,Tabla_Fletes,3,FALSE) -> #N/A | R93: =IF(P93="Centro",Q93,IF(P93="Norte",Q93*1.6,IF(P93="Occidente",Q93*1.2,IF(P93="Sur",Q93*2)))) -> FALSE | S93: =VLOOKUP(E93,Tabla_Instalacion,2,FALSE) -> #N/A | T93: =IF(P93="Centro",S93,IF(P93="Norte",S93*1.1,IF(P93="Occidente",S93*1.1,IF(P93="Sur",S93*1.1)))) -> FALSE | U93: =IF(F93="Offiho",0,Q93+S93) -> #N/A | V93: =IF(K93=0,U93/$H$573,U93*(K93/L93))*H93 -> #N/A | W93: =IF(F93="Offiho",J93,IF(_xlfn.XLOOKUP(F93,Proveedores!A$2:A$50,Proveedores!E$2:E$50,"")="Nacional",(J93/0.5)+(V93*H93),((J93/0.3/0.5)+(V93*H93)))) -> #N/A | X93: =W93*H93 -> #N/A | Y93: =IF(F93="Sunon Inc",$AJ$577,IF(F93="Alma - Exterior",$AJ$578,IF(F93="Yabo - Hotelería",$AJ$579,IF(F93="OSJ - Medical",$AJ$580,IF(F93="Seezo - Home",$AJ$581,IF(F93="A&D - Home",$AJ$582,IF(F93="Encore Alfombras Hoteleria Asia",$AJ$583,IF(F93="Zhong Xian - Leds",$AJ$584,IF(F93="Tarkett Europa",$AJ$585,IF(F93="2tec2",$AJ$586,IF(F93="Balsan Europa",$AJ$587,IF(F93="Armstrong Pisos USA",$AJ$588,IF(F93="Tarkett USA",$AJ$589,IF(F93="Tarkett Brasil",$AJ$590,IF(F93="Tarkett MX",$AJ$591,IF(F93="Jome",$AJ$592,IF(F93="Offiho",$AJ$593,IF(F93="Lumbro",$AJ$594,IF(F93="Sunon Mty",$AJ$595,IF(F93="Conceptos Sofas",$AJ$596,IF(F93="Lauco Sofas",$AJ$597,IF(F93="CR Global - Mesas Ajustables",$AJ$598,IF(F93="Vandesk",$AJ$599,IF(F93="Mamparas Tela",$AJ$600,IF(F93="Mampara Cristales",$AJ$601,IF(F93="Herrajes",$AJ$602,IF(F93="MetalWork",$AJ$603,IF(F93="Requiez",$AJ$604,IF(F93="Labenze",$AJ$605,IF(F93="Infinity",$AJ$606,IF(F93="Proveedor Externo",$AJ$607))))))))))))))))))))))))))))))) -> FALSE | Z93: 0 | AA93: =W93*Z93 -> #N/A | AB93: =IF(Z93>Y93,"ERROR",(W93-AA93)) -> #N/A | AC93: =AB93*H93 -> #N/A | AD93: =IF(A94=TRUE,MAX(0,1-(AE93/W93)),"NA") -> #N/A | AE93: =IF(A92=FALSE,"NO APLICA",AB93*1.2) -> #N/A | AF93: =AE93*H93 -> #N/A | AG93: =(AC93-N93)/AC93 -> #N/A | AH93: =IF(AG93<30%,"ERROR","OK") -> #N/A
A94: =$A$13 -> TRUE | B94: =A94 -> TRUE | C94: =$C$13 -> Dólares | G94: =IFERROR(VLOOKUP(F94,Tabla_Proveedores_1,2,0)," ") | H94: 0 | I94: =IFERROR(VLOOKUP(G94,Proveedores!B:C,2,0)," ") | J94: 0 | L94: =K94*H94 -> 0 | M94: =IF(F94="Offiho", J94*0.55, IF(AND(F94<>"Sunon Inc",F94<>"Alma - Exterior",F94<>"Yabo - Hotelería",F94<>"OSJ - Medical",F94<>"Seezo - Home",F94<>"A&D -Home",F94<>"Encore Alfombras Hoteleria Asia",F94<>"Zhong Xian - Leds",F94<>"Tarkett Europa",F94<>"2tec2",F94<>"Balsan Europa",F94<>"Armstrong Pisos USA",F94<>"Tarkett USA",F94<>"Tarkett Brasil"),J94,IFERROR(IF(K653<=$AO$578,J94*2.14,IF(K653<=$AN$579,J94*1.8,IF(K653>$AN$580,J94*1.5))),J94))*1.1) -> 0 | N94: =M94*H94 -> 0 | O94: =IFERROR(VLOOKUP(G94,Proveedores!B:D,3,0)," ") | Q94: =VLOOKUP(E94,Tabla_Fletes,3,FALSE) -> #N/A | R94: =IF(P94="Centro",Q94,IF(P94="Norte",Q94*1.6,IF(P94="Occidente",Q94*1.2,IF(P94="Sur",Q94*2)))) -> FALSE | S94: =VLOOKUP(E94,Tabla_Instalacion,2,FALSE) -> #N/A | T94: =IF(P94="Centro",S94,IF(P94="Norte",S94*1.1,IF(P94="Occidente",S94*1.1,IF(P94="Sur",S94*1.1)))) -> FALSE | U94: =IF(F94="Offiho",0,Q94+S94) -> #N/A | V94: =IF(K94=0,U94/$H$573,U94*(K94/L94))*H94 -> #N/A | W94: =IF(F94="Offiho",J94,IF(_xlfn.XLOOKUP(F94,Proveedores!A$2:A$50,Proveedores!E$2:E$50,"")="Nacional",(J94/0.5)+(V94*H94),((J94/0.3/0.5)+(V94*H94)))) -> #N/A | X94: =W94*H94 -> #N/A | Y94: =IF(F94="Sunon Inc",$AJ$577,IF(F94="Alma - Exterior",$AJ$578,IF(F94="Yabo - Hotelería",$AJ$579,IF(F94="OSJ - Medical",$AJ$580,IF(F94="Seezo - Home",$AJ$581,IF(F94="A&D - Home",$AJ$582,IF(F94="Encore Alfombras Hoteleria Asia",$AJ$583,IF(F94="Zhong Xian - Leds",$AJ$584,IF(F94="Tarkett Europa",$AJ$585,IF(F94="2tec2",$AJ$586,IF(F94="Balsan Europa",$AJ$587,IF(F94="Armstrong Pisos USA",$AJ$588,IF(F94="Tarkett USA",$AJ$589,IF(F94="Tarkett Brasil",$AJ$590,IF(F94="Tarkett MX",$AJ$591,IF(F94="Jome",$AJ$592,IF(F94="Offiho",$AJ$593,IF(F94="Lumbro",$AJ$594,IF(F94="Sunon Mty",$AJ$595,IF(F94="Conceptos Sofas",$AJ$596,IF(F94="Lauco Sofas",$AJ$597,IF(F94="CR Global - Mesas Ajustables",$AJ$598,IF(F94="Vandesk",$AJ$599,IF(F94="Mamparas Tela",$AJ$600,IF(F94="Mampara Cristales",$AJ$601,IF(F94="Herrajes",$AJ$602,IF(F94="MetalWork",$AJ$603,IF(F94="Requiez",$AJ$604,IF(F94="Labenze",$AJ$605,IF(F94="Infinity",$AJ$606,IF(F94="Proveedor Externo",$AJ$607))))))))))))))))))))))))))))))) -> FALSE | Z94: 0 | AA94: =W94*Z94 -> #N/A | AB94: =IF(Z94>Y94,"ERROR",(W94-AA94)) -> #N/A | AC94: =AB94*H94 -> #N/A | AD94: =IF(A95=TRUE,MAX(0,1-(AE94/W94)),"NA") -> #N/A | AE94: =IF(A93=FALSE,"NO APLICA",AB94*1.2) -> #N/A | AF94: =AE94*H94 -> #N/A | AG94: =(AC94-N94)/AC94 -> #N/A | AH94: =IF(AG94<30%,"ERROR","OK") -> #N/A
A95: =$A$13 -> TRUE | B95: =A95 -> TRUE | C95: =$C$13 -> Dólares | G95: =IFERROR(VLOOKUP(F95,Tabla_Proveedores_1,2,0)," ") | H95: 0 | I95: =IFERROR(VLOOKUP(G95,Proveedores!B:C,2,0)," ") | J95: 0 | L95: =K95*H95 -> 0 | M95: =IF(F95="Offiho", J95*0.55, IF(AND(F95<>"Sunon Inc",F95<>"Alma - Exterior",F95<>"Yabo - Hotelería",F95<>"OSJ - Medical",F95<>"Seezo - Home",F95<>"A&D -Home",F95<>"Encore Alfombras Hoteleria Asia",F95<>"Zhong Xian - Leds",F95<>"Tarkett Europa",F95<>"2tec2",F95<>"Balsan Europa",F95<>"Armstrong Pisos USA",F95<>"Tarkett USA",F95<>"Tarkett Brasil"),J95,IFERROR(IF(K654<=$AO$578,J95*2.14,IF(K654<=$AN$579,J95*1.8,IF(K654>$AN$580,J95*1.5))),J95))*1.1) -> 0 | N95: =M95*H95 -> 0 | O95: =IFERROR(VLOOKUP(G95,Proveedores!B:D,3,0)," ") | Q95: =VLOOKUP(E95,Tabla_Fletes,3,FALSE) -> #N/A | R95: =IF(P95="Centro",Q95,IF(P95="Norte",Q95*1.6,IF(P95="Occidente",Q95*1.2,IF(P95="Sur",Q95*2)))) -> FALSE | S95: =VLOOKUP(E95,Tabla_Instalacion,2,FALSE) -> #N/A | T95: =IF(P95="Centro",S95,IF(P95="Norte",S95*1.1,IF(P95="Occidente",S95*1.1,IF(P95="Sur",S95*1.1)))) -> FALSE | U95: =IF(F95="Offiho",0,Q95+S95) -> #N/A | V95: =IF(K95=0,U95/$H$573,U95*(K95/L95))*H95 -> #N/A | W95: =IF(F95="Offiho",J95,IF(_xlfn.XLOOKUP(F95,Proveedores!A$2:A$50,Proveedores!E$2:E$50,"")="Nacional",(J95/0.5)+(V95*H95),((J95/0.3/0.5)+(V95*H95)))) -> #N/A | X95: =W95*H95 -> #N/A | Y95: =IF(F95="Sunon Inc",$AJ$577,IF(F95="Alma - Exterior",$AJ$578,IF(F95="Yabo - Hotelería",$AJ$579,IF(F95="OSJ - Medical",$AJ$580,IF(F95="Seezo - Home",$AJ$581,IF(F95="A&D - Home",$AJ$582,IF(F95="Encore Alfombras Hoteleria Asia",$AJ$583,IF(F95="Zhong Xian - Leds",$AJ$584,IF(F95="Tarkett Europa",$AJ$585,IF(F95="2tec2",$AJ$586,IF(F95="Balsan Europa",$AJ$587,IF(F95="Armstrong Pisos USA",$AJ$588,IF(F95="Tarkett USA",$AJ$589,IF(F95="Tarkett Brasil",$AJ$590,IF(F95="Tarkett MX",$AJ$591,IF(F95="Jome",$AJ$592,IF(F95="Offiho",$AJ$593,IF(F95="Lumbro",$AJ$594,IF(F95="Sunon Mty",$AJ$595,IF(F95="Conceptos Sofas",$AJ$596,IF(F95="Lauco Sofas",$AJ$597,IF(F95="CR Global - Mesas Ajustables",$AJ$598,IF(F95="Vandesk",$AJ$599,IF(F95="Mamparas Tela",$AJ$600,IF(F95="Mampara Cristales",$AJ$601,IF(F95="Herrajes",$AJ$602,IF(F95="MetalWork",$AJ$603,IF(F95="Requiez",$AJ$604,IF(F95="Labenze",$AJ$605,IF(F95="Infinity",$AJ$606,IF(F95="Proveedor Externo",$AJ$607))))))))))))))))))))))))))))))) -> FALSE | Z95: 0 | AA95: =W95*Z95 -> #N/A | AB95: =IF(Z95>Y95,"ERROR",(W95-AA95)) -> #N/A | AC95: =AB95*H95 -> #N/A | AD95: =IF(A96=TRUE,MAX(0,1-(AE95/W95)),"NA") -> #N/A | AE95: =IF(A94=FALSE,"NO APLICA",AB95*1.2) -> #N/A | AF95: =AE95*H95 -> #N/A | AG95: =(AC95-N95)/AC95 -> #N/A | AH95: =IF(AG95<30%,"ERROR","OK") -> #N/A
A96: =$A$13 -> TRUE | B96: =A96 -> TRUE | C96: =$C$13 -> Dólares | G96: =IFERROR(VLOOKUP(F96,Tabla_Proveedores_1,2,0)," ") | H96: 0 | I96: =IFERROR(VLOOKUP(G96,Proveedores!B:C,2,0)," ") | J96: 0 | L96: =K96*H96 -> 0 | M96: =IF(F96="Offiho", J96*0.55, IF(AND(F96<>"Sunon Inc",F96<>"Alma - Exterior",F96<>"Yabo - Hotelería",F96<>"OSJ - Medical",F96<>"Seezo - Home",F96<>"A&D -Home",F96<>"Encore Alfombras Hoteleria Asia",F96<>"Zhong Xian - Leds",F96<>"Tarkett Europa",F96<>"2tec2",F96<>"Balsan Europa",F96<>"Armstrong Pisos USA",F96<>"Tarkett USA",F96<>"Tarkett Brasil"),J96,IFERROR(IF(K655<=$AO$578,J96*2.14,IF(K655<=$AN$579,J96*1.8,IF(K655>$AN$580,J96*1.5))),J96))*1.1) -> 0 | N96: =M96*H96 -> 0 | O96: =IFERROR(VLOOKUP(G96,Proveedores!B:D,3,0)," ") | Q96: =VLOOKUP(E96,Tabla_Fletes,3,FALSE) -> #N/A | R96: =IF(P96="Centro",Q96,IF(P96="Norte",Q96*1.6,IF(P96="Occidente",Q96*1.2,IF(P96="Sur",Q96*2)))) -> FALSE | S96: =VLOOKUP(E96,Tabla_Instalacion,2,FALSE) -> #N/A | T96: =IF(P96="Centro",S96,IF(P96="Norte",S96*1.1,IF(P96="Occidente",S96*1.1,IF(P96="Sur",S96*1.1)))) -> FALSE | U96: =IF(F96="Offiho",0,Q96+S96) -> #N/A | V96: =IF(K96=0,U96/$H$573,U96*(K96/L96))*H96 -> #N/A | W96: =IF(F96="Offiho",J96,IF(_xlfn.XLOOKUP(F96,Proveedores!A$2:A$50,Proveedores!E$2:E$50,"")="Nacional",(J96/0.5)+(V96*H96),((J96/0.3/0.5)+(V96*H96)))) -> #N/A | X96: =W96*H96 -> #N/A | Y96: =IF(F96="Sunon Inc",$AJ$577,IF(F96="Alma - Exterior",$AJ$578,IF(F96="Yabo - Hotelería",$AJ$579,IF(F96="OSJ - Medical",$AJ$580,IF(F96="Seezo - Home",$AJ$581,IF(F96="A&D - Home",$AJ$582,IF(F96="Encore Alfombras Hoteleria Asia",$AJ$583,IF(F96="Zhong Xian - Leds",$AJ$584,IF(F96="Tarkett Europa",$AJ$585,IF(F96="2tec2",$AJ$586,IF(F96="Balsan Europa",$AJ$587,IF(F96="Armstrong Pisos USA",$AJ$588,IF(F96="Tarkett USA",$AJ$589,IF(F96="Tarkett Brasil",$AJ$590,IF(F96="Tarkett MX",$AJ$591,IF(F96="Jome",$AJ$592,IF(F96="Offiho",$AJ$593,IF(F96="Lumbro",$AJ$594,IF(F96="Sunon Mty",$AJ$595,IF(F96="Conceptos Sofas",$AJ$596,IF(F96="Lauco Sofas",$AJ$597,IF(F96="CR Global - Mesas Ajustables",$AJ$598,IF(F96="Vandesk",$AJ$599,IF(F96="Mamparas Tela",$AJ$600,IF(F96="Mampara Cristales",$AJ$601,IF(F96="Herrajes",$AJ$602,IF(F96="MetalWork",$AJ$603,IF(F96="Requiez",$AJ$604,IF(F96="Labenze",$AJ$605,IF(F96="Infinity",$AJ$606,IF(F96="Proveedor Externo",$AJ$607))))))))))))))))))))))))))))))) -> FALSE | Z96: 0 | AA96: =W96*Z96 -> #N/A | AB96: =IF(Z96>Y96,"ERROR",(W96-AA96)) -> #N/A | AC96: =AB96*H96 -> #N/A | AD96: =IF(A97=TRUE,MAX(0,1-(AE96/W96)),"NA") -> #N/A | AE96: =IF(A95=FALSE,"NO APLICA",AB96*1.2) -> #N/A | AF96: =AE96*H96 -> #N/A | AG96: =(AC96-N96)/AC96 -> #N/A | AH96: =IF(AG96<30%,"ERROR","OK") -> #N/A
A97: =$A$13 -> TRUE | B97: =A97 -> TRUE | C97: =$C$13 -> Dólares | G97: =IFERROR(VLOOKUP(F97,Tabla_Proveedores_1,2,0)," ") | H97: 0 | I97: =IFERROR(VLOOKUP(G97,Proveedores!B:C,2,0)," ") | J97: 0 | L97: =K97*H97 -> 0 | M97: =IF(F97="Offiho", J97*0.55, IF(AND(F97<>"Sunon Inc",F97<>"Alma - Exterior",F97<>"Yabo - Hotelería",F97<>"OSJ - Medical",F97<>"Seezo - Home",F97<>"A&D -Home",F97<>"Encore Alfombras Hoteleria Asia",F97<>"Zhong Xian - Leds",F97<>"Tarkett Europa",F97<>"2tec2",F97<>"Balsan Europa",F97<>"Armstrong Pisos USA",F97<>"Tarkett USA",F97<>"Tarkett Brasil"),J97,IFERROR(IF(K656<=$AO$578,J97*2.14,IF(K656<=$AN$579,J97*1.8,IF(K656>$AN$580,J97*1.5))),J97))*1.1) -> 0 | N97: =M97*H97 -> 0 | O97: =IFERROR(VLOOKUP(G97,Proveedores!B:D,3,0)," ") | Q97: =VLOOKUP(E97,Tabla_Fletes,3,FALSE) -> #N/A | R97: =IF(P97="Centro",Q97,IF(P97="Norte",Q97*1.6,IF(P97="Occidente",Q97*1.2,IF(P97="Sur",Q97*2)))) -> FALSE | S97: =VLOOKUP(E97,Tabla_Instalacion,2,FALSE) -> #N/A | T97: =IF(P97="Centro",S97,IF(P97="Norte",S97*1.1,IF(P97="Occidente",S97*1.1,IF(P97="Sur",S97*1.1)))) -> FALSE | U97: =IF(F97="Offiho",0,Q97+S97) -> #N/A | V97: =IF(K97=0,U97/$H$573,U97*(K97/L97))*H97 -> #N/A | W97: =IF(F97="Offiho",J97,IF(_xlfn.XLOOKUP(F97,Proveedores!A$2:A$50,Proveedores!E$2:E$50,"")="Nacional",(J97/0.5)+(V97*H97),((J97/0.3/0.5)+(V97*H97)))) -> #N/A | X97: =W97*H97 -> #N/A | Y97: =IF(F97="Sunon Inc",$AJ$577,IF(F97="Alma - Exterior",$AJ$578,IF(F97="Yabo - Hotelería",$AJ$579,IF(F97="OSJ - Medical",$AJ$580,IF(F97="Seezo - Home",$AJ$581,IF(F97="A&D - Home",$AJ$582,IF(F97="Encore Alfombras Hoteleria Asia",$AJ$583,IF(F97="Zhong Xian - Leds",$AJ$584,IF(F97="Tarkett Europa",$AJ$585,IF(F97="2tec2",$AJ$586,IF(F97="Balsan Europa",$AJ$587,IF(F97="Armstrong Pisos USA",$AJ$588,IF(F97="Tarkett USA",$AJ$589,IF(F97="Tarkett Brasil",$AJ$590,IF(F97="Tarkett MX",$AJ$591,IF(F97="Jome",$AJ$592,IF(F97="Offiho",$AJ$593,IF(F97="Lumbro",$AJ$594,IF(F97="Sunon Mty",$AJ$595,IF(F97="Conceptos Sofas",$AJ$596,IF(F97="Lauco Sofas",$AJ$597,IF(F97="CR Global - Mesas Ajustables",$AJ$598,IF(F97="Vandesk",$AJ$599,IF(F97="Mamparas Tela",$AJ$600,IF(F97="Mampara Cristales",$AJ$601,IF(F97="Herrajes",$AJ$602,IF(F97="MetalWork",$AJ$603,IF(F97="Requiez",$AJ$604,IF(F97="Labenze",$AJ$605,IF(F97="Infinity",$AJ$606,IF(F97="Proveedor Externo",$AJ$607))))))))))))))))))))))))))))))) -> FALSE | Z97: 0 | AA97: =W97*Z97 -> #N/A | AB97: =IF(Z97>Y97,"ERROR",(W97-AA97)) -> #N/A | AC97: =AB97*H97 -> #N/A | AD97: =IF(A98=TRUE,MAX(0,1-(AE97/W97)),"NA") -> #N/A | AE97: =IF(A96=FALSE,"NO APLICA",AB97*1.2) -> #N/A | AF97: =AE97*H97 -> #N/A | AG97: =(AC97-N97)/AC97 -> #N/A | AH97: =IF(AG97<30%,"ERROR","OK") -> #N/A
A98: =$A$13 -> TRUE | B98: =A98 -> TRUE | C98: =$C$13 -> Dólares | G98: =IFERROR(VLOOKUP(F98,Tabla_Proveedores_1,2,0)," ") | H98: 0 | I98: =IFERROR(VLOOKUP(G98,Proveedores!B:C,2,0)," ") | J98: 0 | L98: =K98*H98 -> 0 | M98: =IF(F98="Offiho", J98*0.55, IF(AND(F98<>"Sunon Inc",F98<>"Alma - Exterior",F98<>"Yabo - Hotelería",F98<>"OSJ - Medical",F98<>"Seezo - Home",F98<>"A&D -Home",F98<>"Encore Alfombras Hoteleria Asia",F98<>"Zhong Xian - Leds",F98<>"Tarkett Europa",F98<>"2tec2",F98<>"Balsan Europa",F98<>"Armstrong Pisos USA",F98<>"Tarkett USA",F98<>"Tarkett Brasil"),J98,IFERROR(IF(K657<=$AO$578,J98*2.14,IF(K657<=$AN$579,J98*1.8,IF(K657>$AN$580,J98*1.5))),J98))*1.1) -> 0 | N98: =M98*H98 -> 0 | O98: =IFERROR(VLOOKUP(G98,Proveedores!B:D,3,0)," ") | Q98: =VLOOKUP(E98,Tabla_Fletes,3,FALSE) -> #N/A | R98: =IF(P98="Centro",Q98,IF(P98="Norte",Q98*1.6,IF(P98="Occidente",Q98*1.2,IF(P98="Sur",Q98*2)))) -> FALSE | S98: =VLOOKUP(E98,Tabla_Instalacion,2,FALSE) -> #N/A | T98: =IF(P98="Centro",S98,IF(P98="Norte",S98*1.1,IF(P98="Occidente",S98*1.1,IF(P98="Sur",S98*1.1)))) -> FALSE | U98: =IF(F98="Offiho",0,Q98+S98) -> #N/A | V98: =IF(K98=0,U98/$H$573,U98*(K98/L98))*H98 -> #N/A | W98: =IF(F98="Offiho",J98,IF(_xlfn.XLOOKUP(F98,Proveedores!A$2:A$50,Proveedores!E$2:E$50,"")="Nacional",(J98/0.5)+(V98*H98),((J98/0.3/0.5)+(V98*H98)))) -> #N/A | X98: =W98*H98 -> #N/A | Y98: =IF(F98="Sunon Inc",$AJ$577,IF(F98="Alma - Exterior",$AJ$578,IF(F98="Yabo - Hotelería",$AJ$579,IF(F98="OSJ - Medical",$AJ$580,IF(F98="Seezo - Home",$AJ$581,IF(F98="A&D - Home",$AJ$582,IF(F98="Encore Alfombras Hoteleria Asia",$AJ$583,IF(F98="Zhong Xian - Leds",$AJ$584,IF(F98="Tarkett Europa",$AJ$585,IF(F98="2tec2",$AJ$586,IF(F98="Balsan Europa",$AJ$587,IF(F98="Armstrong Pisos USA",$AJ$588,IF(F98="Tarkett USA",$AJ$589,IF(F98="Tarkett Brasil",$AJ$590,IF(F98="Tarkett MX",$AJ$591,IF(F98="Jome",$AJ$592,IF(F98="Offiho",$AJ$593,IF(F98="Lumbro",$AJ$594,IF(F98="Sunon Mty",$AJ$595,IF(F98="Conceptos Sofas",$AJ$596,IF(F98="Lauco Sofas",$AJ$597,IF(F98="CR Global - Mesas Ajustables",$AJ$598,IF(F98="Vandesk",$AJ$599,IF(F98="Mamparas Tela",$AJ$600,IF(F98="Mampara Cristales",$AJ$601,IF(F98="Herrajes",$AJ$602,IF(F98="MetalWork",$AJ$603,IF(F98="Requiez",$AJ$604,IF(F98="Labenze",$AJ$605,IF(F98="Infinity",$AJ$606,IF(F98="Proveedor Externo",$AJ$607))))))))))))))))))))))))))))))) -> FALSE | Z98: 0 | AA98: =W98*Z98 -> #N/A | AB98: =IF(Z98>Y98,"ERROR",(W98-AA98)) -> #N/A | AC98: =AB98*H98 -> #N/A | AD98: =IF(A99=TRUE,MAX(0,1-(AE98/W98)),"NA") -> #N/A | AE98: =IF(A97=FALSE,"NO APLICA",AB98*1.2) -> #N/A | AF98: =AE98*H98 -> #N/A | AG98: =(AC98-N98)/AC98 -> #N/A | AH98: =IF(AG98<30%,"ERROR","OK") -> #N/A
... A116: =$A$13 -> TRUE | B116: =A116 -> TRUE | C116: =$C$13 -> Dólares | G116: =IFERROR(VLOOKUP(F116,Tabla_Proveedores_1,2,0)," ") | H116: 0 | I116: =IFERROR(VLOOKUP(G116,Proveedores!B:C,2,0)," ") | J116: 0 | L116: =K116*H116 -> 0 | M116: =IF(F116="Offiho", J116*0.55, IF(AND(F116<>"Sunon Inc",F116<>"Alma - Exterior",F116<>"Yabo - Hotelería",F116<>"OSJ - Medical",F116<>"Seezo - Home",F116<>"A&D -Home",F116<>"Encore Alfombras Hoteleria Asia",F116<>"Zhong Xian - Leds",F116<>"Tarkett Europa",F116<>"2tec2",F116<>"Balsan Europa",F116<>"Armstrong Pisos USA",F116<>"Tarkett USA",F116<>"Tarkett Brasil"),J116,IFERROR(IF(K675<=$AO$578,J116*2.14,IF(K675<=$AN$579,J116*1.8,IF(K675>$AN$580,J116*1.5))),J116))*1.1) -> 0 | N116: =M116*H116 -> 0 | O116: =IFERROR(VLOOKUP(G116,Proveedores!B:D,3,0)," ") | Q116: =VLOOKUP(E116,Tabla_Fletes,3,FALSE) -> #N/A | R116: =IF(P116="Centro",Q116,IF(P116="Norte",Q116*1.6,IF(P116="Occidente",Q116*1.2,IF(P116="Sur",Q116*2)))) -> FALSE | S116: =VLOOKUP(E116,Tabla_Instalacion,2,FALSE) -> #N/A | T116: =IF(P116="Centro",S116,IF(P116="Norte",S116*1.1,IF(P116="Occidente",S116*1.1,IF(P116="Sur",S116*1.1)))) -> FALSE | U116: =IF(F116="Offiho",0,Q116+S116) -> #N/A | V116: =IF(K116=0,U116/$H$573,U116*(K116/L116))*H116 -> #N/A | W116: =IF(F116="Offiho",J116,IF(_xlfn.XLOOKUP(F116,Proveedores!A$2:A$50,Proveedores!E$2:E$50,"")="Nacional",(J116/0.5)+(V116*H116),((J116/0.3/0.5)+(V116*H116)))) -> #N/A | X116: =W116*H116 -> #N/A | Y116: =IF(F116="Sunon Inc",$AJ$577,IF(F116="Alma - Exterior",$AJ$578,IF(F116="Yabo - Hotelería",$AJ$579,IF(F116="OSJ - Medical",$AJ$580,IF(F116="Seezo - Home",$AJ$581,IF(F116="A&D - Home",$AJ$582,IF(F116="Encore Alfombras Hoteleria Asia",$AJ$583,IF(F116="Zhong Xian - Leds",$AJ$584,IF(F116="Tarkett Europa",$AJ$585,IF(F116="2tec2",$AJ$586,IF(F116="Balsan Europa",$AJ$587,IF(F116="Armstrong Pisos USA",$AJ$588,IF(F116="Tarkett USA",$AJ$589,IF(F116="Tarkett Brasil",$AJ$590,IF(F116="Tarkett MX",$AJ$591,IF(F116="Jome",$AJ$592,IF(F116="Offiho",$AJ$593,IF(F116="Lumbro",$AJ$594,IF(F116="Sunon Mty",$AJ$595,IF(F116="Conceptos Sofas",$AJ$596,IF(F116="Lauco Sofas",$AJ$597,IF(F116="CR Global - Mesas Ajustables",$AJ$598,IF(F116="Vandesk",$AJ$599,IF(F116="Mamparas Tela",$AJ$600,IF(F116="Mampara Cristales",$AJ$601,IF(F116="Herrajes",$AJ$602,IF(F116="MetalWork",$AJ$603,IF(F116="Requiez",$AJ$604,IF(F116="Labenze",$AJ$605,IF(F116="Infinity",$AJ$606,IF(F116="Proveedor Externo",$AJ$607))))))))))))))))))))))))))))))) -> FALSE | Z116: 0 | AA116: =W116*Z116 -> #N/A | AB116: =IF(Z116>Y116,"ERROR",(W116-AA116)) -> #N/A | AC116: =AB116*H116 -> #N/A | AD116: =IF(A117=TRUE,MAX(0,1-(AE116/W116)),"NA") -> NA | AE116: =IF(A115=FALSE,"NO APLICA",AB116*1.2) -> #N/A | AF116: =AE116*H116 -> #N/A | AG116: =(AC116-N116)/AC116 -> #N/A | AH116: =IF(AG116<30%,"ERROR","OK") -> #N/A
A117: Subtotales Sección 3 | H117: {=SUM(IFERROR(H84:H116,0))} -> 0 | L117: {=SUM(IFERROR(L84:L116,0))} -> 0 | N117: {=SUM(IFERROR(N84:N116,0))} -> 0 | X117: {=SUM(IFERROR(X84:X116,0))} -> 0 | AC117: {=SUM(IFERROR(AC84:AC116,0))} -> 0 | AF117: {=SUM(IFERROR(AF84:AF116,0))} -> 0 | AG117: =IFERROR(1-(N117/AC117),0) -> 0
A118: Sección 4 - NOMBRE
A119: =$A$13 -> TRUE | B119: =A119 -> TRUE | C119: =$C$13 -> Dólares | G119: =IFERROR(VLOOKUP(F119,Tabla_Proveedores_1,2,0)," ") | H119: 0 | I119: =IFERROR(VLOOKUP(G119,Proveedores!B:C,2,0)," ") | J119: 0 | L119: =K119*H119 -> 0 | M119: =IF(F119="Offiho", J119*0.55, IF(AND(F119<>"Sunon Inc",F119<>"Alma - Exterior",F119<>"Yabo - Hotelería",F119<>"OSJ - Medical",F119<>"Seezo - Home",F119<>"A&D -Home",F119<>"Encore Alfombras Hoteleria Asia",F119<>"Zhong Xian - Leds",F119<>"Tarkett Europa",F119<>"2tec2",F119<>"Balsan Europa",F119<>"Armstrong Pisos USA",F119<>"Tarkett USA",F119<>"Tarkett Brasil"),J119,IFERROR(IF(K678<=$AO$578,J119*2.14,IF(K678<=$AN$579,J119*1.8,IF(K678>$AN$580,J119*1.5))),J119))*1.1) -> 0 | N119: =M119*H119 -> 0 | O119: =IFERROR(VLOOKUP(G119,Proveedores!B:D,3,0)," ") | Q119: =VLOOKUP(E119,Tabla_Fletes,3,FALSE) -> #N/A | R119: =IF(P119="Centro",Q119,IF(P119="Norte",Q119*1.6,IF(P119="Occidente",Q119*1.2,IF(P119="Sur",Q119*2)))) -> FALSE | S119: =VLOOKUP(E119,Tabla_Instalacion,2,FALSE) -> #N/A | T119: =IF(P119="Centro",S119,IF(P119="Norte",S119*1.1,IF(P119="Occidente",S119*1.1,IF(P119="Sur",S119*1.1)))) -> FALSE | U119: =IF(F119="Offiho",0,Q119+S119) -> #N/A | V119: =IF(K119=0,U119/$H$573,U119*(K119/L119))*H119 -> #N/A | W119: =IF(F119="Offiho",J119,IF(_xlfn.XLOOKUP(F119,Proveedores!A$2:A$50,Proveedores!E$2:E$50,"")="Nacional",(J119/0.5)+(V119*H119),((J119/0.3/0.5)+(V119*H119)))) -> #N/A | X119: =W119*H119 -> #N/A | Y119: =IF(F119="Sunon Inc",$AJ$577,IF(F119="Alma - Exterior",$AJ$578,IF(F119="Yabo - Hotelería",$AJ$579,IF(F119="OSJ - Medical",$AJ$580,IF(F119="Seezo - Home",$AJ$581,IF(F119="A&D - Home",$AJ$582,IF(F119="Encore Alfombras Hoteleria Asia",$AJ$583,IF(F119="Zhong Xian - Leds",$AJ$584,IF(F119="Tarkett Europa",$AJ$585,IF(F119="2tec2",$AJ$586,IF(F119="Balsan Europa",$AJ$587,IF(F119="Armstrong Pisos USA",$AJ$588,IF(F119="Tarkett USA",$AJ$589,IF(F119="Tarkett Brasil",$AJ$590,IF(F119="Tarkett MX",$AJ$591,IF(F119="Jome",$AJ$592,IF(F119="Offiho",$AJ$593,IF(F119="Lumbro",$AJ$594,IF(F119="Sunon Mty",$AJ$595,IF(F119="Conceptos Sofas",$AJ$596,IF(F119="Lauco Sofas",$AJ$597,IF(F119="CR Global - Mesas Ajustables",$AJ$598,IF(F119="Vandesk",$AJ$599,IF(F119="Mamparas Tela",$AJ$600,IF(F119="Mampara Cristales",$AJ$601,IF(F119="Herrajes",$AJ$602,IF(F119="MetalWork",$AJ$603,IF(F119="Requiez",$AJ$604,IF(F119="Labenze",$AJ$605,IF(F119="Infinity",$AJ$606,IF(F119="Proveedor Externo",$AJ$607))))))))))))))))))))))))))))))) -> FALSE | Z119: 0 | AA119: =W119*Z119 -> #N/A | AB119: =IF(Z119>Y119,"ERROR",(W119-AA119)) -> #N/A | AC119: =AB119*H119 -> #N/A | AD119: =IF(A120=TRUE,MAX(0,1-(AE119/W119)),"NA") -> #N/A | AE119: =IF(A118=FALSE,"NO APLICA",AB119*1.2) -> #N/A | AF119: =AE119*H119 -> #N/A | AG119: =(AC119-N119)/AC119 -> #N/A | AH119: =IF(AG119<30%,"ERROR","OK") -> #N/A
A120: =$A$13 -> TRUE | B120: =A120 -> TRUE | C120: =$C$13 -> Dólares | G120: =IFERROR(VLOOKUP(F120,Tabla_Proveedores_1,2,0)," ") | H120: 0 | I120: =IFERROR(VLOOKUP(G120,Proveedores!B:C,2,0)," ") | J120: 0 | L120: =K120*H120 -> 0 | M120: =IF(F120="Offiho", J120*0.55, IF(AND(F120<>"Sunon Inc",F120<>"Alma - Exterior",F120<>"Yabo - Hotelería",F120<>"OSJ - Medical",F120<>"Seezo - Home",F120<>"A&D -Home",F120<>"Encore Alfombras Hoteleria Asia",F120<>"Zhong Xian - Leds",F120<>"Tarkett Europa",F120<>"2tec2",F120<>"Balsan Europa",F120<>"Armstrong Pisos USA",F120<>"Tarkett USA",F120<>"Tarkett Brasil"),J120,IFERROR(IF(K679<=$AO$578,J120*2.14,IF(K679<=$AN$579,J120*1.8,IF(K679>$AN$580,J120*1.5))),J120))*1.1) -> 0 | N120: =M120*H120 -> 0 | O120: =IFERROR(VLOOKUP(G120,Proveedores!B:D,3,0)," ") | Q120: =VLOOKUP(E120,Tabla_Fletes,3,FALSE) -> #N/A | R120: =IF(P120="Centro",Q120,IF(P120="Norte",Q120*1.6,IF(P120="Occidente",Q120*1.2,IF(P120="Sur",Q120*2)))) -> FALSE | S120: =VLOOKUP(E120,Tabla_Instalacion,2,FALSE) -> #N/A | T120: =IF(P120="Centro",S120,IF(P120="Norte",S120*1.1,IF(P120="Occidente",S120*1.1,IF(P120="Sur",S120*1.1)))) -> FALSE | U120: =IF(F120="Offiho",0,Q120+S120) -> #N/A | V120: =IF(K120=0,U120/$H$573,U120*(K120/L120))*H120 -> #N/A | W120: =IF(F120="Offiho",J120,IF(_xlfn.XLOOKUP(F120,Proveedores!A$2:A$50,Proveedores!E$2:E$50,"")="Nacional",(J120/0.5)+(V120*H120),((J120/0.3/0.5)+(V120*H120)))) -> #N/A | X120: =W120*H120 -> #N/A | Y120: =IF(F120="Sunon Inc",$AJ$577,IF(F120="Alma - Exterior",$AJ$578,IF(F120="Yabo - Hotelería",$AJ$579,IF(F120="OSJ - Medical",$AJ$580,IF(F120="Seezo - Home",$AJ$581,IF(F120="A&D - Home",$AJ$582,IF(F120="Encore Alfombras Hoteleria Asia",$AJ$583,IF(F120="Zhong Xian - Leds",$AJ$584,IF(F120="Tarkett Europa",$AJ$585,IF(F120="2tec2",$AJ$586,IF(F120="Balsan Europa",$AJ$587,IF(F120="Armstrong Pisos USA",$AJ$588,IF(F120="Tarkett USA",$AJ$589,IF(F120="Tarkett Brasil",$AJ$590,IF(F120="Tarkett MX",$AJ$591,IF(F120="Jome",$AJ$592,IF(F120="Offiho",$AJ$593,IF(F120="Lumbro",$AJ$594,IF(F120="Sunon Mty",$AJ$595,IF(F120="Conceptos Sofas",$AJ$596,IF(F120="Lauco Sofas",$AJ$597,IF(F120="CR Global - Mesas Ajustables",$AJ$598,IF(F120="Vandesk",$AJ$599,IF(F120="Mamparas Tela",$AJ$600,IF(F120="Mampara Cristales",$AJ$601,IF(F120="Herrajes",$AJ$602,IF(F120="MetalWork",$AJ$603,IF(F120="Requiez",$AJ$604,IF(F120="Labenze",$AJ$605,IF(F120="Infinity",$AJ$606,IF(F120="Proveedor Externo",$AJ$607))))))))))))))))))))))))))))))) -> FALSE | Z120: 0 | AA120: =W120*Z120 -> #N/A | AB120: =IF(Z120>Y120,"ERROR",(W120-AA120)) -> #N/A | AC120: =AB120*H120 -> #N/A | AD120: =IF(A121=TRUE,MAX(0,1-(AE120/W120)),"NA") -> #N/A | AE120: =IF(A119=FALSE,"NO APLICA",AB120*1.2) -> #N/A | AF120: =AE120*H120 -> #N/A | AG120: =(AC120-N120)/AC120 -> #N/A | AH120: =IF(AG120<30%,"ERROR","OK") -> #N/A
A121: =$A$13 -> TRUE | B121: =A121 -> TRUE | C121: =$C$13 -> Dólares | G121: =IFERROR(VLOOKUP(F121,Tabla_Proveedores_1,2,0)," ") | H121: 0 | I121: =IFERROR(VLOOKUP(G121,Proveedores!B:C,2,0)," ") | J121: 0 | L121: =K121*H121 -> 0 | M121: =IF(F121="Offiho", J121*0.55, IF(AND(F121<>"Sunon Inc",F121<>"Alma - Exterior",F121<>"Yabo - Hotelería",F121<>"OSJ - Medical",F121<>"Seezo - Home",F121<>"A&D -Home",F121<>"Encore Alfombras Hoteleria Asia",F121<>"Zhong Xian - Leds",F121<>"Tarkett Europa",F121<>"2tec2",F121<>"Balsan Europa",F121<>"Armstrong Pisos USA",F121<>"Tarkett USA",F121<>"Tarkett Brasil"),J121,IFERROR(IF(K680<=$AO$578,J121*2.14,IF(K680<=$AN$579,J121*1.8,IF(K680>$AN$580,J121*1.5))),J121))*1.1) -> 0 | N121: =(M121*H121) -> 0 | O121: =IFERROR(VLOOKUP(G121,Proveedores!B:D,3,0)," ") | Q121: =VLOOKUP(E121,Tabla_Fletes,3,FALSE) -> #N/A | R121: =IF(P121="Centro",Q121,IF(P121="Norte",Q121*1.6,IF(P121="Occidente",Q121*1.2,IF(P121="Sur",Q121*2)))) -> FALSE | S121: =VLOOKUP(E121,Tabla_Instalacion,2,FALSE) -> #N/A | T121: =IF(P121="Centro",S121,IF(P121="Norte",S121*1.1,IF(P121="Occidente",S121*1.1,IF(P121="Sur",S121*1.1)))) -> FALSE | U121: =IF(F121="Offiho",0,Q121+S121) -> #N/A | V121: =IF(K121=0,U121/$H$573,U121*(K121/L121))*H121 -> #N/A | W121: =IF(F121="Offiho",J121,IF(_xlfn.XLOOKUP(F121,Proveedores!A$2:A$50,Proveedores!E$2:E$50,"")="Nacional",(J121/0.5)+(V121*H121),((J121/0.3/0.5)+(V121*H121)))) -> #N/A | X121: =W121*H121 -> #N/A | Y121: =IF(F121="Sunon Inc",$AJ$577,IF(F121="Alma - Exterior",$AJ$578,IF(F121="Yabo - Hotelería",$AJ$579,IF(F121="OSJ - Medical",$AJ$580,IF(F121="Seezo - Home",$AJ$581,IF(F121="A&D - Home",$AJ$582,IF(F121="Encore Alfombras Hoteleria Asia",$AJ$583,IF(F121="Zhong Xian - Leds",$AJ$584,IF(F121="Tarkett Europa",$AJ$585,IF(F121="2tec2",$AJ$586,IF(F121="Balsan Europa",$AJ$587,IF(F121="Armstrong Pisos USA",$AJ$588,IF(F121="Tarkett USA",$AJ$589,IF(F121="Tarkett Brasil",$AJ$590,IF(F121="Tarkett MX",$AJ$591,IF(F121="Jome",$AJ$592,IF(F121="Offiho",$AJ$593,IF(F121="Lumbro",$AJ$594,IF(F121="Sunon Mty",$AJ$595,IF(F121="Conceptos Sofas",$AJ$596,IF(F121="Lauco Sofas",$AJ$597,IF(F121="CR Global - Mesas Ajustables",$AJ$598,IF(F121="Vandesk",$AJ$599,IF(F121="Mamparas Tela",$AJ$600,IF(F121="Mampara Cristales",$AJ$601,IF(F121="Herrajes",$AJ$602,IF(F121="MetalWork",$AJ$603,IF(F121="Requiez",$AJ$604,IF(F121="Labenze",$AJ$605,IF(F121="Infinity",$AJ$606,IF(F121="Proveedor Externo",$AJ$607))))))))))))))))))))))))))))))) -> FALSE | Z121: 0 | AA121: =W121*Z121 -> #N/A | AB121: =IF(Z121>Y121,"ERROR",(W121-AA121)) -> #N/A | AC121: =AB121*H121 -> #N/A | AD121: =IF(A122=TRUE,MAX(0,1-(AE121/W121)),"NA") -> #N/A | AE121: =IF(A120=FALSE,"NO APLICA",AB121*1.2) -> #N/A | AF121: =AE121*H121 -> #N/A | AG121: =(AC121-N121)/AC121 -> #N/A | AH121: =IF(AG121<30%,"ERROR","OK") -> #N/A
A122: =$A$13 -> TRUE | B122: =A122 -> TRUE | C122: =$C$13 -> Dólares | G122: =IFERROR(VLOOKUP(F122,Tabla_Proveedores_1,2,0)," ") | H122: 0 | I122: =IFERROR(VLOOKUP(G122,Proveedores!B:C,2,0)," ") | J122: 0 | L122: =K122*H122 -> 0 | M122: =IF(F122="Offiho", J122*0.55, IF(AND(F122<>"Sunon Inc",F122<>"Alma - Exterior",F122<>"Yabo - Hotelería",F122<>"OSJ - Medical",F122<>"Seezo - Home",F122<>"A&D -Home",F122<>"Encore Alfombras Hoteleria Asia",F122<>"Zhong Xian - Leds",F122<>"Tarkett Europa",F122<>"2tec2",F122<>"Balsan Europa",F122<>"Armstrong Pisos USA",F122<>"Tarkett USA",F122<>"Tarkett Brasil"),J122,IFERROR(IF(K681<=$AO$578,J122*2.14,IF(K681<=$AN$579,J122*1.8,IF(K681>$AN$580,J122*1.5))),J122))*1.1) -> 0 | N122: =M122*H122 -> 0 | O122: =IFERROR(VLOOKUP(G122,Proveedores!B:D,3,0)," ") | Q122: =VLOOKUP(E122,Tabla_Fletes,3,FALSE) -> #N/A | R122: =IF(P122="Centro",Q122,IF(P122="Norte",Q122*1.6,IF(P122="Occidente",Q122*1.2,IF(P122="Sur",Q122*2)))) -> FALSE | S122: =VLOOKUP(E122,Tabla_Instalacion,2,FALSE) -> #N/A | T122: =IF(P122="Centro",S122,IF(P122="Norte",S122*1.1,IF(P122="Occidente",S122*1.1,IF(P122="Sur",S122*1.1)))) -> FALSE | U122: =IF(F122="Offiho",0,Q122+S122) -> #N/A | V122: =IF(K122=0,U122/$H$573,U122*(K122/L122))*H122 -> #N/A | W122: =IF(F122="Offiho",J122,IF(_xlfn.XLOOKUP(F122,Proveedores!A$2:A$50,Proveedores!E$2:E$50,"")="Nacional",(J122/0.5)+(V122*H122),((J122/0.3/0.5)+(V122*H122)))) -> #N/A | X122: =W122*H122 -> #N/A | Y122: =IF(F122="Sunon Inc",$AJ$577,IF(F122="Alma - Exterior",$AJ$578,IF(F122="Yabo - Hotelería",$AJ$579,IF(F122="OSJ - Medical",$AJ$580,IF(F122="Seezo - Home",$AJ$581,IF(F122="A&D - Home",$AJ$582,IF(F122="Encore Alfombras Hoteleria Asia",$AJ$583,IF(F122="Zhong Xian - Leds",$AJ$584,IF(F122="Tarkett Europa",$AJ$585,IF(F122="2tec2",$AJ$586,IF(F122="Balsan Europa",$AJ$587,IF(F122="Armstrong Pisos USA",$AJ$588,IF(F122="Tarkett USA",$AJ$589,IF(F122="Tarkett Brasil",$AJ$590,IF(F122="Tarkett MX",$AJ$591,IF(F122="Jome",$AJ$592,IF(F122="Offiho",$AJ$593,IF(F122="Lumbro",$AJ$594,IF(F122="Sunon Mty",$AJ$595,IF(F122="Conceptos Sofas",$AJ$596,IF(F122="Lauco Sofas",$AJ$597,IF(F122="CR Global - Mesas Ajustables",$AJ$598,IF(F122="Vandesk",$AJ$599,IF(F122="Mamparas Tela",$AJ$600,IF(F122="Mampara Cristales",$AJ$601,IF(F122="Herrajes",$AJ$602,IF(F122="MetalWork",$AJ$603,IF(F122="Requiez",$AJ$604,IF(F122="Labenze",$AJ$605,IF(F122="Infinity",$AJ$606,IF(F122="Proveedor Externo",$AJ$607))))))))))))))))))))))))))))))) -> FALSE | Z122: 0 | AA122: =W122*Z122 -> #N/A | AB122: =IF(Z122>Y122,"ERROR",(W122-AA122)) -> #N/A | AC122: =AB122*H122 -> #N/A | AD122: =IF(A123=TRUE,MAX(0,1-(AE122/W122)),"NA") -> #N/A | AE122: =IF(A121=FALSE,"NO APLICA",AB122*1.2) -> #N/A | AF122: =AE122*H122 -> #N/A | AG122: =(AC122-N122)/AC122 -> #N/A | AH122: =IF(AG122<30%,"ERROR","OK") -> #N/A
A123: =$A$13 -> TRUE | B123: =A123 -> TRUE | C123: =$C$13 -> Dólares | G123: =IFERROR(VLOOKUP(F123,Tabla_Proveedores_1,2,0)," ") | H123: 0 | I123: =IFERROR(VLOOKUP(G123,Proveedores!B:C,2,0)," ") | J123: 0 | L123: =K123*H123 -> 0 | M123: =IF(F123="Offiho", J123*0.55, IF(AND(F123<>"Sunon Inc",F123<>"Alma - Exterior",F123<>"Yabo - Hotelería",F123<>"OSJ - Medical",F123<>"Seezo - Home",F123<>"A&D -Home",F123<>"Encore Alfombras Hoteleria Asia",F123<>"Zhong Xian - Leds",F123<>"Tarkett Europa",F123<>"2tec2",F123<>"Balsan Europa",F123<>"Armstrong Pisos USA",F123<>"Tarkett USA",F123<>"Tarkett Brasil"),J123,IFERROR(IF(K682<=$AO$578,J123*2.14,IF(K682<=$AN$579,J123*1.8,IF(K682>$AN$580,J123*1.5))),J123))*1.1) -> 0 | N123: =M123*H123 -> 0 | O123: =IFERROR(VLOOKUP(G123,Proveedores!B:D,3,0)," ") | Q123: =VLOOKUP(E123,Tabla_Fletes,3,FALSE) -> #N/A | R123: =IF(P123="Centro",Q123,IF(P123="Norte",Q123*1.6,IF(P123="Occidente",Q123*1.2,IF(P123="Sur",Q123*2)))) -> FALSE | S123: =VLOOKUP(E123,Tabla_Instalacion,2,FALSE) -> #N/A | T123: =IF(P123="Centro",S123,IF(P123="Norte",S123*1.1,IF(P123="Occidente",S123*1.1,IF(P123="Sur",S123*1.1)))) -> FALSE | U123: =IF(F123="Offiho",0,Q123+S123) -> #N/A | V123: =IF(K123=0,U123/$H$573,U123*(K123/L123))*H123 -> #N/A | W123: =IF(F123="Offiho",J123,IF(_xlfn.XLOOKUP(F123,Proveedores!A$2:A$50,Proveedores!E$2:E$50,"")="Nacional",(J123/0.5)+(V123*H123),((J123/0.3/0.5)+(V123*H123)))) -> #N/A | X123: =W123*H123 -> #N/A | Y123: =IF(F123="Sunon Inc",$AJ$577,IF(F123="Alma - Exterior",$AJ$578,IF(F123="Yabo - Hotelería",$AJ$579,IF(F123="OSJ - Medical",$AJ$580,IF(F123="Seezo - Home",$AJ$581,IF(F123="A&D - Home",$AJ$582,IF(F123="Encore Alfombras Hoteleria Asia",$AJ$583,IF(F123="Zhong Xian - Leds",$AJ$584,IF(F123="Tarkett Europa",$AJ$585,IF(F123="2tec2",$AJ$586,IF(F123="Balsan Europa",$AJ$587,IF(F123="Armstrong Pisos USA",$AJ$588,IF(F123="Tarkett USA",$AJ$589,IF(F123="Tarkett Brasil",$AJ$590,IF(F123="Tarkett MX",$AJ$591,IF(F123="Jome",$AJ$592,IF(F123="Offiho",$AJ$593,IF(F123="Lumbro",$AJ$594,IF(F123="Sunon Mty",$AJ$595,IF(F123="Conceptos Sofas",$AJ$596,IF(F123="Lauco Sofas",$AJ$597,IF(F123="CR Global - Mesas Ajustables",$AJ$598,IF(F123="Vandesk",$AJ$599,IF(F123="Mamparas Tela",$AJ$600,IF(F123="Mampara Cristales",$AJ$601,IF(F123="Herrajes",$AJ$602,IF(F123="MetalWork",$AJ$603,IF(F123="Requiez",$AJ$604,IF(F123="Labenze",$AJ$605,IF(F123="Infinity",$AJ$606,IF(F123="Proveedor Externo",$AJ$607))))))))))))))))))))))))))))))) -> FALSE | Z123: 0 | AA123: =W123*Z123 -> #N/A | AB123: =IF(Z123>Y123,"ERROR",(W123-AA123)) -> #N/A | AC123: =AB123*H123 -> #N/A | AD123: =IF(A124=TRUE,MAX(0,1-(AE123/W123)),"NA") -> #N/A | AE123: =IF(A122=FALSE,"NO APLICA",AB123*1.2) -> #N/A | AF123: =AE123*H123 -> #N/A | AG123: =(AC123-N123)/AC123 -> #N/A | AH123: =IF(AG123<30%,"ERROR","OK") -> #N/A
A124: =$A$13 -> TRUE | B124: =A124 -> TRUE | C124: =$C$13 -> Dólares | G124: =IFERROR(VLOOKUP(F124,Tabla_Proveedores_1,2,0)," ") | H124: 0 | I124: =IFERROR(VLOOKUP(G124,Proveedores!B:C,2,0)," ") | J124: 0 | L124: =K124*H124 -> 0 | M124: =IF(F124="Offiho", J124*0.55, IF(AND(F124<>"Sunon Inc",F124<>"Alma - Exterior",F124<>"Yabo - Hotelería",F124<>"OSJ - Medical",F124<>"Seezo - Home",F124<>"A&D -Home",F124<>"Encore Alfombras Hoteleria Asia",F124<>"Zhong Xian - Leds",F124<>"Tarkett Europa",F124<>"2tec2",F124<>"Balsan Europa",F124<>"Armstrong Pisos USA",F124<>"Tarkett USA",F124<>"Tarkett Brasil"),J124,IFERROR(IF(K683<=$AO$578,J124*2.14,IF(K683<=$AN$579,J124*1.8,IF(K683>$AN$580,J124*1.5))),J124))*1.1) -> 0 | N124: =M124*H124 -> 0 | O124: =IFERROR(VLOOKUP(G124,Proveedores!B:D,3,0)," ") | Q124: =VLOOKUP(E124,Tabla_Fletes,3,FALSE) -> #N/A | R124: =IF(P124="Centro",Q124,IF(P124="Norte",Q124*1.6,IF(P124="Occidente",Q124*1.2,IF(P124="Sur",Q124*2)))) -> FALSE | S124: =VLOOKUP(E124,Tabla_Instalacion,2,FALSE) -> #N/A | T124: =IF(P124="Centro",S124,IF(P124="Norte",S124*1.1,IF(P124="Occidente",S124*1.1,IF(P124="Sur",S124*1.1)))) -> FALSE | U124: =IF(F124="Offiho",0,Q124+S124) -> #N/A | V124: =IF(K124=0,U124/$H$573,U124*(K124/L124))*H124 -> #N/A | W124: =IF(F124="Offiho",J124,IF(_xlfn.XLOOKUP(F124,Proveedores!A$2:A$50,Proveedores!E$2:E$50,"")="Nacional",(J124/0.5)+(V124*H124),((J124/0.3/0.5)+(V124*H124)))) -> #N/A | X124: =W124*H124 -> #N/A | Y124: =IF(F124="Sunon Inc",$AJ$577,IF(F124="Alma - Exterior",$AJ$578,IF(F124="Yabo - Hotelería",$AJ$579,IF(F124="OSJ - Medical",$AJ$580,IF(F124="Seezo - Home",$AJ$581,IF(F124="A&D - Home",$AJ$582,IF(F124="Encore Alfombras Hoteleria Asia",$AJ$583,IF(F124="Zhong Xian - Leds",$AJ$584,IF(F124="Tarkett Europa",$AJ$585,IF(F124="2tec2",$AJ$586,IF(F124="Balsan Europa",$AJ$587,IF(F124="Armstrong Pisos USA",$AJ$588,IF(F124="Tarkett USA",$AJ$589,IF(F124="Tarkett Brasil",$AJ$590,IF(F124="Tarkett MX",$AJ$591,IF(F124="Jome",$AJ$592,IF(F124="Offiho",$AJ$593,IF(F124="Lumbro",$AJ$594,IF(F124="Sunon Mty",$AJ$595,IF(F124="Conceptos Sofas",$AJ$596,IF(F124="Lauco Sofas",$AJ$597,IF(F124="CR Global - Mesas Ajustables",$AJ$598,IF(F124="Vandesk",$AJ$599,IF(F124="Mamparas Tela",$AJ$600,IF(F124="Mampara Cristales",$AJ$601,IF(F124="Herrajes",$AJ$602,IF(F124="MetalWork",$AJ$603,IF(F124="Requiez",$AJ$604,IF(F124="Labenze",$AJ$605,IF(F124="Infinity",$AJ$606,IF(F124="Proveedor Externo",$AJ$607))))))))))))))))))))))))))))))) -> FALSE | Z124: 0 | AA124: =W124*Z124 -> #N/A | AB124: =IF(Z124>Y124,"ERROR",(W124-AA124)) -> #N/A | AC124: =AB124*H124 -> #N/A | AD124: =IF(A125=TRUE,MAX(0,1-(AE124/W124)),"NA") -> #N/A | AE124: =IF(A123=FALSE,"NO APLICA",AB124*1.2) -> #N/A | AF124: =AE124*H124 -> #N/A | AG124: =(AC124-N124)/AC124 -> #N/A | AH124: =IF(AG124<30%,"ERROR","OK") -> #N/A
A125: =$A$13 -> TRUE | B125: =A125 -> TRUE | C125: =$C$13 -> Dólares | G125: =IFERROR(VLOOKUP(F125,Tabla_Proveedores_1,2,0)," ") | H125: 0 | I125: =IFERROR(VLOOKUP(G125,Proveedores!B:C,2,0)," ") | J125: 0 | L125: =K125*H125 -> 0 | M125: =IF(F125="Offiho", J125*0.55, IF(AND(F125<>"Sunon Inc",F125<>"Alma - Exterior",F125<>"Yabo - Hotelería",F125<>"OSJ - Medical",F125<>"Seezo - Home",F125<>"A&D -Home",F125<>"Encore Alfombras Hoteleria Asia",F125<>"Zhong Xian - Leds",F125<>"Tarkett Europa",F125<>"2tec2",F125<>"Balsan Europa",F125<>"Armstrong Pisos USA",F125<>"Tarkett USA",F125<>"Tarkett Brasil"),J125,IFERROR(IF(K684<=$AO$578,J125*2.14,IF(K684<=$AN$579,J125*1.8,IF(K684>$AN$580,J125*1.5))),J125))*1.1) -> 0 | N125: =M125*H125 -> 0 | O125: =IFERROR(VLOOKUP(G125,Proveedores!B:D,3,0)," ") | Q125: =VLOOKUP(E125,Tabla_Fletes,3,FALSE) -> #N/A | R125: =IF(P125="Centro",Q125,IF(P125="Norte",Q125*1.6,IF(P125="Occidente",Q125*1.2,IF(P125="Sur",Q125*2)))) -> FALSE | S125: =VLOOKUP(E125,Tabla_Instalacion,2,FALSE) -> #N/A | T125: =IF(P125="Centro",S125,IF(P125="Norte",S125*1.1,IF(P125="Occidente",S125*1.1,IF(P125="Sur",S125*1.1)))) -> FALSE | U125: =IF(F125="Offiho",0,Q125+S125) -> #N/A | V125: =IF(K125=0,U125/$H$573,U125*(K125/L125))*H125 -> #N/A | W125: =IF(F125="Offiho",J125,IF(_xlfn.XLOOKUP(F125,Proveedores!A$2:A$50,Proveedores!E$2:E$50,"")="Nacional",(J125/0.5)+(V125*H125),((J125/0.3/0.5)+(V125*H125)))) -> #N/A | X125: =W125*H125 -> #N/A | Y125: =IF(F125="Sunon Inc",$AJ$577,IF(F125="Alma - Exterior",$AJ$578,IF(F125="Yabo - Hotelería",$AJ$579,IF(F125="OSJ - Medical",$AJ$580,IF(F125="Seezo - Home",$AJ$581,IF(F125="A&D - Home",$AJ$582,IF(F125="Encore Alfombras Hoteleria Asia",$AJ$583,IF(F125="Zhong Xian - Leds",$AJ$584,IF(F125="Tarkett Europa",$AJ$585,IF(F125="2tec2",$AJ$586,IF(F125="Balsan Europa",$AJ$587,IF(F125="Armstrong Pisos USA",$AJ$588,IF(F125="Tarkett USA",$AJ$589,IF(F125="Tarkett Brasil",$AJ$590,IF(F125="Tarkett MX",$AJ$591,IF(F125="Jome",$AJ$592,IF(F125="Offiho",$AJ$593,IF(F125="Lumbro",$AJ$594,IF(F125="Sunon Mty",$AJ$595,IF(F125="Conceptos Sofas",$AJ$596,IF(F125="Lauco Sofas",$AJ$597,IF(F125="CR Global - Mesas Ajustables",$AJ$598,IF(F125="Vandesk",$AJ$599,IF(F125="Mamparas Tela",$AJ$600,IF(F125="Mampara Cristales",$AJ$601,IF(F125="Herrajes",$AJ$602,IF(F125="MetalWork",$AJ$603,IF(F125="Requiez",$AJ$604,IF(F125="Labenze",$AJ$605,IF(F125="Infinity",$AJ$606,IF(F125="Proveedor Externo",$AJ$607))))))))))))))))))))))))))))))) -> FALSE | Z125: 0 | AA125: =W125*Z125 -> #N/A | AB125: =IF(Z125>Y125,"ERROR",(W125-AA125)) -> #N/A | AC125: =AB125*H125 -> #N/A | AD125: =IF(A126=TRUE,MAX(0,1-(AE125/W125)),"NA") -> #N/A | AE125: =IF(A124=FALSE,"NO APLICA",AB125*1.2) -> #N/A | AF125: =AE125*H125 -> #N/A | AG125: =(AC125-N125)/AC125 -> #N/A | AH125: =IF(AG125<30%,"ERROR","OK") -> #N/A
A126: =$A$13 -> TRUE | B126: =A126 -> TRUE | C126: =$C$13 -> Dólares | G126: =IFERROR(VLOOKUP(F126,Tabla_Proveedores_1,2,0)," ") | H126: 0 | I126: =IFERROR(VLOOKUP(G126,Proveedores!B:C,2,0)," ") | J126: 0 | L126: =K126*H126 -> 0 | M126: =IF(F126="Offiho", J126*0.55, IF(AND(F126<>"Sunon Inc",F126<>"Alma - Exterior",F126<>"Yabo - Hotelería",F126<>"OSJ - Medical",F126<>"Seezo - Home",F126<>"A&D -Home",F126<>"Encore Alfombras Hoteleria Asia",F126<>"Zhong Xian - Leds",F126<>"Tarkett Europa",F126<>"2tec2",F126<>"Balsan Europa",F126<>"Armstrong Pisos USA",F126<>"Tarkett USA",F126<>"Tarkett Brasil"),J126,IFERROR(IF(K685<=$AO$578,J126*2.14,IF(K685<=$AN$579,J126*1.8,IF(K685>$AN$580,J126*1.5))),J126))*1.1) -> 0 | N126: =M126*H126 -> 0 | O126: =IFERROR(VLOOKUP(G126,Proveedores!B:D,3,0)," ") | Q126: =VLOOKUP(E126,Tabla_Fletes,3,FALSE) -> #N/A | R126: =IF(P126="Centro",Q126,IF(P126="Norte",Q126*1.6,IF(P126="Occidente",Q126*1.2,IF(P126="Sur",Q126*2)))) -> FALSE | S126: =VLOOKUP(E126,Tabla_Instalacion,2,FALSE) -> #N/A | T126: =IF(P126="Centro",S126,IF(P126="Norte",S126*1.1,IF(P126="Occidente",S126*1.1,IF(P126="Sur",S126*1.1)))) -> FALSE | U126: =IF(F126="Offiho",0,Q126+S126) -> #N/A | V126: =IF(K126=0,U126/$H$573,U126*(K126/L126))*H126 -> #N/A | W126: =IF(F126="Offiho",J126,IF(_xlfn.XLOOKUP(F126,Proveedores!A$2:A$50,Proveedores!E$2:E$50,"")="Nacional",(J126/0.5)+(V126*H126),((J126/0.3/0.5)+(V126*H126)))) -> #N/A | X126: =W126*H126 -> #N/A | Y126: =IF(F126="Sunon Inc",$AJ$577,IF(F126="Alma - Exterior",$AJ$578,IF(F126="Yabo - Hotelería",$AJ$579,IF(F126="OSJ - Medical",$AJ$580,IF(F126="Seezo - Home",$AJ$581,IF(F126="A&D - Home",$AJ$582,IF(F126="Encore Alfombras Hoteleria Asia",$AJ$583,IF(F126="Zhong Xian - Leds",$AJ$584,IF(F126="Tarkett Europa",$AJ$585,IF(F126="2tec2",$AJ$586,IF(F126="Balsan Europa",$AJ$587,IF(F126="Armstrong Pisos USA",$AJ$588,IF(F126="Tarkett USA",$AJ$589,IF(F126="Tarkett Brasil",$AJ$590,IF(F126="Tarkett MX",$AJ$591,IF(F126="Jome",$AJ$592,IF(F126="Offiho",$AJ$593,IF(F126="Lumbro",$AJ$594,IF(F126="Sunon Mty",$AJ$595,IF(F126="Conceptos Sofas",$AJ$596,IF(F126="Lauco Sofas",$AJ$597,IF(F126="CR Global - Mesas Ajustables",$AJ$598,IF(F126="Vandesk",$AJ$599,IF(F126="Mamparas Tela",$AJ$600,IF(F126="Mampara Cristales",$AJ$601,IF(F126="Herrajes",$AJ$602,IF(F126="MetalWork",$AJ$603,IF(F126="Requiez",$AJ$604,IF(F126="Labenze",$AJ$605,IF(F126="Infinity",$AJ$606,IF(F126="Proveedor Externo",$AJ$607))))))))))))))))))))))))))))))) -> FALSE | Z126: 0 | AA126: =W126*Z126 -> #N/A | AB126: =IF(Z126>Y126,"ERROR",(W126-AA126)) -> #N/A | AC126: =AB126*H126 -> #N/A | AD126: =IF(A127=TRUE,MAX(0,1-(AE126/W126)),"NA") -> #N/A | AE126: =IF(A125=FALSE,"NO APLICA",AB126*1.2) -> #N/A | AF126: =AE126*H126 -> #N/A | AG126: =(AC126-N126)/AC126 -> #N/A | AH126: =IF(AG126<30%,"ERROR","OK") -> #N/A
A127: =$A$13 -> TRUE | B127: =A127 -> TRUE | C127: =$C$13 -> Dólares | G127: =IFERROR(VLOOKUP(F127,Tabla_Proveedores_1,2,0)," ") | H127: 0 | I127: =IFERROR(VLOOKUP(G127,Proveedores!B:C,2,0)," ") | J127: 0 | L127: =K127*H127 -> 0 | M127: =IF(F127="Offiho", J127*0.55, IF(AND(F127<>"Sunon Inc",F127<>"Alma - Exterior",F127<>"Yabo - Hotelería",F127<>"OSJ - Medical",F127<>"Seezo - Home",F127<>"A&D -Home",F127<>"Encore Alfombras Hoteleria Asia",F127<>"Zhong Xian - Leds",F127<>"Tarkett Europa",F127<>"2tec2",F127<>"Balsan Europa",F127<>"Armstrong Pisos USA",F127<>"Tarkett USA",F127<>"Tarkett Brasil"),J127,IFERROR(IF(K686<=$AO$578,J127*2.14,IF(K686<=$AN$579,J127*1.8,IF(K686>$AN$580,J127*1.5))),J127))*1.1) -> 0 | N127: =M127*H127 -> 0 | O127: =IFERROR(VLOOKUP(G127,Proveedores!B:D,3,0)," ") | Q127: =VLOOKUP(E127,Tabla_Fletes,3,FALSE) -> #N/A | R127: =IF(P127="Centro",Q127,IF(P127="Norte",Q127*1.6,IF(P127="Occidente",Q127*1.2,IF(P127="Sur",Q127*2)))) -> FALSE | S127: =VLOOKUP(E127,Tabla_Instalacion,2,FALSE) -> #N/A | T127: =IF(P127="Centro",S127,IF(P127="Norte",S127*1.1,IF(P127="Occidente",S127*1.1,IF(P127="Sur",S127*1.1)))) -> FALSE | U127: =IF(F127="Offiho",0,Q127+S127) -> #N/A | V127: =IF(K127=0,U127/$H$573,U127*(K127/L127))*H127 -> #N/A | W127: =IF(F127="Offiho",J127,IF(_xlfn.XLOOKUP(F127,Proveedores!A$2:A$50,Proveedores!E$2:E$50,"")="Nacional",(J127/0.5)+(V127*H127),((J127/0.3/0.5)+(V127*H127)))) -> #N/A | X127: =W127*H127 -> #N/A | Y127: =IF(F127="Sunon Inc",$AJ$577,IF(F127="Alma - Exterior",$AJ$578,IF(F127="Yabo - Hotelería",$AJ$579,IF(F127="OSJ - Medical",$AJ$580,IF(F127="Seezo - Home",$AJ$581,IF(F127="A&D - Home",$AJ$582,IF(F127="Encore Alfombras Hoteleria Asia",$AJ$583,IF(F127="Zhong Xian - Leds",$AJ$584,IF(F127="Tarkett Europa",$AJ$585,IF(F127="2tec2",$AJ$586,IF(F127="Balsan Europa",$AJ$587,IF(F127="Armstrong Pisos USA",$AJ$588,IF(F127="Tarkett USA",$AJ$589,IF(F127="Tarkett Brasil",$AJ$590,IF(F127="Tarkett MX",$AJ$591,IF(F127="Jome",$AJ$592,IF(F127="Offiho",$AJ$593,IF(F127="Lumbro",$AJ$594,IF(F127="Sunon Mty",$AJ$595,IF(F127="Conceptos Sofas",$AJ$596,IF(F127="Lauco Sofas",$AJ$597,IF(F127="CR Global - Mesas Ajustables",$AJ$598,IF(F127="Vandesk",$AJ$599,IF(F127="Mamparas Tela",$AJ$600,IF(F127="Mampara Cristales",$AJ$601,IF(F127="Herrajes",$AJ$602,IF(F127="MetalWork",$AJ$603,IF(F127="Requiez",$AJ$604,IF(F127="Labenze",$AJ$605,IF(F127="Infinity",$AJ$606,IF(F127="Proveedor Externo",$AJ$607))))))))))))))))))))))))))))))) -> FALSE | Z127: 0 | AA127: =W127*Z127 -> #N/A | AB127: =IF(Z127>Y127,"ERROR",(W127-AA127)) -> #N/A | AC127: =AB127*H127 -> #N/A | AD127: =IF(A128=TRUE,MAX(0,1-(AE127/W127)),"NA") -> #N/A | AE127: =IF(A126=FALSE,"NO APLICA",AB127*1.2) -> #N/A | AF127: =AE127*H127 -> #N/A | AG127: =(AC127-N127)/AC127 -> #N/A | AH127: =IF(AG127<30%,"ERROR","OK") -> #N/A
A128: =$A$13 -> TRUE | B128: =A128 -> TRUE | C128: =$C$13 -> Dólares | G128: =IFERROR(VLOOKUP(F128,Tabla_Proveedores_1,2,0)," ") | H128: 0 | I128: =IFERROR(VLOOKUP(G128,Proveedores!B:C,2,0)," ") | J128: 0 | L128: =K128*H128 -> 0 | M128: =IF(F128="Offiho", J128*0.55, IF(AND(F128<>"Sunon Inc",F128<>"Alma - Exterior",F128<>"Yabo - Hotelería",F128<>"OSJ - Medical",F128<>"Seezo - Home",F128<>"A&D -Home",F128<>"Encore Alfombras Hoteleria Asia",F128<>"Zhong Xian - Leds",F128<>"Tarkett Europa",F128<>"2tec2",F128<>"Balsan Europa",F128<>"Armstrong Pisos USA",F128<>"Tarkett USA",F128<>"Tarkett Brasil"),J128,IFERROR(IF(K687<=$AO$578,J128*2.14,IF(K687<=$AN$579,J128*1.8,IF(K687>$AN$580,J128*1.5))),J128))*1.1) -> 0 | N128: =M128*H128 -> 0 | O128: =IFERROR(VLOOKUP(G128,Proveedores!B:D,3,0)," ") | Q128: =VLOOKUP(E128,Tabla_Fletes,3,FALSE) -> #N/A | R128: =IF(P128="Centro",Q128,IF(P128="Norte",Q128*1.6,IF(P128="Occidente",Q128*1.2,IF(P128="Sur",Q128*2)))) -> FALSE | S128: =VLOOKUP(E128,Tabla_Instalacion,2,FALSE) -> #N/A | T128: =IF(P128="Centro",S128,IF(P128="Norte",S128*1.1,IF(P128="Occidente",S128*1.1,IF(P128="Sur",S128*1.1)))) -> FALSE | U128: =IF(F128="Offiho",0,Q128+S128) -> #N/A | V128: =IF(K128=0,U128/$H$573,U128*(K128/L128))*H128 -> #N/A | W128: =IF(F128="Offiho",J128,IF(_xlfn.XLOOKUP(F128,Proveedores!A$2:A$50,Proveedores!E$2:E$50,"")="Nacional",(J128/0.5)+(V128*H128),((J128/0.3/0.5)+(V128*H128)))) -> #N/A | X128: =W128*H128 -> #N/A | Y128: =IF(F128="Sunon Inc",$AJ$577,IF(F128="Alma - Exterior",$AJ$578,IF(F128="Yabo - Hotelería",$AJ$579,IF(F128="OSJ - Medical",$AJ$580,IF(F128="Seezo - Home",$AJ$581,IF(F128="A&D - Home",$AJ$582,IF(F128="Encore Alfombras Hoteleria Asia",$AJ$583,IF(F128="Zhong Xian - Leds",$AJ$584,IF(F128="Tarkett Europa",$AJ$585,IF(F128="2tec2",$AJ$586,IF(F128="Balsan Europa",$AJ$587,IF(F128="Armstrong Pisos USA",$AJ$588,IF(F128="Tarkett USA",$AJ$589,IF(F128="Tarkett Brasil",$AJ$590,IF(F128="Tarkett MX",$AJ$591,IF(F128="Jome",$AJ$592,IF(F128="Offiho",$AJ$593,IF(F128="Lumbro",$AJ$594,IF(F128="Sunon Mty",$AJ$595,IF(F128="Conceptos Sofas",$AJ$596,IF(F128="Lauco Sofas",$AJ$597,IF(F128="CR Global - Mesas Ajustables",$AJ$598,IF(F128="Vandesk",$AJ$599,IF(F128="Mamparas Tela",$AJ$600,IF(F128="Mampara Cristales",$AJ$601,IF(F128="Herrajes",$AJ$602,IF(F128="MetalWork",$AJ$603,IF(F128="Requiez",$AJ$604,IF(F128="Labenze",$AJ$605,IF(F128="Infinity",$AJ$606,IF(F128="Proveedor Externo",$AJ$607))))))))))))))))))))))))))))))) -> FALSE | Z128: 0 | AA128: =W128*Z128 -> #N/A | AB128: =IF(Z128>Y128,"ERROR",(W128-AA128)) -> #N/A | AC128: =AB128*H128 -> #N/A | AD128: =IF(A129=TRUE,MAX(0,1-(AE128/W128)),"NA") -> #N/A | AE128: =IF(A127=FALSE,"NO APLICA",AB128*1.2) -> #N/A | AF128: =AE128*H128 -> #N/A | AG128: =(AC128-N128)/AC128 -> #N/A | AH128: =IF(AG128<30%,"ERROR","OK") -> #N/A
A129: =$A$13 -> TRUE | B129: =A129 -> TRUE | C129: =$C$13 -> Dólares | G129: =IFERROR(VLOOKUP(F129,Tabla_Proveedores_1,2,0)," ") | H129: 0 | I129: =IFERROR(VLOOKUP(G129,Proveedores!B:C,2,0)," ") | J129: 0 | L129: =K129*H129 -> 0 | M129: =IF(F129="Offiho", J129*0.55, IF(AND(F129<>"Sunon Inc",F129<>"Alma - Exterior",F129<>"Yabo - Hotelería",F129<>"OSJ - Medical",F129<>"Seezo - Home",F129<>"A&D -Home",F129<>"Encore Alfombras Hoteleria Asia",F129<>"Zhong Xian - Leds",F129<>"Tarkett Europa",F129<>"2tec2",F129<>"Balsan Europa",F129<>"Armstrong Pisos USA",F129<>"Tarkett USA",F129<>"Tarkett Brasil"),J129,IFERROR(IF(K688<=$AO$578,J129*2.14,IF(K688<=$AN$579,J129*1.8,IF(K688>$AN$580,J129*1.5))),J129))*1.1) -> 0 | N129: =M129*H129 -> 0 | O129: =IFERROR(VLOOKUP(G129,Proveedores!B:D,3,0)," ") | Q129: =VLOOKUP(E129,Tabla_Fletes,3,FALSE) -> #N/A | R129: =IF(P129="Centro",Q129,IF(P129="Norte",Q129*1.6,IF(P129="Occidente",Q129*1.2,IF(P129="Sur",Q129*2)))) -> FALSE | S129: =VLOOKUP(E129,Tabla_Instalacion,2,FALSE) -> #N/A | T129: =IF(P129="Centro",S129,IF(P129="Norte",S129*1.1,IF(P129="Occidente",S129*1.1,IF(P129="Sur",S129*1.1)))) -> FALSE | U129: =IF(F129="Offiho",0,Q129+S129) -> #N/A | V129: =IF(K129=0,U129/$H$573,U129*(K129/L129))*H129 -> #N/A | W129: =IF(F129="Offiho",J129,IF(_xlfn.XLOOKUP(F129,Proveedores!A$2:A$50,Proveedores!E$2:E$50,"")="Nacional",(J129/0.5)+(V129*H129),((J129/0.3/0.5)+(V129*H129)))) -> #N/A | X129: =W129*H129 -> #N/A | Y129: =IF(F129="Sunon Inc",$AJ$577,IF(F129="Alma - Exterior",$AJ$578,IF(F129="Yabo - Hotelería",$AJ$579,IF(F129="OSJ - Medical",$AJ$580,IF(F129="Seezo - Home",$AJ$581,IF(F129="A&D - Home",$AJ$582,IF(F129="Encore Alfombras Hoteleria Asia",$AJ$583,IF(F129="Zhong Xian - Leds",$AJ$584,IF(F129="Tarkett Europa",$AJ$585,IF(F129="2tec2",$AJ$586,IF(F129="Balsan Europa",$AJ$587,IF(F129="Armstrong Pisos USA",$AJ$588,IF(F129="Tarkett USA",$AJ$589,IF(F129="Tarkett Brasil",$AJ$590,IF(F129="Tarkett MX",$AJ$591,IF(F129="Jome",$AJ$592,IF(F129="Offiho",$AJ$593,IF(F129="Lumbro",$AJ$594,IF(F129="Sunon Mty",$AJ$595,IF(F129="Conceptos Sofas",$AJ$596,IF(F129="Lauco Sofas",$AJ$597,IF(F129="CR Global - Mesas Ajustables",$AJ$598,IF(F129="Vandesk",$AJ$599,IF(F129="Mamparas Tela",$AJ$600,IF(F129="Mampara Cristales",$AJ$601,IF(F129="Herrajes",$AJ$602,IF(F129="MetalWork",$AJ$603,IF(F129="Requiez",$AJ$604,IF(F129="Labenze",$AJ$605,IF(F129="Infinity",$AJ$606,IF(F129="Proveedor Externo",$AJ$607))))))))))))))))))))))))))))))) -> FALSE | Z129: 0 | AA129: =W129*Z129 -> #N/A | AB129: =IF(Z129>Y129,"ERROR",(W129-AA129)) -> #N/A | AC129: =AB129*H129 -> #N/A | AD129: =IF(A130=TRUE,MAX(0,1-(AE129/W129)),"NA") -> #N/A | AE129: =IF(A128=FALSE,"NO APLICA",AB129*1.2) -> #N/A | AF129: =AE129*H129 -> #N/A | AG129: =(AC129-N129)/AC129 -> #N/A | AH129: =IF(AG129<30%,"ERROR","OK") -> #N/A
A130: =$A$13 -> TRUE | B130: =A130 -> TRUE | C130: =$C$13 -> Dólares | G130: =IFERROR(VLOOKUP(F130,Tabla_Proveedores_1,2,0)," ") | H130: 0 | I130: =IFERROR(VLOOKUP(G130,Proveedores!B:C,2,0)," ") | J130: 0 | L130: =K130*H130 -> 0 | M130: =IF(F130="Offiho", J130*0.55, IF(AND(F130<>"Sunon Inc",F130<>"Alma - Exterior",F130<>"Yabo - Hotelería",F130<>"OSJ - Medical",F130<>"Seezo - Home",F130<>"A&D -Home",F130<>"Encore Alfombras Hoteleria Asia",F130<>"Zhong Xian - Leds",F130<>"Tarkett Europa",F130<>"2tec2",F130<>"Balsan Europa",F130<>"Armstrong Pisos USA",F130<>"Tarkett USA",F130<>"Tarkett Brasil"),J130,IFERROR(IF(K689<=$AO$578,J130*2.14,IF(K689<=$AN$579,J130*1.8,IF(K689>$AN$580,J130*1.5))),J130))*1.1) -> 0 | N130: =M130*H130 -> 0 | O130: =IFERROR(VLOOKUP(G130,Proveedores!B:D,3,0)," ") | Q130: =VLOOKUP(E130,Tabla_Fletes,3,FALSE) -> #N/A | R130: =IF(P130="Centro",Q130,IF(P130="Norte",Q130*1.6,IF(P130="Occidente",Q130*1.2,IF(P130="Sur",Q130*2)))) -> FALSE | S130: =VLOOKUP(E130,Tabla_Instalacion,2,FALSE) -> #N/A | T130: =IF(P130="Centro",S130,IF(P130="Norte",S130*1.1,IF(P130="Occidente",S130*1.1,IF(P130="Sur",S130*1.1)))) -> FALSE | U130: =IF(F130="Offiho",0,Q130+S130) -> #N/A | V130: =IF(K130=0,U130/$H$573,U130*(K130/L130))*H130 -> #N/A | W130: =IF(F130="Offiho",J130,IF(_xlfn.XLOOKUP(F130,Proveedores!A$2:A$50,Proveedores!E$2:E$50,"")="Nacional",(J130/0.5)+(V130*H130),((J130/0.3/0.5)+(V130*H130)))) -> #N/A | X130: =W130*H130 -> #N/A | Y130: =IF(F130="Sunon Inc",$AJ$577,IF(F130="Alma - Exterior",$AJ$578,IF(F130="Yabo - Hotelería",$AJ$579,IF(F130="OSJ - Medical",$AJ$580,IF(F130="Seezo - Home",$AJ$581,IF(F130="A&D - Home",$AJ$582,IF(F130="Encore Alfombras Hoteleria Asia",$AJ$583,IF(F130="Zhong Xian - Leds",$AJ$584,IF(F130="Tarkett Europa",$AJ$585,IF(F130="2tec2",$AJ$586,IF(F130="Balsan Europa",$AJ$587,IF(F130="Armstrong Pisos USA",$AJ$588,IF(F130="Tarkett USA",$AJ$589,IF(F130="Tarkett Brasil",$AJ$590,IF(F130="Tarkett MX",$AJ$591,IF(F130="Jome",$AJ$592,IF(F130="Offiho",$AJ$593,IF(F130="Lumbro",$AJ$594,IF(F130="Sunon Mty",$AJ$595,IF(F130="Conceptos Sofas",$AJ$596,IF(F130="Lauco Sofas",$AJ$597,IF(F130="CR Global - Mesas Ajustables",$AJ$598,IF(F130="Vandesk",$AJ$599,IF(F130="Mamparas Tela",$AJ$600,IF(F130="Mampara Cristales",$AJ$601,IF(F130="Herrajes",$AJ$602,IF(F130="MetalWork",$AJ$603,IF(F130="Requiez",$AJ$604,IF(F130="Labenze",$AJ$605,IF(F130="Infinity",$AJ$606,IF(F130="Proveedor Externo",$AJ$607))))))))))))))))))))))))))))))) -> FALSE | Z130: 0 | AA130: =W130*Z130 -> #N/A | AB130: =IF(Z130>Y130,"ERROR",(W130-AA130)) -> #N/A | AC130: =AB130*H130 -> #N/A | AD130: =IF(A131=TRUE,MAX(0,1-(AE130/W130)),"NA") -> #N/A | AE130: =IF(A129=FALSE,"NO APLICA",AB130*1.2) -> #N/A | AF130: =AE130*H130 -> #N/A | AG130: =(AC130-N130)/AC130 -> #N/A | AH130: =IF(AG130<30%,"ERROR","OK") -> #N/A
A131: =$A$13 -> TRUE | B131: =A131 -> TRUE | C131: =$C$13 -> Dólares | G131: =IFERROR(VLOOKUP(F131,Tabla_Proveedores_1,2,0)," ") | H131: 0 | I131: =IFERROR(VLOOKUP(G131,Proveedores!B:C,2,0)," ") | J131: 0 | L131: =K131*H131 -> 0 | M131: =IF(F131="Offiho", J131*0.55, IF(AND(F131<>"Sunon Inc",F131<>"Alma - Exterior",F131<>"Yabo - Hotelería",F131<>"OSJ - Medical",F131<>"Seezo - Home",F131<>"A&D -Home",F131<>"Encore Alfombras Hoteleria Asia",F131<>"Zhong Xian - Leds",F131<>"Tarkett Europa",F131<>"2tec2",F131<>"Balsan Europa",F131<>"Armstrong Pisos USA",F131<>"Tarkett USA",F131<>"Tarkett Brasil"),J131,IFERROR(IF(K690<=$AO$578,J131*2.14,IF(K690<=$AN$579,J131*1.8,IF(K690>$AN$580,J131*1.5))),J131))*1.1) -> 0 | N131: =M131*H131 -> 0 | O131: =IFERROR(VLOOKUP(G131,Proveedores!B:D,3,0)," ") | Q131: =VLOOKUP(E131,Tabla_Fletes,3,FALSE) -> #N/A | R131: =IF(P131="Centro",Q131,IF(P131="Norte",Q131*1.6,IF(P131="Occidente",Q131*1.2,IF(P131="Sur",Q131*2)))) -> FALSE | S131: =VLOOKUP(E131,Tabla_Instalacion,2,FALSE) -> #N/A | T131: =IF(P131="Centro",S131,IF(P131="Norte",S131*1.1,IF(P131="Occidente",S131*1.1,IF(P131="Sur",S131*1.1)))) -> FALSE | U131: =IF(F131="Offiho",0,Q131+S131) -> #N/A | V131: =IF(K131=0,U131/$H$573,U131*(K131/L131))*H131 -> #N/A | W131: =IF(F131="Offiho",J131,IF(_xlfn.XLOOKUP(F131,Proveedores!A$2:A$50,Proveedores!E$2:E$50,"")="Nacional",(J131/0.5)+(V131*H131),((J131/0.3/0.5)+(V131*H131)))) -> #N/A | X131: =W131*H131 -> #N/A | Y131: =IF(F131="Sunon Inc",$AJ$577,IF(F131="Alma - Exterior",$AJ$578,IF(F131="Yabo - Hotelería",$AJ$579,IF(F131="OSJ - Medical",$AJ$580,IF(F131="Seezo - Home",$AJ$581,IF(F131="A&D - Home",$AJ$582,IF(F131="Encore Alfombras Hoteleria Asia",$AJ$583,IF(F131="Zhong Xian - Leds",$AJ$584,IF(F131="Tarkett Europa",$AJ$585,IF(F131="2tec2",$AJ$586,IF(F131="Balsan Europa",$AJ$587,IF(F131="Armstrong Pisos USA",$AJ$588,IF(F131="Tarkett USA",$AJ$589,IF(F131="Tarkett Brasil",$AJ$590,IF(F131="Tarkett MX",$AJ$591,IF(F131="Jome",$AJ$592,IF(F131="Offiho",$AJ$593,IF(F131="Lumbro",$AJ$594,IF(F131="Sunon Mty",$AJ$595,IF(F131="Conceptos Sofas",$AJ$596,IF(F131="Lauco Sofas",$AJ$597,IF(F131="CR Global - Mesas Ajustables",$AJ$598,IF(F131="Vandesk",$AJ$599,IF(F131="Mamparas Tela",$AJ$600,IF(F131="Mampara Cristales",$AJ$601,IF(F131="Herrajes",$AJ$602,IF(F131="MetalWork",$AJ$603,IF(F131="Requiez",$AJ$604,IF(F131="Labenze",$AJ$605,IF(F131="Infinity",$AJ$606,IF(F131="Proveedor Externo",$AJ$607))))))))))))))))))))))))))))))) -> FALSE | Z131: 0 | AA131: =W131*Z131 -> #N/A | AB131: =IF(Z131>Y131,"ERROR",(W131-AA131)) -> #N/A | AC131: =AB131*H131 -> #N/A | AD131: =IF(A132=TRUE,MAX(0,1-(AE131/W131)),"NA") -> #N/A | AE131: =IF(A130=FALSE,"NO APLICA",AB131*1.2) -> #N/A | AF131: =AE131*H131 -> #N/A | AG131: =(AC131-N131)/AC131 -> #N/A | AH131: =IF(AG131<30%,"ERROR","OK") -> #N/A
A132: =$A$13 -> TRUE | B132: =A132 -> TRUE | C132: =$C$13 -> Dólares | G132: =IFERROR(VLOOKUP(F132,Tabla_Proveedores_1,2,0)," ") | H132: 0 | I132: =IFERROR(VLOOKUP(G132,Proveedores!B:C,2,0)," ") | J132: 0 | L132: =K132*H132 -> 0 | M132: =IF(F132="Offiho", J132*0.55, IF(AND(F132<>"Sunon Inc",F132<>"Alma - Exterior",F132<>"Yabo - Hotelería",F132<>"OSJ - Medical",F132<>"Seezo - Home",F132<>"A&D -Home",F132<>"Encore Alfombras Hoteleria Asia",F132<>"Zhong Xian - Leds",F132<>"Tarkett Europa",F132<>"2tec2",F132<>"Balsan Europa",F132<>"Armstrong Pisos USA",F132<>"Tarkett USA",F132<>"Tarkett Brasil"),J132,IFERROR(IF(K691<=$AO$578,J132*2.14,IF(K691<=$AN$579,J132*1.8,IF(K691>$AN$580,J132*1.5))),J132))*1.1) -> 0 | N132: =M132*H132 -> 0 | O132: =IFERROR(VLOOKUP(G132,Proveedores!B:D,3,0)," ") | Q132: =VLOOKUP(E132,Tabla_Fletes,3,FALSE) -> #N/A | R132: =IF(P132="Centro",Q132,IF(P132="Norte",Q132*1.6,IF(P132="Occidente",Q132*1.2,IF(P132="Sur",Q132*2)))) -> FALSE | S132: =VLOOKUP(E132,Tabla_Instalacion,2,FALSE) -> #N/A | T132: =IF(P132="Centro",S132,IF(P132="Norte",S132*1.1,IF(P132="Occidente",S132*1.1,IF(P132="Sur",S132*1.1)))) -> FALSE | U132: =IF(F132="Offiho",0,Q132+S132) -> #N/A | V132: =IF(K132=0,U132/$H$573,U132*(K132/L132))*H132 -> #N/A | W132: =IF(F132="Offiho",J132,IF(_xlfn.XLOOKUP(F132,Proveedores!A$2:A$50,Proveedores!E$2:E$50,"")="Nacional",(J132/0.5)+(V132*H132),((J132/0.3/0.5)+(V132*H132)))) -> #N/A | X132: =W132*H132 -> #N/A | Y132: =IF(F132="Sunon Inc",$AJ$577,IF(F132="Alma - Exterior",$AJ$578,IF(F132="Yabo - Hotelería",$AJ$579,IF(F132="OSJ - Medical",$AJ$580,IF(F132="Seezo - Home",$AJ$581,IF(F132="A&D - Home",$AJ$582,IF(F132="Encore Alfombras Hoteleria Asia",$AJ$583,IF(F132="Zhong Xian - Leds",$AJ$584,IF(F132="Tarkett Europa",$AJ$585,IF(F132="2tec2",$AJ$586,IF(F132="Balsan Europa",$AJ$587,IF(F132="Armstrong Pisos USA",$AJ$588,IF(F132="Tarkett USA",$AJ$589,IF(F132="Tarkett Brasil",$AJ$590,IF(F132="Tarkett MX",$AJ$591,IF(F132="Jome",$AJ$592,IF(F132="Offiho",$AJ$593,IF(F132="Lumbro",$AJ$594,IF(F132="Sunon Mty",$AJ$595,IF(F132="Conceptos Sofas",$AJ$596,IF(F132="Lauco Sofas",$AJ$597,IF(F132="CR Global - Mesas Ajustables",$AJ$598,IF(F132="Vandesk",$AJ$599,IF(F132="Mamparas Tela",$AJ$600,IF(F132="Mampara Cristales",$AJ$601,IF(F132="Herrajes",$AJ$602,IF(F132="MetalWork",$AJ$603,IF(F132="Requiez",$AJ$604,IF(F132="Labenze",$AJ$605,IF(F132="Infinity",$AJ$606,IF(F132="Proveedor Externo",$AJ$607))))))))))))))))))))))))))))))) -> FALSE | Z132: 0 | AA132: =W132*Z132 -> #N/A | AB132: =IF(Z132>Y132,"ERROR",(W132-AA132)) -> #N/A | AC132: =AB132*H132 -> #N/A | AD132: =IF(A133=TRUE,MAX(0,1-(AE132/W132)),"NA") -> #N/A | AE132: =IF(A131=FALSE,"NO APLICA",AB132*1.2) -> #N/A | AF132: =AE132*H132 -> #N/A | AG132: =(AC132-N132)/AC132 -> #N/A | AH132: =IF(AG132<30%,"ERROR","OK") -> #N/A
A133: =$A$13 -> TRUE | B133: =A133 -> TRUE | C133: =$C$13 -> Dólares | G133: =IFERROR(VLOOKUP(F133,Tabla_Proveedores_1,2,0)," ") | H133: 0 | I133: =IFERROR(VLOOKUP(G133,Proveedores!B:C,2,0)," ") | J133: 0 | L133: =K133*H133 -> 0 | M133: =IF(F133="Offiho", J133*0.55, IF(AND(F133<>"Sunon Inc",F133<>"Alma - Exterior",F133<>"Yabo - Hotelería",F133<>"OSJ - Medical",F133<>"Seezo - Home",F133<>"A&D -Home",F133<>"Encore Alfombras Hoteleria Asia",F133<>"Zhong Xian - Leds",F133<>"Tarkett Europa",F133<>"2tec2",F133<>"Balsan Europa",F133<>"Armstrong Pisos USA",F133<>"Tarkett USA",F133<>"Tarkett Brasil"),J133,IFERROR(IF(K692<=$AO$578,J133*2.14,IF(K692<=$AN$579,J133*1.8,IF(K692>$AN$580,J133*1.5))),J133))*1.1) -> 0 | N133: =M133*H133 -> 0 | O133: =IFERROR(VLOOKUP(G133,Proveedores!B:D,3,0)," ") | Q133: =VLOOKUP(E133,Tabla_Fletes,3,FALSE) -> #N/A | R133: =IF(P133="Centro",Q133,IF(P133="Norte",Q133*1.6,IF(P133="Occidente",Q133*1.2,IF(P133="Sur",Q133*2)))) -> FALSE | S133: =VLOOKUP(E133,Tabla_Instalacion,2,FALSE) -> #N/A | T133: =IF(P133="Centro",S133,IF(P133="Norte",S133*1.1,IF(P133="Occidente",S133*1.1,IF(P133="Sur",S133*1.1)))) -> FALSE | U133: =IF(F133="Offiho",0,Q133+S133) -> #N/A | V133: =IF(K133=0,U133/$H$573,U133*(K133/L133))*H133 -> #N/A | W133: =IF(F133="Offiho",J133,IF(_xlfn.XLOOKUP(F133,Proveedores!A$2:A$50,Proveedores!E$2:E$50,"")="Nacional",(J133/0.5)+(V133*H133),((J133/0.3/0.5)+(V133*H133)))) -> #N/A | X133: =W133*H133 -> #N/A | Y133: =IF(F133="Sunon Inc",$AJ$577,IF(F133="Alma - Exterior",$AJ$578,IF(F133="Yabo - Hotelería",$AJ$579,IF(F133="OSJ - Medical",$AJ$580,IF(F133="Seezo - Home",$AJ$581,IF(F133="A&D - Home",$AJ$582,IF(F133="Encore Alfombras Hoteleria Asia",$AJ$583,IF(F133="Zhong Xian - Leds",$AJ$584,IF(F133="Tarkett Europa",$AJ$585,IF(F133="2tec2",$AJ$586,IF(F133="Balsan Europa",$AJ$587,IF(F133="Armstrong Pisos USA",$AJ$588,IF(F133="Tarkett USA",$AJ$589,IF(F133="Tarkett Brasil",$AJ$590,IF(F133="Tarkett MX",$AJ$591,IF(F133="Jome",$AJ$592,IF(F133="Offiho",$AJ$593,IF(F133="Lumbro",$AJ$594,IF(F133="Sunon Mty",$AJ$595,IF(F133="Conceptos Sofas",$AJ$596,IF(F133="Lauco Sofas",$AJ$597,IF(F133="CR Global - Mesas Ajustables",$AJ$598,IF(F133="Vandesk",$AJ$599,IF(F133="Mamparas Tela",$AJ$600,IF(F133="Mampara Cristales",$AJ$601,IF(F133="Herrajes",$AJ$602,IF(F133="MetalWork",$AJ$603,IF(F133="Requiez",$AJ$604,IF(F133="Labenze",$AJ$605,IF(F133="Infinity",$AJ$606,IF(F133="Proveedor Externo",$AJ$607))))))))))))))))))))))))))))))) -> FALSE | Z133: 0 | AA133: =W133*Z133 -> #N/A | AB133: =IF(Z133>Y133,"ERROR",(W133-AA133)) -> #N/A | AC133: =AB133*H133 -> #N/A | AD133: =IF(A134=TRUE,MAX(0,1-(AE133/W133)),"NA") -> #N/A | AE133: =IF(A132=FALSE,"NO APLICA",AB133*1.2) -> #N/A | AF133: =AE133*H133 -> #N/A | AG133: =(AC133-N133)/AC133 -> #N/A | AH133: =IF(AG133<30%,"ERROR","OK") -> #N/A
... A151: =$A$13 -> TRUE | B151: =A151 -> TRUE | C151: =$C$13 -> Dólares | G151: =IFERROR(VLOOKUP(F151,Tabla_Proveedores_1,2,0)," ") | H151: 0 | I151: =IFERROR(VLOOKUP(G151,Proveedores!B:C,2,0)," ") | J151: 0 | L151: =K151*H151 -> 0 | M151: =IF(F151="Offiho", J151*0.55, IF(AND(F151<>"Sunon Inc",F151<>"Alma - Exterior",F151<>"Yabo - Hotelería",F151<>"OSJ - Medical",F151<>"Seezo - Home",F151<>"A&D -Home",F151<>"Encore Alfombras Hoteleria Asia",F151<>"Zhong Xian - Leds",F151<>"Tarkett Europa",F151<>"2tec2",F151<>"Balsan Europa",F151<>"Armstrong Pisos USA",F151<>"Tarkett USA",F151<>"Tarkett Brasil"),J151,IFERROR(IF(K710<=$AO$578,J151*2.14,IF(K710<=$AN$579,J151*1.8,IF(K710>$AN$580,J151*1.5))),J151))*1.1) -> 0 | N151: =M151*H151 -> 0 | O151: =IFERROR(VLOOKUP(G151,Proveedores!B:D,3,0)," ") | Q151: =VLOOKUP(E151,Tabla_Fletes,3,FALSE) -> #N/A | R151: =IF(P151="Centro",Q151,IF(P151="Norte",Q151*1.6,IF(P151="Occidente",Q151*1.2,IF(P151="Sur",Q151*2)))) -> FALSE | S151: =VLOOKUP(E151,Tabla_Instalacion,2,FALSE) -> #N/A | T151: =IF(P151="Centro",S151,IF(P151="Norte",S151*1.1,IF(P151="Occidente",S151*1.1,IF(P151="Sur",S151*1.1)))) -> FALSE | U151: =IF(F151="Offiho",0,Q151+S151) -> #N/A | V151: =IF(K151=0,U151/$H$573,U151*(K151/L151))*H151 -> #N/A | W151: =IF(F151="Offiho",J151,IF(_xlfn.XLOOKUP(F151,Proveedores!A$2:A$50,Proveedores!E$2:E$50,"")="Nacional",(J151/0.5)+(V151*H151),((J151/0.3/0.5)+(V151*H151)))) -> #N/A | X151: =W151*H151 -> #N/A | Y151: =IF(F151="Sunon Inc",$AJ$577,IF(F151="Alma - Exterior",$AJ$578,IF(F151="Yabo - Hotelería",$AJ$579,IF(F151="OSJ - Medical",$AJ$580,IF(F151="Seezo - Home",$AJ$581,IF(F151="A&D - Home",$AJ$582,IF(F151="Encore Alfombras Hoteleria Asia",$AJ$583,IF(F151="Zhong Xian - Leds",$AJ$584,IF(F151="Tarkett Europa",$AJ$585,IF(F151="2tec2",$AJ$586,IF(F151="Balsan Europa",$AJ$587,IF(F151="Armstrong Pisos USA",$AJ$588,IF(F151="Tarkett USA",$AJ$589,IF(F151="Tarkett Brasil",$AJ$590,IF(F151="Tarkett MX",$AJ$591,IF(F151="Jome",$AJ$592,IF(F151="Offiho",$AJ$593,IF(F151="Lumbro",$AJ$594,IF(F151="Sunon Mty",$AJ$595,IF(F151="Conceptos Sofas",$AJ$596,IF(F151="Lauco Sofas",$AJ$597,IF(F151="CR Global - Mesas Ajustables",$AJ$598,IF(F151="Vandesk",$AJ$599,IF(F151="Mamparas Tela",$AJ$600,IF(F151="Mampara Cristales",$AJ$601,IF(F151="Herrajes",$AJ$602,IF(F151="MetalWork",$AJ$603,IF(F151="Requiez",$AJ$604,IF(F151="Labenze",$AJ$605,IF(F151="Infinity",$AJ$606,IF(F151="Proveedor Externo",$AJ$607))))))))))))))))))))))))))))))) -> FALSE | Z151: 0 | AA151: =W151*Z151 -> #N/A | AB151: =IF(Z151>Y151,"ERROR",(W151-AA151)) -> #N/A | AC151: =AB151*H151 -> #N/A | AD151: =IF(A152=TRUE,MAX(0,1-(AE151/W151)),"NA") -> NA | AE151: =IF(A150=FALSE,"NO APLICA",AB151*1.2) -> #N/A | AF151: =AE151*H151 -> #N/A | AG151: =(AC151-N151)/AC151 -> #N/A | AH151: =IF(AG151<30%,"ERROR","OK") -> #N/A
A152: Subtotales Sección 4 | H152: {=SUM(IFERROR(H119:H151,0))} -> 0 | L152: {=SUM(IFERROR(L119:L151,0))} -> 0 | N152: {=SUM(IFERROR(N119:N151,0))} -> 0 | X152: {=SUM(IFERROR(X119:X151,0))} -> 0 | AC152: {=SUM(IFERROR(AC119:AC151,0))} -> 0 | AF152: {=SUM(IFERROR(AF119:AF151,0))} -> 0 | AG152: =IFERROR(1-(N152/AC152),0) -> 0
A153: Sección 5 - NOMBRE
A154: =$A$13 -> TRUE | B154: =A154 -> TRUE | C154: =$C$13 -> Dólares | G154: =IFERROR(VLOOKUP(F154,Tabla_Proveedores_1,2,0)," ") | H154: 0 | I154: =IFERROR(VLOOKUP(G154,Proveedores!B:C,2,0)," ") | J154: 0 | L154: =K154*H154 -> 0 | M154: =IF(F154="Offiho", J154*0.55, IF(AND(F154<>"Sunon Inc",F154<>"Alma - Exterior",F154<>"Yabo - Hotelería",F154<>"OSJ - Medical",F154<>"Seezo - Home",F154<>"A&D -Home",F154<>"Encore Alfombras Hoteleria Asia",F154<>"Zhong Xian - Leds",F154<>"Tarkett Europa",F154<>"2tec2",F154<>"Balsan Europa",F154<>"Armstrong Pisos USA",F154<>"Tarkett USA",F154<>"Tarkett Brasil"),J154,IFERROR(IF(K713<=$AO$578,J154*2.14,IF(K713<=$AN$579,J154*1.8,IF(K713>$AN$580,J154*1.5))),J154))*1.1) -> 0 | N154: =M154*H154 -> 0 | O154: =IFERROR(VLOOKUP(G154,Proveedores!B:D,3,0)," ") | Q154: =VLOOKUP(E154,Tabla_Fletes,3,FALSE) -> #N/A | R154: =IF(P154="Centro",Q154,IF(P154="Norte",Q154*1.6,IF(P154="Occidente",Q154*1.2,IF(P154="Sur",Q154*2)))) -> FALSE | S154: =VLOOKUP(E154,Tabla_Instalacion,2,FALSE) -> #N/A | T154: =IF(P154="Centro",S154,IF(P154="Norte",S154*1.1,IF(P154="Occidente",S154*1.1,IF(P154="Sur",S154*1.1)))) -> FALSE | U154: =IF(F154="Offiho",0,Q154+S154) -> #N/A | V154: =IF(K154=0,U154/$H$573,U154*(K154/L154))*H154 -> #N/A | W154: =IF(F154="Offiho",J154,IF(_xlfn.XLOOKUP(F154,Proveedores!A$2:A$50,Proveedores!E$2:E$50,"")="Nacional",(J154/0.5)+(V154*H154),((J154/0.3/0.5)+(V154*H154)))) -> #N/A | X154: =W154*H154 -> #N/A | Y154: =IF(F154="Sunon Inc",$AJ$577,IF(F154="Alma - Exterior",$AJ$578,IF(F154="Yabo - Hotelería",$AJ$579,IF(F154="OSJ - Medical",$AJ$580,IF(F154="Seezo - Home",$AJ$581,IF(F154="A&D - Home",$AJ$582,IF(F154="Encore Alfombras Hoteleria Asia",$AJ$583,IF(F154="Zhong Xian - Leds",$AJ$584,IF(F154="Tarkett Europa",$AJ$585,IF(F154="2tec2",$AJ$586,IF(F154="Balsan Europa",$AJ$587,IF(F154="Armstrong Pisos USA",$AJ$588,IF(F154="Tarkett USA",$AJ$589,IF(F154="Tarkett Brasil",$AJ$590,IF(F154="Tarkett MX",$AJ$591,IF(F154="Jome",$AJ$592,IF(F154="Offiho",$AJ$593,IF(F154="Lumbro",$AJ$594,IF(F154="Sunon Mty",$AJ$595,IF(F154="Conceptos Sofas",$AJ$596,IF(F154="Lauco Sofas",$AJ$597,IF(F154="CR Global - Mesas Ajustables",$AJ$598,IF(F154="Vandesk",$AJ$599,IF(F154="Mamparas Tela",$AJ$600,IF(F154="Mampara Cristales",$AJ$601,IF(F154="Herrajes",$AJ$602,IF(F154="MetalWork",$AJ$603,IF(F154="Requiez",$AJ$604,IF(F154="Labenze",$AJ$605,IF(F154="Infinity",$AJ$606,IF(F154="Proveedor Externo",$AJ$607))))))))))))))))))))))))))))))) -> FALSE | Z154: 0.2 | AA154: =W154*Z154 -> #N/A | AB154: =IF(Z154>Y154,"ERROR",(W154-AA154)) -> #N/A | AC154: =AB154*H154 -> #N/A | AD154: =IF(A155=TRUE,MAX(0,1-(AE154/W154)),"NA") -> #N/A | AE154: =IF(A153=FALSE,"NO APLICA",AB154*1.2) -> #N/A | AF154: =AE154*H154 -> #N/A | AG154: =(AC154-N154)/AC154 -> #N/A | AH154: =IF(AG154<30%,"ERROR","OK") -> #N/A
